Workbook

Sheet Haq — Monthly P&L and cash
A1: Haq — Monthly P&L and cash
A2: Haq — Monthly plan · Main Scenario
A4: Variable / dimension | B4: 2026-11 | C4: 2026-12 | D4: 2027-01 | E4: 2027-02 | F4: 2027-03 | G4: 2027-04 | H4: 2027-05 | I4: 2027-06 | J4: 2027-07 | K4: 2027-08 | L4: 2027-09 | M4: 2027-10 | N4: 2027-11 | O4: 2027-12 | P4: 2028-01 | Q4: 2028-02 | R4: 2028-03 | S4: 2028-04 | T4: 2028-05 | U4: 2028-06 | V4: 2028-07 | W4: 2028-08 | X4: 2028-09 | Y4: 2028-10
A5: Haq month | B5: =(YEAR(DATE(2026,11,1))-2026)*12+MONTH(DATE(2026,11,1))-10 -> 1 | C5: =(YEAR(DATE(2026,12,1))-2026)*12+MONTH(DATE(2026,12,1))-10 -> 2 | D5: =(YEAR(DATE(2027,1,1))-2026)*12+MONTH(DATE(2027,1,1))-10 -> 3 | E5: =(YEAR(DATE(2027,2,1))-2026)*12+MONTH(DATE(2027,2,1))-10 -> 4 | F5: =(YEAR(DATE(2027,3,1))-2026)*12+MONTH(DATE(2027,3,1))-10 -> 5 | G5: =(YEAR(DATE(2027,4,1))-2026)*12+MONTH(DATE(2027,4,1))-10 -> 6 | H5: =(YEAR(DATE(2027,5,1))-2026)*12+MONTH(DATE(2027,5,1))-10 -> 7 | I5: =(YEAR(DATE(2027,6,1))-2026)*12+MONTH(DATE(2027,6,1))-10 -> 8 | J5: =(YEAR(DATE(2027,7,1))-2026)*12+MONTH(DATE(2027,7,1))-10 -> 9 | K5: =(YEAR(DATE(2027,8,1))-2026)*12+MONTH(DATE(2027,8,1))-10 -> 10 | L5: =(YEAR(DATE(2027,9,1))-2026)*12+MONTH(DATE(2027,9,1))-10 -> 11 | M5: =(YEAR(DATE(2027,10,1))-2026)*12+MONTH(DATE(2027,10,1))-10 -> 12 | N5: =(YEAR(DATE(2027,11,1))-2026)*12+MONTH(DATE(2027,11,1))-10 -> 13 | O5: =(YEAR(DATE(2027,12,1))-2026)*12+MONTH(DATE(2027,12,1))-10 -> 14 | P5: =(YEAR(DATE(2028,1,1))-2026)*12+MONTH(DATE(2028,1,1))-10 -> 15 | Q5: =(YEAR(DATE(2028,2,1))-2026)*12+MONTH(DATE(2028,2,1))-10 -> 16 | R5: =(YEAR(DATE(2028,3,1))-2026)*12+MONTH(DATE(2028,3,1))-10 -> 17 | S5: =(YEAR(DATE(2028,4,1))-2026)*12+MONTH(DATE(2028,4,1))-10 -> 18 | T5: =(YEAR(DATE(2028,5,1))-2026)*12+MONTH(DATE(2028,5,1))-10 -> 19 | U5: =(YEAR(DATE(2028,6,1))-2026)*12+MONTH(DATE(2028,6,1))-10 -> 20 | V5: =(YEAR(DATE(2028,7,1))-2026)*12+MONTH(DATE(2028,7,1))-10 -> 21 | W5: =(YEAR(DATE(2028,8,1))-2026)*12+MONTH(DATE(2028,8,1))-10 -> 22 | X5: =(YEAR(DATE(2028,9,1))-2026)*12+MONTH(DATE(2028,9,1))-10 -> 23 | Y5: =(YEAR(DATE(2028,10,1))-2026)*12+MONTH(DATE(2028,10,1))-10 -> 24
A6: Haq check cost | B6: =IF(IF(IF(ISERROR('Haq — Monthly P&L and cash'!B5<'Model inputs'!AJ54),'Haq — Monthly P&L and cash'!B5<'Model inputs'!AJ54,IF(OR('Haq — Monthly P&L and cash'!B5="",'Model inputs'!AJ54=""),"",'Haq — Monthly P&L and cash'!B5<'Model inputs'!AJ54))="",FALSE,IF(ISERROR('Haq — Monthly P&L and cash'!B5<'Model inputs'!AJ54),'Haq — Monthly P&L and cash'!B5<'Model inputs'!AJ54,IF(OR('Haq — Monthly P&L and cash'!B5="",'Model inputs'!AJ54=""),"",'Haq — Monthly P&L and cash'!B5<'Model inputs'!AJ54))),IF('Model inputs'!AJ87="","",'Model inputs'!AJ87),IF(IF(IF(ISERROR('Haq — Monthly P&L and cash'!B5<'Model inputs'!AJ84),'Haq — Monthly P&L and cash'!B5<'Model inputs'!AJ84,IF(OR('Haq — Monthly P&L and cash'!B5="",'Model inputs'!AJ84=""),"",'Haq — Monthly P&L and cash'!B5<'Model inputs'!AJ84))="",FALSE,IF(ISERROR('Haq — Monthly P&L and cash'!B5<'Model inputs'!AJ84),'Haq — Monthly P&L and cash'!B5<'Model inputs'!AJ84,IF(OR('Haq — Monthly P&L and cash'!B5="",'Model inputs'!AJ84=""),"",'Haq — Monthly P&L and cash'!B5<'Model inputs'!AJ84))),IF('Model inputs'!AJ55="","",'Model inputs'!AJ55),IF('Model inputs'!AJ85="","",'Model inputs'!AJ85))) -> 20 | C6: =IF(IF(IF(ISERROR('Haq — Monthly P&L and cash'!C5<'Model inputs'!AJ54),'Haq — Monthly P&L and cash'!C5<'Model inputs'!AJ54,IF(OR('Haq — Monthly P&L and cash'!C5="",'Model inputs'!AJ54=""),"",'Haq — Monthly P&L and cash'!C5<'Model inputs'!AJ54))="",FALSE,IF(ISERROR('Haq — Monthly P&L and cash'!C5<'Model inputs'!AJ54),'Haq — Monthly P&L and cash'!C5<'Model inputs'!AJ54,IF(OR('Haq — Monthly P&L and cash'!C5="",'Model inputs'!AJ54=""),"",'Haq — Monthly P&L and cash'!C5<'Model inputs'!AJ54))),IF('Model inputs'!AJ87="","",'Model inputs'!AJ87),IF(IF(IF(ISERROR('Haq — Monthly P&L and cash'!C5<'Model inputs'!AJ84),'Haq — Monthly P&L and cash'!C5<'Model inputs'!AJ84,IF(OR('Haq — Monthly P&L and cash'!C5="",'Model inputs'!AJ84=""),"",'Haq — Monthly P&L and cash'!C5<'Model inputs'!AJ84))="",FALSE,IF(ISERROR('Haq — Monthly P&L and cash'!C5<'Model inputs'!AJ84),'Haq — Monthly P&L and cash'!C5<'Model inputs'!AJ84,IF(OR('Haq — Monthly P&L and cash'!C5="",'Model inputs'!AJ84=""),"",'Haq — Monthly P&L and cash'!C5<'Model inputs'!AJ84))),IF('Model inputs'!AJ55="","",'Model inputs'!AJ55),IF('Model inputs'!AJ85="","",'Model inputs'!AJ85))) -> 20 | D6: =IF(IF(IF(ISERROR('Haq — Monthly P&L and cash'!D5<'Model inputs'!AJ54),'Haq — Monthly P&L and cash'!D5<'Model inputs'!AJ54,IF(OR('Haq — Monthly P&L and cash'!D5="",'Model inputs'!AJ54=""),"",'Haq — Monthly P&L and cash'!D5<'Model inputs'!AJ54))="",FALSE,IF(ISERROR('Haq — Monthly P&L and cash'!D5<'Model inputs'!AJ54),'Haq — Monthly P&L and cash'!D5<'Model inputs'!AJ54,IF(OR('Haq — Monthly P&L and cash'!D5="",'Model inputs'!AJ54=""),"",'Haq — Monthly P&L and cash'!D5<'Model inputs'!AJ54))),IF('Model inputs'!AJ87="","",'Model inputs'!AJ87),IF(IF(IF(ISERROR('Haq — Monthly P&L and cash'!D5<'Model inputs'!AJ84),'Haq — Monthly P&L and cash'!D5<'Model inputs'!AJ84,IF(OR('Haq — Monthly P&L and cash'!D5="",'Model inputs'!AJ84=""),"",'Haq — Monthly P&L and cash'!D5<'Model inputs'!AJ84))="",FALSE,IF(ISERROR('Haq — Monthly P&L and cash'!D5<'Model inputs'!AJ84),'Haq — Monthly P&L and cash'!D5<'Model inputs'!AJ84,IF(OR('Haq — Monthly P&L and cash'!D5="",'Model inputs'!AJ84=""),"",'Haq — Monthly P&L and cash'!D5<'Model inputs'!AJ84))),IF('Model inputs'!AJ55="","",'Model inputs'!AJ55),IF('Model inputs'!AJ85="","",'Model inputs'!AJ85))) -> 20 | E6: =IF(IF(IF(ISERROR('Haq — Monthly P&L and cash'!E5<'Model inputs'!AJ54),'Haq — Monthly P&L and cash'!E5<'Model inputs'!AJ54,IF(OR('Haq — Monthly P&L and cash'!E5="",'Model inputs'!AJ54=""),"",'Haq — Monthly P&L and cash'!E5<'Model inputs'!AJ54))="",FALSE,IF(ISERROR('Haq — Monthly P&L and cash'!E5<'Model inputs'!AJ54),'Haq — Monthly P&L and cash'!E5<'Model inputs'!AJ54,IF(OR('Haq — Monthly P&L and cash'!E5="",'Model inputs'!AJ54=""),"",'Haq — Monthly P&L and cash'!E5<'Model inputs'!AJ54))),IF('Model inputs'!AJ87="","",'Model inputs'!AJ87),IF(IF(IF(ISERROR('Haq — Monthly P&L and cash'!E5<'Model inputs'!AJ84),'Haq — Monthly P&L and cash'!E5<'Model inputs'!AJ84,IF(OR('Haq — Monthly P&L and cash'!E5="",'Model inputs'!AJ84=""),"",'Haq — Monthly P&L and cash'!E5<'Model inputs'!AJ84))="",FALSE,IF(ISERROR('Haq — Monthly P&L and cash'!E5<'Model inputs'!AJ84),'Haq — Monthly P&L and cash'!E5<'Model inputs'!AJ84,IF(OR('Haq — Monthly P&L and cash'!E5="",'Model inputs'!AJ84=""),"",'Haq — Monthly P&L and cash'!E5<'Model inputs'!AJ84))),IF('Model inputs'!AJ55="","",'Model inputs'!AJ55),IF('Model inputs'!AJ85="","",'Model inputs'!AJ85))) -> 10 | F6: =IF(IF(IF(ISERROR('Haq — Monthly P&L and cash'!F5<'Model inputs'!AJ54),'Haq — Monthly P&L and cash'!F5<'Model inputs'!AJ54,IF(OR('Haq — Monthly P&L and cash'!F5="",'Model inputs'!AJ54=""),"",'Haq — Monthly P&L and cash'!F5<'Model inputs'!AJ54))="",FALSE,IF(ISERROR('Haq — Monthly P&L and cash'!F5<'Model inputs'!AJ54),'Haq — Monthly P&L and cash'!F5<'Model inputs'!AJ54,IF(OR('Haq — Monthly P&L and cash'!F5="",'Model inputs'!AJ54=""),"",'Haq — Monthly P&L and cash'!F5<'Model inputs'!AJ54))),IF('Model inputs'!AJ87="","",'Model inputs'!AJ87),IF(IF(IF(ISERROR('Haq — Monthly P&L and cash'!F5<'Model inputs'!AJ84),'Haq — Monthly P&L and cash'!F5<'Model inputs'!AJ84,IF(OR('Haq — Monthly P&L and cash'!F5="",'Model inputs'!AJ84=""),"",'Haq — Monthly P&L and cash'!F5<'Model inputs'!AJ84))="",FALSE,IF(ISERROR('Haq — Monthly P&L and cash'!F5<'Model inputs'!AJ84),'Haq — Monthly P&L and cash'!F5<'Model inputs'!AJ84,IF(OR('Haq — Monthly P&L and cash'!F5="",'Model inputs'!AJ84=""),"",'Haq — Monthly P&L and cash'!F5<'Model inputs'!AJ84))),IF('Model inputs'!AJ55="","",'Model inputs'!AJ55),IF('Model inputs'!AJ85="","",'Model inputs'!AJ85))) -> 10 | G6: =IF(IF(IF(ISERROR('Haq — Monthly P&L and cash'!G5<'Model inputs'!AJ54),'Haq — Monthly P&L and cash'!G5<'Model inputs'!AJ54,IF(OR('Haq — Monthly P&L and cash'!G5="",'Model inputs'!AJ54=""),"",'Haq — Monthly P&L and cash'!G5<'Model inputs'!AJ54))="",FALSE,IF(ISERROR('Haq — Monthly P&L and cash'!G5<'Model inputs'!AJ54),'Haq — Monthly P&L and cash'!G5<'Model inputs'!AJ54,IF(OR('Haq — Monthly P&L and cash'!G5="",'Model inputs'!AJ54=""),"",'Haq — Monthly P&L and cash'!G5<'Model inputs'!AJ54))),IF('Model inputs'!AJ87="","",'Model inputs'!AJ87),IF(IF(IF(ISERROR('Haq — Monthly P&L and cash'!G5<'Model inputs'!AJ84),'Haq — Monthly P&L and cash'!G5<'Model inputs'!AJ84,IF(OR('Haq — Monthly P&L and cash'!G5="",'Model inputs'!AJ84=""),"",'Haq — Monthly P&L and cash'!G5<'Model inputs'!AJ84))="",FALSE,IF(ISERROR('Haq — Monthly P&L and cash'!G5<'Model inputs'!AJ84),'Haq — Monthly P&L and cash'!G5<'Model inputs'!AJ84,IF(OR('Haq — Monthly P&L and cash'!G5="",'Model inputs'!AJ84=""),"",'Haq — Monthly P&L and cash'!G5<'Model inputs'!AJ84))),IF('Model inputs'!AJ55="","",'Model inputs'!AJ55),IF('Model inputs'!AJ85="","",'Model inputs'!AJ85))) -> 10 | H6: =IF(IF(IF(ISERROR('Haq — Monthly P&L and cash'!H5<'Model inputs'!AJ54),'Haq — Monthly P&L and cash'!H5<'Model inputs'!AJ54,IF(OR('Haq — Monthly P&L and cash'!H5="",'Model inputs'!AJ54=""),"",'Haq — Monthly P&L and cash'!H5<'Model inputs'!AJ54))="",FALSE,IF(ISERROR('Haq — Monthly P&L and cash'!H5<'Model inputs'!AJ54),'Haq — Monthly P&L and cash'!H5<'Model inputs'!AJ54,IF(OR('Haq — Monthly P&L and cash'!H5="",'Model inputs'!AJ54=""),"",'Haq — Monthly P&L and cash'!H5<'Model inputs'!AJ54))),IF('Model inputs'!AJ87="","",'Model inputs'!AJ87),IF(IF(IF(ISERROR('Haq — Monthly P&L and cash'!H5<'Model inputs'!AJ84),'Haq — Monthly P&L and cash'!H5<'Model inputs'!AJ84,IF(OR('Haq — Monthly P&L and cash'!H5="",'Model inputs'!AJ84=""),"",'Haq — Monthly P&L and cash'!H5<'Model inputs'!AJ84))="",FALSE,IF(ISERROR('Haq — Monthly P&L and cash'!H5<'Model inputs'!AJ84),'Haq — Monthly P&L and cash'!H5<'Model inputs'!AJ84,IF(OR('Haq — Monthly P&L and cash'!H5="",'Model inputs'!AJ84=""),"",'Haq — Monthly P&L and cash'!H5<'Model inputs'!AJ84))),IF('Model inputs'!AJ55="","",'Model inputs'!AJ55),IF('Model inputs'!AJ85="","",'Model inputs'!AJ85))) -> 10 | I6: =IF(IF(IF(ISERROR('Haq — Monthly P&L and cash'!I5<'Model inputs'!AJ54),'Haq — Monthly P&L and cash'!I5<'Model inputs'!AJ54,IF(OR('Haq — Monthly P&L and cash'!I5="",'Model inputs'!AJ54=""),"",'Haq — Monthly P&L and cash'!I5<'Model inputs'!AJ54))="",FALSE,IF(ISERROR('Haq — Monthly P&L and cash'!I5<'Model inputs'!AJ54),'Haq — Monthly P&L and cash'!I5<'Model inputs'!AJ54,IF(OR('Haq — Monthly P&L and cash'!I5="",'Model inputs'!AJ54=""),"",'Haq — Monthly P&L and cash'!I5<'Model inputs'!AJ54))),IF('Model inputs'!AJ87="","",'Model inputs'!AJ87),IF(IF(IF(ISERROR('Haq — Monthly P&L and cash'!I5<'Model inputs'!AJ84),'Haq — Monthly P&L and cash'!I5<'Model inputs'!AJ84,IF(OR('Haq — Monthly P&L and cash'!I5="",'Model inputs'!AJ84=""),"",'Haq — Monthly P&L and cash'!I5<'Model inputs'!AJ84))="",FALSE,IF(ISERROR('Haq — Monthly P&L and cash'!I5<'Model inputs'!AJ84),'Haq — Monthly P&L and cash'!I5<'Model inputs'!AJ84,IF(OR('Haq — Monthly P&L and cash'!I5="",'Model inputs'!AJ84=""),"",'Haq — Monthly P&L and cash'!I5<'Model inputs'!AJ84))),IF('Model inputs'!AJ55="","",'Model inputs'!AJ55),IF('Model inputs'!AJ85="","",'Model inputs'!AJ85))) -> 10 | J6: =IF(IF(IF(ISERROR('Haq — Monthly P&L and cash'!J5<'Model inputs'!AJ54),'Haq — Monthly P&L and cash'!J5<'Model inputs'!AJ54,IF(OR('Haq — Monthly P&L and cash'!J5="",'Model inputs'!AJ54=""),"",'Haq — Monthly P&L and cash'!J5<'Model inputs'!AJ54))="",FALSE,IF(ISERROR('Haq — Monthly P&L and cash'!J5<'Model inputs'!AJ54),'Haq — Monthly P&L and cash'!J5<'Model inputs'!AJ54,IF(OR('Haq — Monthly P&L and cash'!J5="",'Model inputs'!AJ54=""),"",'Haq — Monthly P&L and cash'!J5<'Model inputs'!AJ54))),IF('Model inputs'!AJ87="","",'Model inputs'!AJ87),IF(IF(IF(ISERROR('Haq — Monthly P&L and cash'!J5<'Model inputs'!AJ84),'Haq — Monthly P&L and cash'!J5<'Model inputs'!AJ84,IF(OR('Haq — Monthly P&L and cash'!J5="",'Model inputs'!AJ84=""),"",'Haq — Monthly P&L and cash'!J5<'Model inputs'!AJ84))="",FALSE,IF(ISERROR('Haq — Monthly P&L and cash'!J5<'Model inputs'!AJ84),'Haq — Monthly P&L and cash'!J5<'Model inputs'!AJ84,IF(OR('Haq — Monthly P&L and cash'!J5="",'Model inputs'!AJ84=""),"",'Haq — Monthly P&L and cash'!J5<'Model inputs'!AJ84))),IF('Model inputs'!AJ55="","",'Model inputs'!AJ55),IF('Model inputs'!AJ85="","",'Model inputs'!AJ85))) -> 10 | K6: =IF(IF(IF(ISERROR('Haq — Monthly P&L and cash'!K5<'Model inputs'!AJ54),'Haq — Monthly P&L and cash'!K5<'Model inputs'!AJ54,IF(OR('Haq — Monthly P&L and cash'!K5="",'Model inputs'!AJ54=""),"",'Haq — Monthly P&L and cash'!K5<'Model inputs'!AJ54))="",FALSE,IF(ISERROR('Haq — Monthly P&L and cash'!K5<'Model inputs'!AJ54),'Haq — Monthly P&L and cash'!K5<'Model inputs'!AJ54,IF(OR('Haq — Monthly P&L and cash'!K5="",'Model inputs'!AJ54=""),"",'Haq — Monthly P&L and cash'!K5<'Model inputs'!AJ54))),IF('Model inputs'!AJ87="","",'Model inputs'!AJ87),IF(IF(IF(ISERROR('Haq — Monthly P&L and cash'!K5<'Model inputs'!AJ84),'Haq — Monthly P&L and cash'!K5<'Model inputs'!AJ84,IF(OR('Haq — Monthly P&L and cash'!K5="",'Model inputs'!AJ84=""),"",'Haq — Monthly P&L and cash'!K5<'Model inputs'!AJ84))="",FALSE,IF(ISERROR('Haq — Monthly P&L and cash'!K5<'Model inputs'!AJ84),'Haq — Monthly P&L and cash'!K5<'Model inputs'!AJ84,IF(OR('Haq — Monthly P&L and cash'!K5="",'Model inputs'!AJ84=""),"",'Haq — Monthly P&L and cash'!K5<'Model inputs'!AJ84))),IF('Model inputs'!AJ55="","",'Model inputs'!AJ55),IF('Model inputs'!AJ85="","",'Model inputs'!AJ85))) -> 4 | L6: =IF(IF(IF(ISERROR('Haq — Monthly P&L and cash'!L5<'Model inputs'!AJ54),'Haq — Monthly P&L and cash'!L5<'Model inputs'!AJ54,IF(OR('Haq — Monthly P&L and cash'!L5="",'Model inputs'!AJ54=""),"",'Haq — Monthly P&L and cash'!L5<'Model inputs'!AJ54))="",FALSE,IF(ISERROR('Haq — Monthly P&L and cash'!L5<'Model inputs'!AJ54),'Haq — Monthly P&L and cash'!L5<'Model inputs'!AJ54,IF(OR('Haq — Monthly P&L and cash'!L5="",'Model inputs'!AJ54=""),"",'Haq — Monthly P&L and cash'!L5<'Model inputs'!AJ54))),IF('Model inputs'!AJ87="","",'Model inputs'!AJ87),IF(IF(IF(ISERROR('Haq — Monthly P&L and cash'!L5<'Model inputs'!AJ84),'Haq — Monthly P&L and cash'!L5<'Model inputs'!AJ84,IF(OR('Haq — Monthly P&L and cash'!L5="",'Model inputs'!AJ84=""),"",'Haq — Monthly P&L and cash'!L5<'Model inputs'!AJ84))="",FALSE,IF(ISERROR('Haq — Monthly P&L and cash'!L5<'Model inputs'!AJ84),'Haq — Monthly P&L and cash'!L5<'Model inputs'!AJ84,IF(OR('Haq — Monthly P&L and cash'!L5="",'Model inputs'!AJ84=""),"",'Haq — Monthly P&L and cash'!L5<'Model inputs'!AJ84))),IF('Model inputs'!AJ55="","",'Model inputs'!AJ55),IF('Model inputs'!AJ85="","",'Model inputs'!AJ85))) -> 4 | M6: =IF(IF(IF(ISERROR('Haq — Monthly P&L and cash'!M5<'Model inputs'!AJ54),'Haq — Monthly P&L and cash'!M5<'Model inputs'!AJ54,IF(OR('Haq — Monthly P&L and cash'!M5="",'Model inputs'!AJ54=""),"",'Haq — Monthly P&L and cash'!M5<'Model inputs'!AJ54))="",FALSE,IF(ISERROR('Haq — Monthly P&L and cash'!M5<'Model inputs'!AJ54),'Haq — Monthly P&L and cash'!M5<'Model inputs'!AJ54,IF(OR('Haq — Monthly P&L and cash'!M5="",'Model inputs'!AJ54=""),"",'Haq — Monthly P&L and cash'!M5<'Model inputs'!AJ54))),IF('Model inputs'!AJ87="","",'Model inputs'!AJ87),IF(IF(IF(ISERROR('Haq — Monthly P&L and cash'!M5<'Model inputs'!AJ84),'Haq — Monthly P&L and cash'!M5<'Model inputs'!AJ84,IF(OR('Haq — Monthly P&L and cash'!M5="",'Model inputs'!AJ84=""),"",'Haq — Monthly P&L and cash'!M5<'Model inputs'!AJ84))="",FALSE,IF(ISERROR('Haq — Monthly P&L and cash'!M5<'Model inputs'!AJ84),'Haq — Monthly P&L and cash'!M5<'Model inputs'!AJ84,IF(OR('Haq — Monthly P&L and cash'!M5="",'Model inputs'!AJ84=""),"",'Haq — Monthly P&L and cash'!M5<'Model inputs'!AJ84))),IF('Model inputs'!AJ55="","",'Model inputs'!AJ55),IF('Model inputs'!AJ85="","",'Model inputs'!AJ85))) -> 4 | N6: =IF(IF(IF(ISERROR('Haq — Monthly P&L and cash'!N5<'Model inputs'!AJ54),'Haq — Monthly P&L and cash'!N5<'Model inputs'!AJ54,IF(OR('Haq — Monthly P&L and cash'!N5="",'Model inputs'!AJ54=""),"",'Haq — Monthly P&L and cash'!N5<'Model inputs'!AJ54))="",FALSE,IF(ISERROR('Haq — Monthly P&L and cash'!N5<'Model inputs'!AJ54),'Haq — Monthly P&L and cash'!N5<'Model inputs'!AJ54,IF(OR('Haq — Monthly P&L and cash'!N5="",'Model inputs'!AJ54=""),"",'Haq — Monthly P&L and cash'!N5<'Model inputs'!AJ54))),IF('Model inputs'!AJ87="","",'Model inputs'!AJ87),IF(IF(IF(ISERROR('Haq — Monthly P&L and cash'!N5<'Model inputs'!AJ84),'Haq — Monthly P&L and cash'!N5<'Model inputs'!AJ84,IF(OR('Haq — Monthly P&L and cash'!N5="",'Model inputs'!AJ84=""),"",'Haq — Monthly P&L and cash'!N5<'Model inputs'!AJ84))="",FALSE,IF(ISERROR('Haq — Monthly P&L and cash'!N5<'Model inputs'!AJ84),'Haq — Monthly P&L and cash'!N5<'Model inputs'!AJ84,IF(OR('Haq — Monthly P&L and cash'!N5="",'Model inputs'!AJ84=""),"",'Haq — Monthly P&L and cash'!N5<'Model inputs'!AJ84))),IF('Model inputs'!AJ55="","",'Model inputs'!AJ55),IF('Model inputs'!AJ85="","",'Model inputs'!AJ85))) -> 4 | O6: =IF(IF(IF(ISERROR('Haq — Monthly P&L and cash'!O5<'Model inputs'!AJ54),'Haq — Monthly P&L and cash'!O5<'Model inputs'!AJ54,IF(OR('Haq — Monthly P&L and cash'!O5="",'Model inputs'!AJ54=""),"",'Haq — Monthly P&L and cash'!O5<'Model inputs'!AJ54))="",FALSE,IF(ISERROR('Haq — Monthly P&L and cash'!O5<'Model inputs'!AJ54),'Haq — Monthly P&L and cash'!O5<'Model inputs'!AJ54,IF(OR('Haq — Monthly P&L and cash'!O5="",'Model inputs'!AJ54=""),"",'Haq — Monthly P&L and cash'!O5<'Model inputs'!AJ54))),IF('Model inputs'!AJ87="","",'Model inputs'!AJ87),IF(IF(IF(ISERROR('Haq — Monthly P&L and cash'!O5<'Model inputs'!AJ84),'Haq — Monthly P&L and cash'!O5<'Model inputs'!AJ84,IF(OR('Haq — Monthly P&L and cash'!O5="",'Model inputs'!AJ84=""),"",'Haq — Monthly P&L and cash'!O5<'Model inputs'!AJ84))="",FALSE,IF(ISERROR('Haq — Monthly P&L and cash'!O5<'Model inputs'!AJ84),'Haq — Monthly P&L and cash'!O5<'Model inputs'!AJ84,IF(OR('Haq — Monthly P&L and cash'!O5="",'Model inputs'!AJ84=""),"",'Haq — Monthly P&L and cash'!O5<'Model inputs'!AJ84))),IF('Model inputs'!AJ55="","",'Model inputs'!AJ55),IF('Model inputs'!AJ85="","",'Model inputs'!AJ85))) -> 4 | P6: =IF(IF(IF(ISERROR('Haq — Monthly P&L and cash'!P5<'Model inputs'!AJ54),'Haq — Monthly P&L and cash'!P5<'Model inputs'!AJ54,IF(OR('Haq — Monthly P&L and cash'!P5="",'Model inputs'!AJ54=""),"",'Haq — Monthly P&L and cash'!P5<'Model inputs'!AJ54))="",FALSE,IF(ISERROR('Haq — Monthly P&L and cash'!P5<'Model inputs'!AJ54),'Haq — Monthly P&L and cash'!P5<'Model inputs'!AJ54,IF(OR('Haq — Monthly P&L and cash'!P5="",'Model inputs'!AJ54=""),"",'Haq — Monthly P&L and cash'!P5<'Model inputs'!AJ54))),IF('Model inputs'!AJ87="","",'Model inputs'!AJ87),IF(IF(IF(ISERROR('Haq — Monthly P&L and cash'!P5<'Model inputs'!AJ84),'Haq — Monthly P&L and cash'!P5<'Model inputs'!AJ84,IF(OR('Haq — Monthly P&L and cash'!P5="",'Model inputs'!AJ84=""),"",'Haq — Monthly P&L and cash'!P5<'Model inputs'!AJ84))="",FALSE,IF(ISERROR('Haq — Monthly P&L and cash'!P5<'Model inputs'!AJ84),'Haq — Monthly P&L and cash'!P5<'Model inputs'!AJ84,IF(OR('Haq — Monthly P&L and cash'!P5="",'Model inputs'!AJ84=""),"",'Haq — Monthly P&L and cash'!P5<'Model inputs'!AJ84))),IF('Model inputs'!AJ55="","",'Model inputs'!AJ55),IF('Model inputs'!AJ85="","",'Model inputs'!AJ85))) -> 4 | Q6: =IF(IF(IF(ISERROR('Haq — Monthly P&L and cash'!Q5<'Model inputs'!AJ54),'Haq — Monthly P&L and cash'!Q5<'Model inputs'!AJ54,IF(OR('Haq — Monthly P&L and cash'!Q5="",'Model inputs'!AJ54=""),"",'Haq — Monthly P&L and cash'!Q5<'Model inputs'!AJ54))="",FALSE,IF(ISERROR('Haq — Monthly P&L and cash'!Q5<'Model inputs'!AJ54),'Haq — Monthly P&L and cash'!Q5<'Model inputs'!AJ54,IF(OR('Haq — Monthly P&L and cash'!Q5="",'Model inputs'!AJ54=""),"",'Haq — Monthly P&L and cash'!Q5<'Model inputs'!AJ54))),IF('Model inputs'!AJ87="","",'Model inputs'!AJ87),IF(IF(IF(ISERROR('Haq — Monthly P&L and cash'!Q5<'Model inputs'!AJ84),'Haq — Monthly P&L and cash'!Q5<'Model inputs'!AJ84,IF(OR('Haq — Monthly P&L and cash'!Q5="",'Model inputs'!AJ84=""),"",'Haq — Monthly P&L and cash'!Q5<'Model inputs'!AJ84))="",FALSE,IF(ISERROR('Haq — Monthly P&L and cash'!Q5<'Model inputs'!AJ84),'Haq — Monthly P&L and cash'!Q5<'Model inputs'!AJ84,IF(OR('Haq — Monthly P&L and cash'!Q5="",'Model inputs'!AJ84=""),"",'Haq — Monthly P&L and cash'!Q5<'Model inputs'!AJ84))),IF('Model inputs'!AJ55="","",'Model inputs'!AJ55),IF('Model inputs'!AJ85="","",'Model inputs'!AJ85))) -> 4 | R6: =IF(IF(IF(ISERROR('Haq — Monthly P&L and cash'!R5<'Model inputs'!AJ54),'Haq — Monthly P&L and cash'!R5<'Model inputs'!AJ54,IF(OR('Haq — Monthly P&L and cash'!R5="",'Model inputs'!AJ54=""),"",'Haq — Monthly P&L and cash'!R5<'Model inputs'!AJ54))="",FALSE,IF(ISERROR('Haq — Monthly P&L and cash'!R5<'Model inputs'!AJ54),'Haq — Monthly P&L and cash'!R5<'Model inputs'!AJ54,IF(OR('Haq — Monthly P&L and cash'!R5="",'Model inputs'!AJ54=""),"",'Haq — Monthly P&L and cash'!R5<'Model inputs'!AJ54))),IF('Model inputs'!AJ87="","",'Model inputs'!AJ87),IF(IF(IF(ISERROR('Haq — Monthly P&L and cash'!R5<'Model inputs'!AJ84),'Haq — Monthly P&L and cash'!R5<'Model inputs'!AJ84,IF(OR('Haq — Monthly P&L and cash'!R5="",'Model inputs'!AJ84=""),"",'Haq — Monthly P&L and cash'!R5<'Model inputs'!AJ84))="",FALSE,IF(ISERROR('Haq — Monthly P&L and cash'!R5<'Model inputs'!AJ84),'Haq — Monthly P&L and cash'!R5<'Model inputs'!AJ84,IF(OR('Haq — Monthly P&L and cash'!R5="",'Model inputs'!AJ84=""),"",'Haq — Monthly P&L and cash'!R5<'Model inputs'!AJ84))),IF('Model inputs'!AJ55="","",'Model inputs'!AJ55),IF('Model inputs'!AJ85="","",'Model inputs'!AJ85))) -> 4 | S6: =IF(IF(IF(ISERROR('Haq — Monthly P&L and cash'!S5<'Model inputs'!AJ54),'Haq — Monthly P&L and cash'!S5<'Model inputs'!AJ54,IF(OR('Haq — Monthly P&L and cash'!S5="",'Model inputs'!AJ54=""),"",'Haq — Monthly P&L and cash'!S5<'Model inputs'!AJ54))="",FALSE,IF(ISERROR('Haq — Monthly P&L and cash'!S5<'Model inputs'!AJ54),'Haq — Monthly P&L and cash'!S5<'Model inputs'!AJ54,IF(OR('Haq — Monthly P&L and cash'!S5="",'Model inputs'!AJ54=""),"",'Haq — Monthly P&L and cash'!S5<'Model inputs'!AJ54))),IF('Model inputs'!AJ87="","",'Model inputs'!AJ87),IF(IF(IF(ISERROR('Haq — Monthly P&L and cash'!S5<'Model inputs'!AJ84),'Haq — Monthly P&L and cash'!S5<'Model inputs'!AJ84,IF(OR('Haq — Monthly P&L and cash'!S5="",'Model inputs'!AJ84=""),"",'Haq — Monthly P&L and cash'!S5<'Model inputs'!AJ84))="",FALSE,IF(ISERROR('Haq — Monthly P&L and cash'!S5<'Model inputs'!AJ84),'Haq — Monthly P&L and cash'!S5<'Model inputs'!AJ84,IF(OR('Haq — Monthly P&L and cash'!S5="",'Model inputs'!AJ84=""),"",'Haq — Monthly P&L and cash'!S5<'Model inputs'!AJ84))),IF('Model inputs'!AJ55="","",'Model inputs'!AJ55),IF('Model inputs'!AJ85="","",'Model inputs'!AJ85))) -> 4 | T6: =IF(IF(IF(ISERROR('Haq — Monthly P&L and cash'!T5<'Model inputs'!AJ54),'Haq — Monthly P&L and cash'!T5<'Model inputs'!AJ54,IF(OR('Haq — Monthly P&L and cash'!T5="",'Model inputs'!AJ54=""),"",'Haq — Monthly P&L and cash'!T5<'Model inputs'!AJ54))="",FALSE,IF(ISERROR('Haq — Monthly P&L and cash'!T5<'Model inputs'!AJ54),'Haq — Monthly P&L and cash'!T5<'Model inputs'!AJ54,IF(OR('Haq — Monthly P&L and cash'!T5="",'Model inputs'!AJ54=""),"",'Haq — Monthly P&L and cash'!T5<'Model inputs'!AJ54))),IF('Model inputs'!AJ87="","",'Model inputs'!AJ87),IF(IF(IF(ISERROR('Haq — Monthly P&L and cash'!T5<'Model inputs'!AJ84),'Haq — Monthly P&L and cash'!T5<'Model inputs'!AJ84,IF(OR('Haq — Monthly P&L and cash'!T5="",'Model inputs'!AJ84=""),"",'Haq — Monthly P&L and cash'!T5<'Model inputs'!AJ84))="",FALSE,IF(ISERROR('Haq — Monthly P&L and cash'!T5<'Model inputs'!AJ84),'Haq — Monthly P&L and cash'!T5<'Model inputs'!AJ84,IF(OR('Haq — Monthly P&L and cash'!T5="",'Model inputs'!AJ84=""),"",'Haq — Monthly P&L and cash'!T5<'Model inputs'!AJ84))),IF('Model inputs'!AJ55="","",'Model inputs'!AJ55),IF('Model inputs'!AJ85="","",'Model inputs'!AJ85))) -> 4 | U6: =IF(IF(IF(ISERROR('Haq — Monthly P&L and cash'!U5<'Model inputs'!AJ54),'Haq — Monthly P&L and cash'!U5<'Model inputs'!AJ54,IF(OR('Haq — Monthly P&L and cash'!U5="",'Model inputs'!AJ54=""),"",'Haq — Monthly P&L and cash'!U5<'Model inputs'!AJ54))="",FALSE,IF(ISERROR('Haq — Monthly P&L and cash'!U5<'Model inputs'!AJ54),'Haq — Monthly P&L and cash'!U5<'Model inputs'!AJ54,IF(OR('Haq — Monthly P&L and cash'!U5="",'Model inputs'!AJ54=""),"",'Haq — Monthly P&L and cash'!U5<'Model inputs'!AJ54))),IF('Model inputs'!AJ87="","",'Model inputs'!AJ87),IF(IF(IF(ISERROR('Haq — Monthly P&L and cash'!U5<'Model inputs'!AJ84),'Haq — Monthly P&L and cash'!U5<'Model inputs'!AJ84,IF(OR('Haq — Monthly P&L and cash'!U5="",'Model inputs'!AJ84=""),"",'Haq — Monthly P&L and cash'!U5<'Model inputs'!AJ84))="",FALSE,IF(ISERROR('Haq — Monthly P&L and cash'!U5<'Model inputs'!AJ84),'Haq — Monthly P&L and cash'!U5<'Model inputs'!AJ84,IF(OR('Haq — Monthly P&L and cash'!U5="",'Model inputs'!AJ84=""),"",'Haq — Monthly P&L and cash'!U5<'Model inputs'!AJ84))),IF('Model inputs'!AJ55="","",'Model inputs'!AJ55),IF('Model inputs'!AJ85="","",'Model inputs'!AJ85))) -> 4 | V6: =IF(IF(IF(ISERROR('Haq — Monthly P&L and cash'!V5<'Model inputs'!AJ54),'Haq — Monthly P&L and cash'!V5<'Model inputs'!AJ54,IF(OR('Haq — Monthly P&L and cash'!V5="",'Model inputs'!AJ54=""),"",'Haq — Monthly P&L and cash'!V5<'Model inputs'!AJ54))="",FALSE,IF(ISERROR('Haq — Monthly P&L and cash'!V5<'Model inputs'!AJ54),'Haq — Monthly P&L and cash'!V5<'Model inputs'!AJ54,IF(OR('Haq — Monthly P&L and cash'!V5="",'Model inputs'!AJ54=""),"",'Haq — Monthly P&L and cash'!V5<'Model inputs'!AJ54))),IF('Model inputs'!AJ87="","",'Model inputs'!AJ87),IF(IF(IF(ISERROR('Haq — Monthly P&L and cash'!V5<'Model inputs'!AJ84),'Haq — Monthly P&L and cash'!V5<'Model inputs'!AJ84,IF(OR('Haq — Monthly P&L and cash'!V5="",'Model inputs'!AJ84=""),"",'Haq — Monthly P&L and cash'!V5<'Model inputs'!AJ84))="",FALSE,IF(ISERROR('Haq — Monthly P&L and cash'!V5<'Model inputs'!AJ84),'Haq — Monthly P&L and cash'!V5<'Model inputs'!AJ84,IF(OR('Haq — Monthly P&L and cash'!V5="",'Model inputs'!AJ84=""),"",'Haq — Monthly P&L and cash'!V5<'Model inputs'!AJ84))),IF('Model inputs'!AJ55="","",'Model inputs'!AJ55),IF('Model inputs'!AJ85="","",'Model inputs'!AJ85))) -> 4 | W6: =IF(IF(IF(ISERROR('Haq — Monthly P&L and cash'!W5<'Model inputs'!AJ54),'Haq — Monthly P&L and cash'!W5<'Model inputs'!AJ54,IF(OR('Haq — Monthly P&L and cash'!W5="",'Model inputs'!AJ54=""),"",'Haq — Monthly P&L and cash'!W5<'Model inputs'!AJ54))="",FALSE,IF(ISERROR('Haq — Monthly P&L and cash'!W5<'Model inputs'!AJ54),'Haq — Monthly P&L and cash'!W5<'Model inputs'!AJ54,IF(OR('Haq — Monthly P&L and cash'!W5="",'Model inputs'!AJ54=""),"",'Haq — Monthly P&L and cash'!W5<'Model inputs'!AJ54))),IF('Model inputs'!AJ87="","",'Model inputs'!AJ87),IF(IF(IF(ISERROR('Haq — Monthly P&L and cash'!W5<'Model inputs'!AJ84),'Haq — Monthly P&L and cash'!W5<'Model inputs'!AJ84,IF(OR('Haq — Monthly P&L and cash'!W5="",'Model inputs'!AJ84=""),"",'Haq — Monthly P&L and cash'!W5<'Model inputs'!AJ84))="",FALSE,IF(ISERROR('Haq — Monthly P&L and cash'!W5<'Model inputs'!AJ84),'Haq — Monthly P&L and cash'!W5<'Model inputs'!AJ84,IF(OR('Haq — Monthly P&L and cash'!W5="",'Model inputs'!AJ84=""),"",'Haq — Monthly P&L and cash'!W5<'Model inputs'!AJ84))),IF('Model inputs'!AJ55="","",'Model inputs'!AJ55),IF('Model inputs'!AJ85="","",'Model inputs'!AJ85))) -> 4 | X6: =IF(IF(IF(ISERROR('Haq — Monthly P&L and cash'!X5<'Model inputs'!AJ54),'Haq — Monthly P&L and cash'!X5<'Model inputs'!AJ54,IF(OR('Haq — Monthly P&L and cash'!X5="",'Model inputs'!AJ54=""),"",'Haq — Monthly P&L and cash'!X5<'Model inputs'!AJ54))="",FALSE,IF(ISERROR('Haq — Monthly P&L and cash'!X5<'Model inputs'!AJ54),'Haq — Monthly P&L and cash'!X5<'Model inputs'!AJ54,IF(OR('Haq — Monthly P&L and cash'!X5="",'Model inputs'!AJ54=""),"",'Haq — Monthly P&L and cash'!X5<'Model inputs'!AJ54))),IF('Model inputs'!AJ87="","",'Model inputs'!AJ87),IF(IF(IF(ISERROR('Haq — Monthly P&L and cash'!X5<'Model inputs'!AJ84),'Haq — Monthly P&L and cash'!X5<'Model inputs'!AJ84,IF(OR('Haq — Monthly P&L and cash'!X5="",'Model inputs'!AJ84=""),"",'Haq — Monthly P&L and cash'!X5<'Model inputs'!AJ84))="",FALSE,IF(ISERROR('Haq — Monthly P&L and cash'!X5<'Model inputs'!AJ84),'Haq — Monthly P&L and cash'!X5<'Model inputs'!AJ84,IF(OR('Haq — Monthly P&L and cash'!X5="",'Model inputs'!AJ84=""),"",'Haq — Monthly P&L and cash'!X5<'Model inputs'!AJ84))),IF('Model inputs'!AJ55="","",'Model inputs'!AJ55),IF('Model inputs'!AJ85="","",'Model inputs'!AJ85))) -> 4 | Y6: =IF(IF(IF(ISERROR('Haq — Monthly P&L and cash'!Y5<'Model inputs'!AJ54),'Haq — Monthly P&L and cash'!Y5<'Model inputs'!AJ54,IF(OR('Haq — Monthly P&L and cash'!Y5="",'Model inputs'!AJ54=""),"",'Haq — Monthly P&L and cash'!Y5<'Model inputs'!AJ54))="",FALSE,IF(ISERROR('Haq — Monthly P&L and cash'!Y5<'Model inputs'!AJ54),'Haq — Monthly P&L and cash'!Y5<'Model inputs'!AJ54,IF(OR('Haq — Monthly P&L and cash'!Y5="",'Model inputs'!AJ54=""),"",'Haq — Monthly P&L and cash'!Y5<'Model inputs'!AJ54))),IF('Model inputs'!AJ87="","",'Model inputs'!AJ87),IF(IF(IF(ISERROR('Haq — Monthly P&L and cash'!Y5<'Model inputs'!AJ84),'Haq — Monthly P&L and cash'!Y5<'Model inputs'!AJ84,IF(OR('Haq — Monthly P&L and cash'!Y5="",'Model inputs'!AJ84=""),"",'Haq — Monthly P&L and cash'!Y5<'Model inputs'!AJ84))="",FALSE,IF(ISERROR('Haq — Monthly P&L and cash'!Y5<'Model inputs'!AJ84),'Haq — Monthly P&L and cash'!Y5<'Model inputs'!AJ84,IF(OR('Haq — Monthly P&L and cash'!Y5="",'Model inputs'!AJ84=""),"",'Haq — Monthly P&L and cash'!Y5<'Model inputs'!AJ84))),IF('Model inputs'!AJ55="","",'Model inputs'!AJ55),IF('Model inputs'!AJ85="","",'Model inputs'!AJ85))) -> 4
A7: Haq CSC operators | B7: =IF(IF(IF(ISERROR('Haq — Monthly P&L and cash'!B5<'Model inputs'!AJ40),'Haq — Monthly P&L and cash'!B5<'Model inputs'!AJ40,IF(OR('Haq — Monthly P&L and cash'!B5="",'Model inputs'!AJ40=""),"",'Haq — Monthly P&L and cash'!B5<'Model inputs'!AJ40))="",FALSE,IF(ISERROR('Haq — Monthly P&L and cash'!B5<'Model inputs'!AJ40),'Haq — Monthly P&L and cash'!B5<'Model inputs'!AJ40,IF(OR('Haq — Monthly P&L and cash'!B5="",'Model inputs'!AJ40=""),"",'Haq — Monthly P&L and cash'!B5<'Model inputs'!AJ40))),0,IF(IF(IF(ISERROR('Haq — Monthly P&L and cash'!B5='Model inputs'!AJ40),'Haq — Monthly P&L and cash'!B5='Model inputs'!AJ40,IF(OR('Haq — Monthly P&L and cash'!B5="",'Model inputs'!AJ40=""),"",'Haq — Monthly P&L and cash'!B5='Model inputs'!AJ40))="",FALSE,IF(ISERROR('Haq — Monthly P&L and cash'!B5='Model inputs'!AJ40),'Haq — Monthly P&L and cash'!B5='Model inputs'!AJ40,IF(OR('Haq — Monthly P&L and cash'!B5="",'Model inputs'!AJ40=""),"",'Haq — Monthly P&L and cash'!B5='Model inputs'!AJ40))),IF('Model inputs'!AJ41="","",'Model inputs'!AJ41),'Model inputs'!C14*(1+'Model inputs'!AJ37-'Model inputs'!AJ42))) -> 0 | C7: =IF(IF(IF(ISERROR('Haq — Monthly P&L and cash'!C5<'Model inputs'!AJ40),'Haq — Monthly P&L and cash'!C5<'Model inputs'!AJ40,IF(OR('Haq — Monthly P&L and cash'!C5="",'Model inputs'!AJ40=""),"",'Haq — Monthly P&L and cash'!C5<'Model inputs'!AJ40))="",FALSE,IF(ISERROR('Haq — Monthly P&L and cash'!C5<'Model inputs'!AJ40),'Haq — Monthly P&L and cash'!C5<'Model inputs'!AJ40,IF(OR('Haq — Monthly P&L and cash'!C5="",'Model inputs'!AJ40=""),"",'Haq — Monthly P&L and cash'!C5<'Model inputs'!AJ40))),0,IF(IF(IF(ISERROR('Haq — Monthly P&L and cash'!C5='Model inputs'!AJ40),'Haq — Monthly P&L and cash'!C5='Model inputs'!AJ40,IF(OR('Haq — Monthly P&L and cash'!C5="",'Model inputs'!AJ40=""),"",'Haq — Monthly P&L and cash'!C5='Model inputs'!AJ40))="",FALSE,IF(ISERROR('Haq — Monthly P&L and cash'!C5='Model inputs'!AJ40),'Haq — Monthly P&L and cash'!C5='Model inputs'!AJ40,IF(OR('Haq — Monthly P&L and cash'!C5="",'Model inputs'!AJ40=""),"",'Haq — Monthly P&L and cash'!C5='Model inputs'!AJ40))),IF('Model inputs'!AJ41="","",'Model inputs'!AJ41),'Haq — Monthly P&L and cash'!B7*(1+'Model inputs'!AJ37-'Model inputs'!AJ42))) -> 0 | D7: =IF(IF(IF(ISERROR('Haq — Monthly P&L and cash'!D5<'Model inputs'!AJ40),'Haq — Monthly P&L and cash'!D5<'Model inputs'!AJ40,IF(OR('Haq — Monthly P&L and cash'!D5="",'Model inputs'!AJ40=""),"",'Haq — Monthly P&L and cash'!D5<'Model inputs'!AJ40))="",FALSE,IF(ISERROR('Haq — Monthly P&L and cash'!D5<'Model inputs'!AJ40),'Haq — Monthly P&L and cash'!D5<'Model inputs'!AJ40,IF(OR('Haq — Monthly P&L and cash'!D5="",'Model inputs'!AJ40=""),"",'Haq — Monthly P&L and cash'!D5<'Model inputs'!AJ40))),0,IF(IF(IF(ISERROR('Haq — Monthly P&L and cash'!D5='Model inputs'!AJ40),'Haq — Monthly P&L and cash'!D5='Model inputs'!AJ40,IF(OR('Haq — Monthly P&L and cash'!D5="",'Model inputs'!AJ40=""),"",'Haq — Monthly P&L and cash'!D5='Model inputs'!AJ40))="",FALSE,IF(ISERROR('Haq — Monthly P&L and cash'!D5='Model inputs'!AJ40),'Haq — Monthly P&L and cash'!D5='Model inputs'!AJ40,IF(OR('Haq — Monthly P&L and cash'!D5="",'Model inputs'!AJ40=""),"",'Haq — Monthly P&L and cash'!D5='Model inputs'!AJ40))),IF('Model inputs'!AJ41="","",'Model inputs'!AJ41),'Haq — Monthly P&L and cash'!C7*(1+'Model inputs'!AJ37-'Model inputs'!AJ42))) -> 0 | E7: =IF(IF(IF(ISERROR('Haq — Monthly P&L and cash'!E5<'Model inputs'!AJ40),'Haq — Monthly P&L and cash'!E5<'Model inputs'!AJ40,IF(OR('Haq — Monthly P&L and cash'!E5="",'Model inputs'!AJ40=""),"",'Haq — Monthly P&L and cash'!E5<'Model inputs'!AJ40))="",FALSE,IF(ISERROR('Haq — Monthly P&L and cash'!E5<'Model inputs'!AJ40),'Haq — Monthly P&L and cash'!E5<'Model inputs'!AJ40,IF(OR('Haq — Monthly P&L and cash'!E5="",'Model inputs'!AJ40=""),"",'Haq — Monthly P&L and cash'!E5<'Model inputs'!AJ40))),0,IF(IF(IF(ISERROR('Haq — Monthly P&L and cash'!E5='Model inputs'!AJ40),'Haq — Monthly P&L and cash'!E5='Model inputs'!AJ40,IF(OR('Haq — Monthly P&L and cash'!E5="",'Model inputs'!AJ40=""),"",'Haq — Monthly P&L and cash'!E5='Model inputs'!AJ40))="",FALSE,IF(ISERROR('Haq — Monthly P&L and cash'!E5='Model inputs'!AJ40),'Haq — Monthly P&L and cash'!E5='Model inputs'!AJ40,IF(OR('Haq — Monthly P&L and cash'!E5="",'Model inputs'!AJ40=""),"",'Haq — Monthly P&L and cash'!E5='Model inputs'!AJ40))),IF('Model inputs'!AJ41="","",'Model inputs'!AJ41),'Haq — Monthly P&L and cash'!D7*(1+'Model inputs'!AJ37-'Model inputs'!AJ42))) -> 50 | F7: =IF(IF(IF(ISERROR('Haq — Monthly P&L and cash'!F5<'Model inputs'!AJ40),'Haq — Monthly P&L and cash'!F5<'Model inputs'!AJ40,IF(OR('Haq — Monthly P&L and cash'!F5="",'Model inputs'!AJ40=""),"",'Haq — Monthly P&L and cash'!F5<'Model inputs'!AJ40))="",FALSE,IF(ISERROR('Haq — Monthly P&L and cash'!F5<'Model inputs'!AJ40),'Haq — Monthly P&L and cash'!F5<'Model inputs'!AJ40,IF(OR('Haq — Monthly P&L and cash'!F5="",'Model inputs'!AJ40=""),"",'Haq — Monthly P&L and cash'!F5<'Model inputs'!AJ40))),0,IF(IF(IF(ISERROR('Haq — Monthly P&L and cash'!F5='Model inputs'!AJ40),'Haq — Monthly P&L and cash'!F5='Model inputs'!AJ40,IF(OR('Haq — Monthly P&L and cash'!F5="",'Model inputs'!AJ40=""),"",'Haq — Monthly P&L and cash'!F5='Model inputs'!AJ40))="",FALSE,IF(ISERROR('Haq — Monthly P&L and cash'!F5='Model inputs'!AJ40),'Haq — Monthly P&L and cash'!F5='Model inputs'!AJ40,IF(OR('Haq — Monthly P&L and cash'!F5="",'Model inputs'!AJ40=""),"",'Haq — Monthly P&L and cash'!F5='Model inputs'!AJ40))),IF('Model inputs'!AJ41="","",'Model inputs'!AJ41),'Haq — Monthly P&L and cash'!E7*(1+'Model inputs'!AJ37-'Model inputs'!AJ42))) -> 57.5 | G7: =IF(IF(IF(ISERROR('Haq — Monthly P&L and cash'!G5<'Model inputs'!AJ40),'Haq — Monthly P&L and cash'!G5<'Model inputs'!AJ40,IF(OR('Haq — Monthly P&L and cash'!G5="",'Model inputs'!AJ40=""),"",'Haq — Monthly P&L and cash'!G5<'Model inputs'!AJ40))="",FALSE,IF(ISERROR('Haq — Monthly P&L and cash'!G5<'Model inputs'!AJ40),'Haq — Monthly P&L and cash'!G5<'Model inputs'!AJ40,IF(OR('Haq — Monthly P&L and cash'!G5="",'Model inputs'!AJ40=""),"",'Haq — Monthly P&L and cash'!G5<'Model inputs'!AJ40))),0,IF(IF(IF(ISERROR('Haq — Monthly P&L and cash'!G5='Model inputs'!AJ40),'Haq — Monthly P&L and cash'!G5='Model inputs'!AJ40,IF(OR('Haq — Monthly P&L and cash'!G5="",'Model inputs'!AJ40=""),"",'Haq — Monthly P&L and cash'!G5='Model inputs'!AJ40))="",FALSE,IF(ISERROR('Haq — Monthly P&L and cash'!G5='Model inputs'!AJ40),'Haq — Monthly P&L and cash'!G5='Model inputs'!AJ40,IF(OR('Haq — Monthly P&L and cash'!G5="",'Model inputs'!AJ40=""),"",'Haq — Monthly P&L and cash'!G5='Model inputs'!AJ40))),IF('Model inputs'!AJ41="","",'Model inputs'!AJ41),'Haq — Monthly P&L and cash'!F7*(1+'Model inputs'!AJ37-'Model inputs'!AJ42))) -> 66.125 | H7: =IF(IF(IF(ISERROR('Haq — Monthly P&L and cash'!H5<'Model inputs'!AJ40),'Haq — Monthly P&L and cash'!H5<'Model inputs'!AJ40,IF(OR('Haq — Monthly P&L and cash'!H5="",'Model inputs'!AJ40=""),"",'Haq — Monthly P&L and cash'!H5<'Model inputs'!AJ40))="",FALSE,IF(ISERROR('Haq — Monthly P&L and cash'!H5<'Model inputs'!AJ40),'Haq — Monthly P&L and cash'!H5<'Model inputs'!AJ40,IF(OR('Haq — Monthly P&L and cash'!H5="",'Model inputs'!AJ40=""),"",'Haq — Monthly P&L and cash'!H5<'Model inputs'!AJ40))),0,IF(IF(IF(ISERROR('Haq — Monthly P&L and cash'!H5='Model inputs'!AJ40),'Haq — Monthly P&L and cash'!H5='Model inputs'!AJ40,IF(OR('Haq — Monthly P&L and cash'!H5="",'Model inputs'!AJ40=""),"",'Haq — Monthly P&L and cash'!H5='Model inputs'!AJ40))="",FALSE,IF(ISERROR('Haq — Monthly P&L and cash'!H5='Model inputs'!AJ40),'Haq — Monthly P&L and cash'!H5='Model inputs'!AJ40,IF(OR('Haq — Monthly P&L and cash'!H5="",'Model inputs'!AJ40=""),"",'Haq — Monthly P&L and cash'!H5='Model inputs'!AJ40))),IF('Model inputs'!AJ41="","",'Model inputs'!AJ41),'Haq — Monthly P&L and cash'!G7*(1+'Model inputs'!AJ37-'Model inputs'!AJ42))) -> 76.04375 | I7: =IF(IF(IF(ISERROR('Haq — Monthly P&L and cash'!I5<'Model inputs'!AJ40),'Haq — Monthly P&L and cash'!I5<'Model inputs'!AJ40,IF(OR('Haq — Monthly P&L and cash'!I5="",'Model inputs'!AJ40=""),"",'Haq — Monthly P&L and cash'!I5<'Model inputs'!AJ40))="",FALSE,IF(ISERROR('Haq — Monthly P&L and cash'!I5<'Model inputs'!AJ40),'Haq — Monthly P&L and cash'!I5<'Model inputs'!AJ40,IF(OR('Haq — Monthly P&L and cash'!I5="",'Model inputs'!AJ40=""),"",'Haq — Monthly P&L and cash'!I5<'Model inputs'!AJ40))),0,IF(IF(IF(ISERROR('Haq — Monthly P&L and cash'!I5='Model inputs'!AJ40),'Haq — Monthly P&L and cash'!I5='Model inputs'!AJ40,IF(OR('Haq — Monthly P&L and cash'!I5="",'Model inputs'!AJ40=""),"",'Haq — Monthly P&L and cash'!I5='Model inputs'!AJ40))="",FALSE,IF(ISERROR('Haq — Monthly P&L and cash'!I5='Model inputs'!AJ40),'Haq — Monthly P&L and cash'!I5='Model inputs'!AJ40,IF(OR('Haq — Monthly P&L and cash'!I5="",'Model inputs'!AJ40=""),"",'Haq — Monthly P&L and cash'!I5='Model inputs'!AJ40))),IF('Model inputs'!AJ41="","",'Model inputs'!AJ41),'Haq — Monthly P&L and cash'!H7*(1+'Model inputs'!AJ37-'Model inputs'!AJ42))) -> 87.450312 | J7: =IF(IF(IF(ISERROR('Haq — Monthly P&L and cash'!J5<'Model inputs'!AJ40),'Haq — Monthly P&L and cash'!J5<'Model inputs'!AJ40,IF(OR('Haq — Monthly P&L and cash'!J5="",'Model inputs'!AJ40=""),"",'Haq — Monthly P&L and cash'!J5<'Model inputs'!AJ40))="",FALSE,IF(ISERROR('Haq — Monthly P&L and cash'!J5<'Model inputs'!AJ40),'Haq — Monthly P&L and cash'!J5<'Model inputs'!AJ40,IF(OR('Haq — Monthly P&L and cash'!J5="",'Model inputs'!AJ40=""),"",'Haq — Monthly P&L and cash'!J5<'Model inputs'!AJ40))),0,IF(IF(IF(ISERROR('Haq — Monthly P&L and cash'!J5='Model inputs'!AJ40),'Haq — Monthly P&L and cash'!J5='Model inputs'!AJ40,IF(OR('Haq — Monthly P&L and cash'!J5="",'Model inputs'!AJ40=""),"",'Haq — Monthly P&L and cash'!J5='Model inputs'!AJ40))="",FALSE,IF(ISERROR('Haq — Monthly P&L and cash'!J5='Model inputs'!AJ40),'Haq — Monthly P&L and cash'!J5='Model inputs'!AJ40,IF(OR('Haq — Monthly P&L and cash'!J5="",'Model inputs'!AJ40=""),"",'Haq — Monthly P&L and cash'!J5='Model inputs'!AJ40))),IF('Model inputs'!AJ41="","",'Model inputs'!AJ41),'Haq — Monthly P&L and cash'!I7*(1+'Model inputs'!AJ37-'Model inputs'!AJ42))) -> 100.56786 | K7: =IF(IF(IF(ISERROR('Haq — Monthly P&L and cash'!K5<'Model inputs'!AJ40),'Haq — Monthly P&L and cash'!K5<'Model inputs'!AJ40,IF(OR('Haq — Monthly P&L and cash'!K5="",'Model inputs'!AJ40=""),"",'Haq — Monthly P&L and cash'!K5<'Model inputs'!AJ40))="",FALSE,IF(ISERROR('Haq — Monthly P&L and cash'!K5<'Model inputs'!AJ40),'Haq — Monthly P&L and cash'!K5<'Model inputs'!AJ40,IF(OR('Haq — Monthly P&L and cash'!K5="",'Model inputs'!AJ40=""),"",'Haq — Monthly P&L and cash'!K5<'Model inputs'!AJ40))),0,IF(IF(IF(ISERROR('Haq — Monthly P&L and cash'!K5='Model inputs'!AJ40),'Haq — Monthly P&L and cash'!K5='Model inputs'!AJ40,IF(OR('Haq — Monthly P&L and cash'!K5="",'Model inputs'!AJ40=""),"",'Haq — Monthly P&L and cash'!K5='Model inputs'!AJ40))="",FALSE,IF(ISERROR('Haq — Monthly P&L and cash'!K5='Model inputs'!AJ40),'Haq — Monthly P&L and cash'!K5='Model inputs'!AJ40,IF(OR('Haq — Monthly P&L and cash'!K5="",'Model inputs'!AJ40=""),"",'Haq — Monthly P&L and cash'!K5='Model inputs'!AJ40))),IF('Model inputs'!AJ41="","",'Model inputs'!AJ41),'Haq — Monthly P&L and cash'!J7*(1+'Model inputs'!AJ37-'Model inputs'!AJ42))) -> 115.65304 | L7: =IF(IF(IF(ISERROR('Haq — Monthly P&L and cash'!L5<'Model inputs'!AJ40),'Haq — Monthly P&L and cash'!L5<'Model inputs'!AJ40,IF(OR('Haq — Monthly P&L and cash'!L5="",'Model inputs'!AJ40=""),"",'Haq — Monthly P&L and cash'!L5<'Model inputs'!AJ40))="",FALSE,IF(ISERROR('Haq — Monthly P&L and cash'!L5<'Model inputs'!AJ40),'Haq — Monthly P&L and cash'!L5<'Model inputs'!AJ40,IF(OR('Haq — Monthly P&L and cash'!L5="",'Model inputs'!AJ40=""),"",'Haq — Monthly P&L and cash'!L5<'Model inputs'!AJ40))),0,IF(IF(IF(ISERROR('Haq — Monthly P&L and cash'!L5='Model inputs'!AJ40),'Haq — Monthly P&L and cash'!L5='Model inputs'!AJ40,IF(OR('Haq — Monthly P&L and cash'!L5="",'Model inputs'!AJ40=""),"",'Haq — Monthly P&L and cash'!L5='Model inputs'!AJ40))="",FALSE,IF(ISERROR('Haq — Monthly P&L and cash'!L5='Model inputs'!AJ40),'Haq — Monthly P&L and cash'!L5='Model inputs'!AJ40,IF(OR('Haq — Monthly P&L and cash'!L5="",'Model inputs'!AJ40=""),"",'Haq — Monthly P&L and cash'!L5='Model inputs'!AJ40))),IF('Model inputs'!AJ41="","",'Model inputs'!AJ41),'Haq — Monthly P&L and cash'!K7*(1+'Model inputs'!AJ37-'Model inputs'!AJ42))) -> 133.00099 | M7: =IF(IF(IF(ISERROR('Haq — Monthly P&L and cash'!M5<'Model inputs'!AJ40),'Haq — Monthly P&L and cash'!M5<'Model inputs'!AJ40,IF(OR('Haq — Monthly P&L and cash'!M5="",'Model inputs'!AJ40=""),"",'Haq — Monthly P&L and cash'!M5<'Model inputs'!AJ40))="",FALSE,IF(ISERROR('Haq — Monthly P&L and cash'!M5<'Model inputs'!AJ40),'Haq — Monthly P&L and cash'!M5<'Model inputs'!AJ40,IF(OR('Haq — Monthly P&L and cash'!M5="",'Model inputs'!AJ40=""),"",'Haq — Monthly P&L and cash'!M5<'Model inputs'!AJ40))),0,IF(IF(IF(ISERROR('Haq — Monthly P&L and cash'!M5='Model inputs'!AJ40),'Haq — Monthly P&L and cash'!M5='Model inputs'!AJ40,IF(OR('Haq — Monthly P&L and cash'!M5="",'Model inputs'!AJ40=""),"",'Haq — Monthly P&L and cash'!M5='Model inputs'!AJ40))="",FALSE,IF(ISERROR('Haq — Monthly P&L and cash'!M5='Model inputs'!AJ40),'Haq — Monthly P&L and cash'!M5='Model inputs'!AJ40,IF(OR('Haq — Monthly P&L and cash'!M5="",'Model inputs'!AJ40=""),"",'Haq — Monthly P&L and cash'!M5='Model inputs'!AJ40))),IF('Model inputs'!AJ41="","",'Model inputs'!AJ41),'Haq — Monthly P&L and cash'!L7*(1+'Model inputs'!AJ37-'Model inputs'!AJ42))) -> 152.95114 | N7: =IF(IF(IF(ISERROR('Haq — Monthly P&L and cash'!N5<'Model inputs'!AJ40),'Haq — Monthly P&L and cash'!N5<'Model inputs'!AJ40,IF(OR('Haq — Monthly P&L and cash'!N5="",'Model inputs'!AJ40=""),"",'Haq — Monthly P&L and cash'!N5<'Model inputs'!AJ40))="",FALSE,IF(ISERROR('Haq — Monthly P&L and cash'!N5<'Model inputs'!AJ40),'Haq — Monthly P&L and cash'!N5<'Model inputs'!AJ40,IF(OR('Haq — Monthly P&L and cash'!N5="",'Model inputs'!AJ40=""),"",'Haq — Monthly P&L and cash'!N5<'Model inputs'!AJ40))),0,IF(IF(IF(ISERROR('Haq — Monthly P&L and cash'!N5='Model inputs'!AJ40),'Haq — Monthly P&L and cash'!N5='Model inputs'!AJ40,IF(OR('Haq — Monthly P&L and cash'!N5="",'Model inputs'!AJ40=""),"",'Haq — Monthly P&L and cash'!N5='Model inputs'!AJ40))="",FALSE,IF(ISERROR('Haq — Monthly P&L and cash'!N5='Model inputs'!AJ40),'Haq — Monthly P&L and cash'!N5='Model inputs'!AJ40,IF(OR('Haq — Monthly P&L and cash'!N5="",'Model inputs'!AJ40=""),"",'Haq — Monthly P&L and cash'!N5='Model inputs'!AJ40))),IF('Model inputs'!AJ41="","",'Model inputs'!AJ41),'Haq — Monthly P&L and cash'!M7*(1+'Model inputs'!AJ37-'Model inputs'!AJ42))) -> 175.89381 | O7: =IF(IF(IF(ISERROR('Haq — Monthly P&L and cash'!O5<'Model inputs'!AJ40),'Haq — Monthly P&L and cash'!O5<'Model inputs'!AJ40,IF(OR('Haq — Monthly P&L and cash'!O5="",'Model inputs'!AJ40=""),"",'Haq — Monthly P&L and cash'!O5<'Model inputs'!AJ40))="",FALSE,IF(ISERROR('Haq — Monthly P&L and cash'!O5<'Model inputs'!AJ40),'Haq — Monthly P&L and cash'!O5<'Model inputs'!AJ40,IF(OR('Haq — Monthly P&L and cash'!O5="",'Model inputs'!AJ40=""),"",'Haq — Monthly P&L and cash'!O5<'Model inputs'!AJ40))),0,IF(IF(IF(ISERROR('Haq — Monthly P&L and cash'!O5='Model inputs'!AJ40),'Haq — Monthly P&L and cash'!O5='Model inputs'!AJ40,IF(OR('Haq — Monthly P&L and cash'!O5="",'Model inputs'!AJ40=""),"",'Haq — Monthly P&L and cash'!O5='Model inputs'!AJ40))="",FALSE,IF(ISERROR('Haq — Monthly P&L and cash'!O5='Model inputs'!AJ40),'Haq — Monthly P&L and cash'!O5='Model inputs'!AJ40,IF(OR('Haq — Monthly P&L and cash'!O5="",'Model inputs'!AJ40=""),"",'Haq — Monthly P&L and cash'!O5='Model inputs'!AJ40))),IF('Model inputs'!AJ41="","",'Model inputs'!AJ41),'Haq — Monthly P&L and cash'!N7*(1+'Model inputs'!AJ37-'Model inputs'!AJ42))) -> 202.27789 | P7: =IF(IF(IF(ISERROR('Haq — Monthly P&L and cash'!P5<'Model inputs'!AJ40),'Haq — Monthly P&L and cash'!P5<'Model inputs'!AJ40,IF(OR('Haq — Monthly P&L and cash'!P5="",'Model inputs'!AJ40=""),"",'Haq — Monthly P&L and cash'!P5<'Model inputs'!AJ40))="",FALSE,IF(ISERROR('Haq — Monthly P&L and cash'!P5<'Model inputs'!AJ40),'Haq — Monthly P&L and cash'!P5<'Model inputs'!AJ40,IF(OR('Haq — Monthly P&L and cash'!P5="",'Model inputs'!AJ40=""),"",'Haq — Monthly P&L and cash'!P5<'Model inputs'!AJ40))),0,IF(IF(IF(ISERROR('Haq — Monthly P&L and cash'!P5='Model inputs'!AJ40),'Haq — Monthly P&L and cash'!P5='Model inputs'!AJ40,IF(OR('Haq — Monthly P&L and cash'!P5="",'Model inputs'!AJ40=""),"",'Haq — Monthly P&L and cash'!P5='Model inputs'!AJ40))="",FALSE,IF(ISERROR('Haq — Monthly P&L and cash'!P5='Model inputs'!AJ40),'Haq — Monthly P&L and cash'!P5='Model inputs'!AJ40,IF(OR('Haq — Monthly P&L and cash'!P5="",'Model inputs'!AJ40=""),"",'Haq — Monthly P&L and cash'!P5='Model inputs'!AJ40))),IF('Model inputs'!AJ41="","",'Model inputs'!AJ41),'Haq — Monthly P&L and cash'!O7*(1+'Model inputs'!AJ37-'Model inputs'!AJ42))) -> 232.61957 | Q7: =IF(IF(IF(ISERROR('Haq — Monthly P&L and cash'!Q5<'Model inputs'!AJ40),'Haq — Monthly P&L and cash'!Q5<'Model inputs'!AJ40,IF(OR('Haq — Monthly P&L and cash'!Q5="",'Model inputs'!AJ40=""),"",'Haq — Monthly P&L and cash'!Q5<'Model inputs'!AJ40))="",FALSE,IF(ISERROR('Haq — Monthly P&L and cash'!Q5<'Model inputs'!AJ40),'Haq — Monthly P&L and cash'!Q5<'Model inputs'!AJ40,IF(OR('Haq — Monthly P&L and cash'!Q5="",'Model inputs'!AJ40=""),"",'Haq — Monthly P&L and cash'!Q5<'Model inputs'!AJ40))),0,IF(IF(IF(ISERROR('Haq — Monthly P&L and cash'!Q5='Model inputs'!AJ40),'Haq — Monthly P&L and cash'!Q5='Model inputs'!AJ40,IF(OR('Haq — Monthly P&L and cash'!Q5="",'Model inputs'!AJ40=""),"",'Haq — Monthly P&L and cash'!Q5='Model inputs'!AJ40))="",FALSE,IF(ISERROR('Haq — Monthly P&L and cash'!Q5='Model inputs'!AJ40),'Haq — Monthly P&L and cash'!Q5='Model inputs'!AJ40,IF(OR('Haq — Monthly P&L and cash'!Q5="",'Model inputs'!AJ40=""),"",'Haq — Monthly P&L and cash'!Q5='Model inputs'!AJ40))),IF('Model inputs'!AJ41="","",'Model inputs'!AJ41),'Haq — Monthly P&L and cash'!P7*(1+'Model inputs'!AJ37-'Model inputs'!AJ42))) -> 267.51251 | R7: =IF(IF(IF(ISERROR('Haq — Monthly P&L and cash'!R5<'Model inputs'!AJ40),'Haq — Monthly P&L and cash'!R5<'Model inputs'!AJ40,IF(OR('Haq — Monthly P&L and cash'!R5="",'Model inputs'!AJ40=""),"",'Haq — Monthly P&L and cash'!R5<'Model inputs'!AJ40))="",FALSE,IF(ISERROR('Haq — Monthly P&L and cash'!R5<'Model inputs'!AJ40),'Haq — Monthly P&L and cash'!R5<'Model inputs'!AJ40,IF(OR('Haq — Monthly P&L and cash'!R5="",'Model inputs'!AJ40=""),"",'Haq — Monthly P&L and cash'!R5<'Model inputs'!AJ40))),0,IF(IF(IF(ISERROR('Haq — Monthly P&L and cash'!R5='Model inputs'!AJ40),'Haq — Monthly P&L and cash'!R5='Model inputs'!AJ40,IF(OR('Haq — Monthly P&L and cash'!R5="",'Model inputs'!AJ40=""),"",'Haq — Monthly P&L and cash'!R5='Model inputs'!AJ40))="",FALSE,IF(ISERROR('Haq — Monthly P&L and cash'!R5='Model inputs'!AJ40),'Haq — Monthly P&L and cash'!R5='Model inputs'!AJ40,IF(OR('Haq — Monthly P&L and cash'!R5="",'Model inputs'!AJ40=""),"",'Haq — Monthly P&L and cash'!R5='Model inputs'!AJ40))),IF('Model inputs'!AJ41="","",'Model inputs'!AJ41),'Haq — Monthly P&L and cash'!Q7*(1+'Model inputs'!AJ37-'Model inputs'!AJ42))) -> 307.63938 | S7: =IF(IF(IF(ISERROR('Haq — Monthly P&L and cash'!S5<'Model inputs'!AJ40),'Haq — Monthly P&L and cash'!S5<'Model inputs'!AJ40,IF(OR('Haq — Monthly P&L and cash'!S5="",'Model inputs'!AJ40=""),"",'Haq — Monthly P&L and cash'!S5<'Model inputs'!AJ40))="",FALSE,IF(ISERROR('Haq — Monthly P&L and cash'!S5<'Model inputs'!AJ40),'Haq — Monthly P&L and cash'!S5<'Model inputs'!AJ40,IF(OR('Haq — Monthly P&L and cash'!S5="",'Model inputs'!AJ40=""),"",'Haq — Monthly P&L and cash'!S5<'Model inputs'!AJ40))),0,IF(IF(IF(ISERROR('Haq — Monthly P&L and cash'!S5='Model inputs'!AJ40),'Haq — Monthly P&L and cash'!S5='Model inputs'!AJ40,IF(OR('Haq — Monthly P&L and cash'!S5="",'Model inputs'!AJ40=""),"",'Haq — Monthly P&L and cash'!S5='Model inputs'!AJ40))="",FALSE,IF(ISERROR('Haq — Monthly P&L and cash'!S5='Model inputs'!AJ40),'Haq — Monthly P&L and cash'!S5='Model inputs'!AJ40,IF(OR('Haq — Monthly P&L and cash'!S5="",'Model inputs'!AJ40=""),"",'Haq — Monthly P&L and cash'!S5='Model inputs'!AJ40))),IF('Model inputs'!AJ41="","",'Model inputs'!AJ41),'Haq — Monthly P&L and cash'!R7*(1+'Model inputs'!AJ37-'Model inputs'!AJ42))) -> 353.78529 | T7: =IF(IF(IF(ISERROR('Haq — Monthly P&L and cash'!T5<'Model inputs'!AJ40),'Haq — Monthly P&L and cash'!T5<'Model inputs'!AJ40,IF(OR('Haq — Monthly P&L and cash'!T5="",'Model inputs'!AJ40=""),"",'Haq — Monthly P&L and cash'!T5<'Model inputs'!AJ40))="",FALSE,IF(ISERROR('Haq — Monthly P&L and cash'!T5<'Model inputs'!AJ40),'Haq — Monthly P&L and cash'!T5<'Model inputs'!AJ40,IF(OR('Haq — Monthly P&L and cash'!T5="",'Model inputs'!AJ40=""),"",'Haq — Monthly P&L and cash'!T5<'Model inputs'!AJ40))),0,IF(IF(IF(ISERROR('Haq — Monthly P&L and cash'!T5='Model inputs'!AJ40),'Haq — Monthly P&L and cash'!T5='Model inputs'!AJ40,IF(OR('Haq — Monthly P&L and cash'!T5="",'Model inputs'!AJ40=""),"",'Haq — Monthly P&L and cash'!T5='Model inputs'!AJ40))="",FALSE,IF(ISERROR('Haq — Monthly P&L and cash'!T5='Model inputs'!AJ40),'Haq — Monthly P&L and cash'!T5='Model inputs'!AJ40,IF(OR('Haq — Monthly P&L and cash'!T5="",'Model inputs'!AJ40=""),"",'Haq — Monthly P&L and cash'!T5='Model inputs'!AJ40))),IF('Model inputs'!AJ41="","",'Model inputs'!AJ41),'Haq — Monthly P&L and cash'!S7*(1+'Model inputs'!AJ37-'Model inputs'!AJ42))) -> 406.85308 | U7: =IF(IF(IF(ISERROR('Haq — Monthly P&L and cash'!U5<'Model inputs'!AJ40),'Haq — Monthly P&L and cash'!U5<'Model inputs'!AJ40,IF(OR('Haq — Monthly P&L and cash'!U5="",'Model inputs'!AJ40=""),"",'Haq — Monthly P&L and cash'!U5<'Model inputs'!AJ40))="",FALSE,IF(ISERROR('Haq — Monthly P&L and cash'!U5<'Model inputs'!AJ40),'Haq — Monthly P&L and cash'!U5<'Model inputs'!AJ40,IF(OR('Haq — Monthly P&L and cash'!U5="",'Model inputs'!AJ40=""),"",'Haq — Monthly P&L and cash'!U5<'Model inputs'!AJ40))),0,IF(IF(IF(ISERROR('Haq — Monthly P&L and cash'!U5='Model inputs'!AJ40),'Haq — Monthly P&L and cash'!U5='Model inputs'!AJ40,IF(OR('Haq — Monthly P&L and cash'!U5="",'Model inputs'!AJ40=""),"",'Haq — Monthly P&L and cash'!U5='Model inputs'!AJ40))="",FALSE,IF(ISERROR('Haq — Monthly P&L and cash'!U5='Model inputs'!AJ40),'Haq — Monthly P&L and cash'!U5='Model inputs'!AJ40,IF(OR('Haq — Monthly P&L and cash'!U5="",'Model inputs'!AJ40=""),"",'Haq — Monthly P&L and cash'!U5='Model inputs'!AJ40))),IF('Model inputs'!AJ41="","",'Model inputs'!AJ41),'Haq — Monthly P&L and cash'!T7*(1+'Model inputs'!AJ37-'Model inputs'!AJ42))) -> 467.88104 | V7: =IF(IF(IF(ISERROR('Haq — Monthly P&L and cash'!V5<'Model inputs'!AJ40),'Haq — Monthly P&L and cash'!V5<'Model inputs'!AJ40,IF(OR('Haq — Monthly P&L and cash'!V5="",'Model inputs'!AJ40=""),"",'Haq — Monthly P&L and cash'!V5<'Model inputs'!AJ40))="",FALSE,IF(ISERROR('Haq — Monthly P&L and cash'!V5<'Model inputs'!AJ40),'Haq — Monthly P&L and cash'!V5<'Model inputs'!AJ40,IF(OR('Haq — Monthly P&L and cash'!V5="",'Model inputs'!AJ40=""),"",'Haq — Monthly P&L and cash'!V5<'Model inputs'!AJ40))),0,IF(IF(IF(ISERROR('Haq — Monthly P&L and cash'!V5='Model inputs'!AJ40),'Haq — Monthly P&L and cash'!V5='Model inputs'!AJ40,IF(OR('Haq — Monthly P&L and cash'!V5="",'Model inputs'!AJ40=""),"",'Haq — Monthly P&L and cash'!V5='Model inputs'!AJ40))="",FALSE,IF(ISERROR('Haq — Monthly P&L and cash'!V5='Model inputs'!AJ40),'Haq — Monthly P&L and cash'!V5='Model inputs'!AJ40,IF(OR('Haq — Monthly P&L and cash'!V5="",'Model inputs'!AJ40=""),"",'Haq — Monthly P&L and cash'!V5='Model inputs'!AJ40))),IF('Model inputs'!AJ41="","",'Model inputs'!AJ41),'Haq — Monthly P&L and cash'!U7*(1+'Model inputs'!AJ37-'Model inputs'!AJ42))) -> 538.0632 | W7: =IF(IF(IF(ISERROR('Haq — Monthly P&L and cash'!W5<'Model inputs'!AJ40),'Haq — Monthly P&L and cash'!W5<'Model inputs'!AJ40,IF(OR('Haq — Monthly P&L and cash'!W5="",'Model inputs'!AJ40=""),"",'Haq — Monthly P&L and cash'!W5<'Model inputs'!AJ40))="",FALSE,IF(ISERROR('Haq — Monthly P&L and cash'!W5<'Model inputs'!AJ40),'Haq — Monthly P&L and cash'!W5<'Model inputs'!AJ40,IF(OR('Haq — Monthly P&L and cash'!W5="",'Model inputs'!AJ40=""),"",'Haq — Monthly P&L and cash'!W5<'Model inputs'!AJ40))),0,IF(IF(IF(ISERROR('Haq — Monthly P&L and cash'!W5='Model inputs'!AJ40),'Haq — Monthly P&L and cash'!W5='Model inputs'!AJ40,IF(OR('Haq — Monthly P&L and cash'!W5="",'Model inputs'!AJ40=""),"",'Haq — Monthly P&L and cash'!W5='Model inputs'!AJ40))="",FALSE,IF(ISERROR('Haq — Monthly P&L and cash'!W5='Model inputs'!AJ40),'Haq — Monthly P&L and cash'!W5='Model inputs'!AJ40,IF(OR('Haq — Monthly P&L and cash'!W5="",'Model inputs'!AJ40=""),"",'Haq — Monthly P&L and cash'!W5='Model inputs'!AJ40))),IF('Model inputs'!AJ41="","",'Model inputs'!AJ41),'Haq — Monthly P&L and cash'!V7*(1+'Model inputs'!AJ37-'Model inputs'!AJ42))) -> 618.77268 | X7: =IF(IF(IF(ISERROR('Haq — Monthly P&L and cash'!X5<'Model inputs'!AJ40),'Haq — Monthly P&L and cash'!X5<'Model inputs'!AJ40,IF(OR('Haq — Monthly P&L and cash'!X5="",'Model inputs'!AJ40=""),"",'Haq — Monthly P&L and cash'!X5<'Model inputs'!AJ40))="",FALSE,IF(ISERROR('Haq — Monthly P&L and cash'!X5<'Model inputs'!AJ40),'Haq — Monthly P&L and cash'!X5<'Model inputs'!AJ40,IF(OR('Haq — Monthly P&L and cash'!X5="",'Model inputs'!AJ40=""),"",'Haq — Monthly P&L and cash'!X5<'Model inputs'!AJ40))),0,IF(IF(IF(ISERROR('Haq — Monthly P&L and cash'!X5='Model inputs'!AJ40),'Haq — Monthly P&L and cash'!X5='Model inputs'!AJ40,IF(OR('Haq — Monthly P&L and cash'!X5="",'Model inputs'!AJ40=""),"",'Haq — Monthly P&L and cash'!X5='Model inputs'!AJ40))="",FALSE,IF(ISERROR('Haq — Monthly P&L and cash'!X5='Model inputs'!AJ40),'Haq — Monthly P&L and cash'!X5='Model inputs'!AJ40,IF(OR('Haq — Monthly P&L and cash'!X5="",'Model inputs'!AJ40=""),"",'Haq — Monthly P&L and cash'!X5='Model inputs'!AJ40))),IF('Model inputs'!AJ41="","",'Model inputs'!AJ41),'Haq — Monthly P&L and cash'!W7*(1+'Model inputs'!AJ37-'Model inputs'!AJ42))) -> 711.58858 | Y7: =IF(IF(IF(ISERROR('Haq — Monthly P&L and cash'!Y5<'Model inputs'!AJ40),'Haq — Monthly P&L and cash'!Y5<'Model inputs'!AJ40,IF(OR('Haq — Monthly P&L and cash'!Y5="",'Model inputs'!AJ40=""),"",'Haq — Monthly P&L and cash'!Y5<'Model inputs'!AJ40))="",FALSE,IF(ISERROR('Haq — Monthly P&L and cash'!Y5<'Model inputs'!AJ40),'Haq — Monthly P&L and cash'!Y5<'Model inputs'!AJ40,IF(OR('Haq — Monthly P&L and cash'!Y5="",'Model inputs'!AJ40=""),"",'Haq — Monthly P&L and cash'!Y5<'Model inputs'!AJ40))),0,IF(IF(IF(ISERROR('Haq — Monthly P&L and cash'!Y5='Model inputs'!AJ40),'Haq — Monthly P&L and cash'!Y5='Model inputs'!AJ40,IF(OR('Haq — Monthly P&L and cash'!Y5="",'Model inputs'!AJ40=""),"",'Haq — Monthly P&L and cash'!Y5='Model inputs'!AJ40))="",FALSE,IF(ISERROR('Haq — Monthly P&L and cash'!Y5='Model inputs'!AJ40),'Haq — Monthly P&L and cash'!Y5='Model inputs'!AJ40,IF(OR('Haq — Monthly P&L and cash'!Y5="",'Model inputs'!AJ40=""),"",'Haq — Monthly P&L and cash'!Y5='Model inputs'!AJ40))),IF('Model inputs'!AJ41="","",'Model inputs'!AJ41),'Haq — Monthly P&L and cash'!X7*(1+'Model inputs'!AJ37-'Model inputs'!AJ42))) -> 818.32687
A8: Haq CSC new operators | B8: =IF(IF(IF(ISERROR('Haq — Monthly P&L and cash'!B5='Model inputs'!AJ40),'Haq — Monthly P&L and cash'!B5='Model inputs'!AJ40,IF(OR('Haq — Monthly P&L and cash'!B5="",'Model inputs'!AJ40=""),"",'Haq — Monthly P&L and cash'!B5='Model inputs'!AJ40))="",FALSE,IF(ISERROR('Haq — Monthly P&L and cash'!B5='Model inputs'!AJ40),'Haq — Monthly P&L and cash'!B5='Model inputs'!AJ40,IF(OR('Haq — Monthly P&L and cash'!B5="",'Model inputs'!AJ40=""),"",'Haq — Monthly P&L and cash'!B5='Model inputs'!AJ40))),IF('Model inputs'!AJ41="","",'Model inputs'!AJ41),IF(IF(IF(ISERROR('Haq — Monthly P&L and cash'!B5>'Model inputs'!AJ40),'Haq — Monthly P&L and cash'!B5>'Model inputs'!AJ40,IF(OR('Haq — Monthly P&L and cash'!B5="",'Model inputs'!AJ40=""),"",'Haq — Monthly P&L and cash'!B5>'Model inputs'!AJ40))="",FALSE,IF(ISERROR('Haq — Monthly P&L and cash'!B5>'Model inputs'!AJ40),'Haq — Monthly P&L and cash'!B5>'Model inputs'!AJ40,IF(OR('Haq — Monthly P&L and cash'!B5="",'Model inputs'!AJ40=""),"",'Haq — Monthly P&L and cash'!B5>'Model inputs'!AJ40))),'Model inputs'!C14*'Model inputs'!AJ37,0)) -> 0 | C8: =IF(IF(IF(ISERROR('Haq — Monthly P&L and cash'!C5='Model inputs'!AJ40),'Haq — Monthly P&L and cash'!C5='Model inputs'!AJ40,IF(OR('Haq — Monthly P&L and cash'!C5="",'Model inputs'!AJ40=""),"",'Haq — Monthly P&L and cash'!C5='Model inputs'!AJ40))="",FALSE,IF(ISERROR('Haq — Monthly P&L and cash'!C5='Model inputs'!AJ40),'Haq — Monthly P&L and cash'!C5='Model inputs'!AJ40,IF(OR('Haq — Monthly P&L and cash'!C5="",'Model inputs'!AJ40=""),"",'Haq — Monthly P&L and cash'!C5='Model inputs'!AJ40))),IF('Model inputs'!AJ41="","",'Model inputs'!AJ41),IF(IF(IF(ISERROR('Haq — Monthly P&L and cash'!C5>'Model inputs'!AJ40),'Haq — Monthly P&L and cash'!C5>'Model inputs'!AJ40,IF(OR('Haq — Monthly P&L and cash'!C5="",'Model inputs'!AJ40=""),"",'Haq — Monthly P&L and cash'!C5>'Model inputs'!AJ40))="",FALSE,IF(ISERROR('Haq — Monthly P&L and cash'!C5>'Model inputs'!AJ40),'Haq — Monthly P&L and cash'!C5>'Model inputs'!AJ40,IF(OR('Haq — Monthly P&L and cash'!C5="",'Model inputs'!AJ40=""),"",'Haq — Monthly P&L and cash'!C5>'Model inputs'!AJ40))),'Haq — Monthly P&L and cash'!B7*'Model inputs'!AJ37,0)) -> 0 | D8: =IF(IF(IF(ISERROR('Haq — Monthly P&L and cash'!D5='Model inputs'!AJ40),'Haq — Monthly P&L and cash'!D5='Model inputs'!AJ40,IF(OR('Haq — Monthly P&L and cash'!D5="",'Model inputs'!AJ40=""),"",'Haq — Monthly P&L and cash'!D5='Model inputs'!AJ40))="",FALSE,IF(ISERROR('Haq — Monthly P&L and cash'!D5='Model inputs'!AJ40),'Haq — Monthly P&L and cash'!D5='Model inputs'!AJ40,IF(OR('Haq — Monthly P&L and cash'!D5="",'Model inputs'!AJ40=""),"",'Haq — Monthly P&L and cash'!D5='Model inputs'!AJ40))),IF('Model inputs'!AJ41="","",'Model inputs'!AJ41),IF(IF(IF(ISERROR('Haq — Monthly P&L and cash'!D5>'Model inputs'!AJ40),'Haq — Monthly P&L and cash'!D5>'Model inputs'!AJ40,IF(OR('Haq — Monthly P&L and cash'!D5="",'Model inputs'!AJ40=""),"",'Haq — Monthly P&L and cash'!D5>'Model inputs'!AJ40))="",FALSE,IF(ISERROR('Haq — Monthly P&L and cash'!D5>'Model inputs'!AJ40),'Haq — Monthly P&L and cash'!D5>'Model inputs'!AJ40,IF(OR('Haq — Monthly P&L and cash'!D5="",'Model inputs'!AJ40=""),"",'Haq — Monthly P&L and cash'!D5>'Model inputs'!AJ40))),'Haq — Monthly P&L and cash'!C7*'Model inputs'!AJ37,0)) -> 0 | E8: =IF(IF(IF(ISERROR('Haq — Monthly P&L and cash'!E5='Model inputs'!AJ40),'Haq — Monthly P&L and cash'!E5='Model inputs'!AJ40,IF(OR('Haq — Monthly P&L and cash'!E5="",'Model inputs'!AJ40=""),"",'Haq — Monthly P&L and cash'!E5='Model inputs'!AJ40))="",FALSE,IF(ISERROR('Haq — Monthly P&L and cash'!E5='Model inputs'!AJ40),'Haq — Monthly P&L and cash'!E5='Model inputs'!AJ40,IF(OR('Haq — Monthly P&L and cash'!E5="",'Model inputs'!AJ40=""),"",'Haq — Monthly P&L and cash'!E5='Model inputs'!AJ40))),IF('Model inputs'!AJ41="","",'Model inputs'!AJ41),IF(IF(IF(ISERROR('Haq — Monthly P&L and cash'!E5>'Model inputs'!AJ40),'Haq — Monthly P&L and cash'!E5>'Model inputs'!AJ40,IF(OR('Haq — Monthly P&L and cash'!E5="",'Model inputs'!AJ40=""),"",'Haq — Monthly P&L and cash'!E5>'Model inputs'!AJ40))="",FALSE,IF(ISERROR('Haq — Monthly P&L and cash'!E5>'Model inputs'!AJ40),'Haq — Monthly P&L and cash'!E5>'Model inputs'!AJ40,IF(OR('Haq — Monthly P&L and cash'!E5="",'Model inputs'!AJ40=""),"",'Haq — Monthly P&L and cash'!E5>'Model inputs'!AJ40))),'Haq — Monthly P&L and cash'!D7*'Model inputs'!AJ37,0)) -> 50 | F8: =IF(IF(IF(ISERROR('Haq — Monthly P&L and cash'!F5='Model inputs'!AJ40),'Haq — Monthly P&L and cash'!F5='Model inputs'!AJ40,IF(OR('Haq — Monthly P&L and cash'!F5="",'Model inputs'!AJ40=""),"",'Haq — Monthly P&L and cash'!F5='Model inputs'!AJ40))="",FALSE,IF(ISERROR('Haq — Monthly P&L and cash'!F5='Model inputs'!AJ40),'Haq — Monthly P&L and cash'!F5='Model inputs'!AJ40,IF(OR('Haq — Monthly P&L and cash'!F5="",'Model inputs'!AJ40=""),"",'Haq — Monthly P&L and cash'!F5='Model inputs'!AJ40))),IF('Model inputs'!AJ41="","",'Model inputs'!AJ41),IF(IF(IF(ISERROR('Haq — Monthly P&L and cash'!F5>'Model inputs'!AJ40),'Haq — Monthly P&L and cash'!F5>'Model inputs'!AJ40,IF(OR('Haq — Monthly P&L and cash'!F5="",'Model inputs'!AJ40=""),"",'Haq — Monthly P&L and cash'!F5>'Model inputs'!AJ40))="",FALSE,IF(ISERROR('Haq — Monthly P&L and cash'!F5>'Model inputs'!AJ40),'Haq — Monthly P&L and cash'!F5>'Model inputs'!AJ40,IF(OR('Haq — Monthly P&L and cash'!F5="",'Model inputs'!AJ40=""),"",'Haq — Monthly P&L and cash'!F5>'Model inputs'!AJ40))),'Haq — Monthly P&L and cash'!E7*'Model inputs'!AJ37,0)) -> 10 | G8: =IF(IF(IF(ISERROR('Haq — Monthly P&L and cash'!G5='Model inputs'!AJ40),'Haq — Monthly P&L and cash'!G5='Model inputs'!AJ40,IF(OR('Haq — Monthly P&L and cash'!G5="",'Model inputs'!AJ40=""),"",'Haq — Monthly P&L and cash'!G5='Model inputs'!AJ40))="",FALSE,IF(ISERROR('Haq — Monthly P&L and cash'!G5='Model inputs'!AJ40),'Haq — Monthly P&L and cash'!G5='Model inputs'!AJ40,IF(OR('Haq — Monthly P&L and cash'!G5="",'Model inputs'!AJ40=""),"",'Haq — Monthly P&L and cash'!G5='Model inputs'!AJ40))),IF('Model inputs'!AJ41="","",'Model inputs'!AJ41),IF(IF(IF(ISERROR('Haq — Monthly P&L and cash'!G5>'Model inputs'!AJ40),'Haq — Monthly P&L and cash'!G5>'Model inputs'!AJ40,IF(OR('Haq — Monthly P&L and cash'!G5="",'Model inputs'!AJ40=""),"",'Haq — Monthly P&L and cash'!G5>'Model inputs'!AJ40))="",FALSE,IF(ISERROR('Haq — Monthly P&L and cash'!G5>'Model inputs'!AJ40),'Haq — Monthly P&L and cash'!G5>'Model inputs'!AJ40,IF(OR('Haq — Monthly P&L and cash'!G5="",'Model inputs'!AJ40=""),"",'Haq — Monthly P&L and cash'!G5>'Model inputs'!AJ40))),'Haq — Monthly P&L and cash'!F7*'Model inputs'!AJ37,0)) -> 11.5 | H8: =IF(IF(IF(ISERROR('Haq — Monthly P&L and cash'!H5='Model inputs'!AJ40),'Haq — Monthly P&L and cash'!H5='Model inputs'!AJ40,IF(OR('Haq — Monthly P&L and cash'!H5="",'Model inputs'!AJ40=""),"",'Haq — Monthly P&L and cash'!H5='Model inputs'!AJ40))="",FALSE,IF(ISERROR('Haq — Monthly P&L and cash'!H5='Model inputs'!AJ40),'Haq — Monthly P&L and cash'!H5='Model inputs'!AJ40,IF(OR('Haq — Monthly P&L and cash'!H5="",'Model inputs'!AJ40=""),"",'Haq — Monthly P&L and cash'!H5='Model inputs'!AJ40))),IF('Model inputs'!AJ41="","",'Model inputs'!AJ41),IF(IF(IF(ISERROR('Haq — Monthly P&L and cash'!H5>'Model inputs'!AJ40),'Haq — Monthly P&L and cash'!H5>'Model inputs'!AJ40,IF(OR('Haq — Monthly P&L and cash'!H5="",'Model inputs'!AJ40=""),"",'Haq — Monthly P&L and cash'!H5>'Model inputs'!AJ40))="",FALSE,IF(ISERROR('Haq — Monthly P&L and cash'!H5>'Model inputs'!AJ40),'Haq — Monthly P&L and cash'!H5>'Model inputs'!AJ40,IF(OR('Haq — Monthly P&L and cash'!H5="",'Model inputs'!AJ40=""),"",'Haq — Monthly P&L and cash'!H5>'Model inputs'!AJ40))),'Haq — Monthly P&L and cash'!G7*'Model inputs'!AJ37,0)) -> 13.225 | I8: =IF(IF(IF(ISERROR('Haq — Monthly P&L and cash'!I5='Model inputs'!AJ40),'Haq — Monthly P&L and cash'!I5='Model inputs'!AJ40,IF(OR('Haq — Monthly P&L and cash'!I5="",'Model inputs'!AJ40=""),"",'Haq — Monthly P&L and cash'!I5='Model inputs'!AJ40))="",FALSE,IF(ISERROR('Haq — Monthly P&L and cash'!I5='Model inputs'!AJ40),'Haq — Monthly P&L and cash'!I5='Model inputs'!AJ40,IF(OR('Haq — Monthly P&L and cash'!I5="",'Model inputs'!AJ40=""),"",'Haq — Monthly P&L and cash'!I5='Model inputs'!AJ40))),IF('Model inputs'!AJ41="","",'Model inputs'!AJ41),IF(IF(IF(ISERROR('Haq — Monthly P&L and cash'!I5>'Model inputs'!AJ40),'Haq — Monthly P&L and cash'!I5>'Model inputs'!AJ40,IF(OR('Haq — Monthly P&L and cash'!I5="",'Model inputs'!AJ40=""),"",'Haq — Monthly P&L and cash'!I5>'Model inputs'!AJ40))="",FALSE,IF(ISERROR('Haq — Monthly P&L and cash'!I5>'Model inputs'!AJ40),'Haq — Monthly P&L and cash'!I5>'Model inputs'!AJ40,IF(OR('Haq — Monthly P&L and cash'!I5="",'Model inputs'!AJ40=""),"",'Haq — Monthly P&L and cash'!I5>'Model inputs'!AJ40))),'Haq — Monthly P&L and cash'!H7*'Model inputs'!AJ37,0)) -> 15.20875 | J8: =IF(IF(IF(ISERROR('Haq — Monthly P&L and cash'!J5='Model inputs'!AJ40),'Haq — Monthly P&L and cash'!J5='Model inputs'!AJ40,IF(OR('Haq — Monthly P&L and cash'!J5="",'Model inputs'!AJ40=""),"",'Haq — Monthly P&L and cash'!J5='Model inputs'!AJ40))="",FALSE,IF(ISERROR('Haq — Monthly P&L and cash'!J5='Model inputs'!AJ40),'Haq — Monthly P&L and cash'!J5='Model inputs'!AJ40,IF(OR('Haq — Monthly P&L and cash'!J5="",'Model inputs'!AJ40=""),"",'Haq — Monthly P&L and cash'!J5='Model inputs'!AJ40))),IF('Model inputs'!AJ41="","",'Model inputs'!AJ41),IF(IF(IF(ISERROR('Haq — Monthly P&L and cash'!J5>'Model inputs'!AJ40),'Haq — Monthly P&L and cash'!J5>'Model inputs'!AJ40,IF(OR('Haq — Monthly P&L and cash'!J5="",'Model inputs'!AJ40=""),"",'Haq — Monthly P&L and cash'!J5>'Model inputs'!AJ40))="",FALSE,IF(ISERROR('Haq — Monthly P&L and cash'!J5>'Model inputs'!AJ40),'Haq — Monthly P&L and cash'!J5>'Model inputs'!AJ40,IF(OR('Haq — Monthly P&L and cash'!J5="",'Model inputs'!AJ40=""),"",'Haq — Monthly P&L and cash'!J5>'Model inputs'!AJ40))),'Haq — Monthly P&L and cash'!I7*'Model inputs'!AJ37,0)) -> 17.490062 | K8: =IF(IF(IF(ISERROR('Haq — Monthly P&L and cash'!K5='Model inputs'!AJ40),'Haq — Monthly P&L and cash'!K5='Model inputs'!AJ40,IF(OR('Haq — Monthly P&L and cash'!K5="",'Model inputs'!AJ40=""),"",'Haq — Monthly P&L and cash'!K5='Model inputs'!AJ40))="",FALSE,IF(ISERROR('Haq — Monthly P&L and cash'!K5='Model inputs'!AJ40),'Haq — Monthly P&L and cash'!K5='Model inputs'!AJ40,IF(OR('Haq — Monthly P&L and cash'!K5="",'Model inputs'!AJ40=""),"",'Haq — Monthly P&L and cash'!K5='Model inputs'!AJ40))),IF('Model inputs'!AJ41="","",'Model inputs'!AJ41),IF(IF(IF(ISERROR('Haq — Monthly P&L and cash'!K5>'Model inputs'!AJ40),'Haq — Monthly P&L and cash'!K5>'Model inputs'!AJ40,IF(OR('Haq — Monthly P&L and cash'!K5="",'Model inputs'!AJ40=""),"",'Haq — Monthly P&L and cash'!K5>'Model inputs'!AJ40))="",FALSE,IF(ISERROR('Haq — Monthly P&L and cash'!K5>'Model inputs'!AJ40),'Haq — Monthly P&L and cash'!K5>'Model inputs'!AJ40,IF(OR('Haq — Monthly P&L and cash'!K5="",'Model inputs'!AJ40=""),"",'Haq — Monthly P&L and cash'!K5>'Model inputs'!AJ40))),'Haq — Monthly P&L and cash'!J7*'Model inputs'!AJ37,0)) -> 20.113572 | L8: =IF(IF(IF(ISERROR('Haq — Monthly P&L and cash'!L5='Model inputs'!AJ40),'Haq — Monthly P&L and cash'!L5='Model inputs'!AJ40,IF(OR('Haq — Monthly P&L and cash'!L5="",'Model inputs'!AJ40=""),"",'Haq — Monthly P&L and cash'!L5='Model inputs'!AJ40))="",FALSE,IF(ISERROR('Haq — Monthly P&L and cash'!L5='Model inputs'!AJ40),'Haq — Monthly P&L and cash'!L5='Model inputs'!AJ40,IF(OR('Haq — Monthly P&L and cash'!L5="",'Model inputs'!AJ40=""),"",'Haq — Monthly P&L and cash'!L5='Model inputs'!AJ40))),IF('Model inputs'!AJ41="","",'Model inputs'!AJ41),IF(IF(IF(ISERROR('Haq — Monthly P&L and cash'!L5>'Model inputs'!AJ40),'Haq — Monthly P&L and cash'!L5>'Model inputs'!AJ40,IF(OR('Haq — Monthly P&L and cash'!L5="",'Model inputs'!AJ40=""),"",'Haq — Monthly P&L and cash'!L5>'Model inputs'!AJ40))="",FALSE,IF(ISERROR('Haq — Monthly P&L and cash'!L5>'Model inputs'!AJ40),'Haq — Monthly P&L and cash'!L5>'Model inputs'!AJ40,IF(OR('Haq — Monthly P&L and cash'!L5="",'Model inputs'!AJ40=""),"",'Haq — Monthly P&L and cash'!L5>'Model inputs'!AJ40))),'Haq — Monthly P&L and cash'!K7*'Model inputs'!AJ37,0)) -> 23.130608 | M8: =IF(IF(IF(ISERROR('Haq — Monthly P&L and cash'!M5='Model inputs'!AJ40),'Haq — Monthly P&L and cash'!M5='Model inputs'!AJ40,IF(OR('Haq — Monthly P&L and cash'!M5="",'Model inputs'!AJ40=""),"",'Haq — Monthly P&L and cash'!M5='Model inputs'!AJ40))="",FALSE,IF(ISERROR('Haq — Monthly P&L and cash'!M5='Model inputs'!AJ40),'Haq — Monthly P&L and cash'!M5='Model inputs'!AJ40,IF(OR('Haq — Monthly P&L and cash'!M5="",'Model inputs'!AJ40=""),"",'Haq — Monthly P&L and cash'!M5='Model inputs'!AJ40))),IF('Model inputs'!AJ41="","",'Model inputs'!AJ41),IF(IF(IF(ISERROR('Haq — Monthly P&L and cash'!M5>'Model inputs'!AJ40),'Haq — Monthly P&L and cash'!M5>'Model inputs'!AJ40,IF(OR('Haq — Monthly P&L and cash'!M5="",'Model inputs'!AJ40=""),"",'Haq — Monthly P&L and cash'!M5>'Model inputs'!AJ40))="",FALSE,IF(ISERROR('Haq — Monthly P&L and cash'!M5>'Model inputs'!AJ40),'Haq — Monthly P&L and cash'!M5>'Model inputs'!AJ40,IF(OR('Haq — Monthly P&L and cash'!M5="",'Model inputs'!AJ40=""),"",'Haq — Monthly P&L and cash'!M5>'Model inputs'!AJ40))),'Haq — Monthly P&L and cash'!L7*'Model inputs'!AJ37,0)) -> 26.600199 | N8: =IF(IF(IF(ISERROR('Haq — Monthly P&L and cash'!N5='Model inputs'!AJ40),'Haq — Monthly P&L and cash'!N5='Model inputs'!AJ40,IF(OR('Haq — Monthly P&L and cash'!N5="",'Model inputs'!AJ40=""),"",'Haq — Monthly P&L and cash'!N5='Model inputs'!AJ40))="",FALSE,IF(ISERROR('Haq — Monthly P&L and cash'!N5='Model inputs'!AJ40),'Haq — Monthly P&L and cash'!N5='Model inputs'!AJ40,IF(OR('Haq — Monthly P&L and cash'!N5="",'Model inputs'!AJ40=""),"",'Haq — Monthly P&L and cash'!N5='Model inputs'!AJ40))),IF('Model inputs'!AJ41="","",'Model inputs'!AJ41),IF(IF(IF(ISERROR('Haq — Monthly P&L and cash'!N5>'Model inputs'!AJ40),'Haq — Monthly P&L and cash'!N5>'Model inputs'!AJ40,IF(OR('Haq — Monthly P&L and cash'!N5="",'Model inputs'!AJ40=""),"",'Haq — Monthly P&L and cash'!N5>'Model inputs'!AJ40))="",FALSE,IF(ISERROR('Haq — Monthly P&L and cash'!N5>'Model inputs'!AJ40),'Haq — Monthly P&L and cash'!N5>'Model inputs'!AJ40,IF(OR('Haq — Monthly P&L and cash'!N5="",'Model inputs'!AJ40=""),"",'Haq — Monthly P&L and cash'!N5>'Model inputs'!AJ40))),'Haq — Monthly P&L and cash'!M7*'Model inputs'!AJ37,0)) -> 30.590229 | O8: =IF(IF(IF(ISERROR('Haq — Monthly P&L and cash'!O5='Model inputs'!AJ40),'Haq — Monthly P&L and cash'!O5='Model inputs'!AJ40,IF(OR('Haq — Monthly P&L and cash'!O5="",'Model inputs'!AJ40=""),"",'Haq — Monthly P&L and cash'!O5='Model inputs'!AJ40))="",FALSE,IF(ISERROR('Haq — Monthly P&L and cash'!O5='Model inputs'!AJ40),'Haq — Monthly P&L and cash'!O5='Model inputs'!AJ40,IF(OR('Haq — Monthly P&L and cash'!O5="",'Model inputs'!AJ40=""),"",'Haq — Monthly P&L and cash'!O5='Model inputs'!AJ40))),IF('Model inputs'!AJ41="","",'Model inputs'!AJ41),IF(IF(IF(ISERROR('Haq — Monthly P&L and cash'!O5>'Model inputs'!AJ40),'Haq — Monthly P&L and cash'!O5>'Model inputs'!AJ40,IF(OR('Haq — Monthly P&L and cash'!O5="",'Model inputs'!AJ40=""),"",'Haq — Monthly P&L and cash'!O5>'Model inputs'!AJ40))="",FALSE,IF(ISERROR('Haq — Monthly P&L and cash'!O5>'Model inputs'!AJ40),'Haq — Monthly P&L and cash'!O5>'Model inputs'!AJ40,IF(OR('Haq — Monthly P&L and cash'!O5="",'Model inputs'!AJ40=""),"",'Haq — Monthly P&L and cash'!O5>'Model inputs'!AJ40))),'Haq — Monthly P&L and cash'!N7*'Model inputs'!AJ37,0)) -> 35.178763 | P8: =IF(IF(IF(ISERROR('Haq — Monthly P&L and cash'!P5='Model inputs'!AJ40),'Haq — Monthly P&L and cash'!P5='Model inputs'!AJ40,IF(OR('Haq — Monthly P&L and cash'!P5="",'Model inputs'!AJ40=""),"",'Haq — Monthly P&L and cash'!P5='Model inputs'!AJ40))="",FALSE,IF(ISERROR('Haq — Monthly P&L and cash'!P5='Model inputs'!AJ40),'Haq — Monthly P&L and cash'!P5='Model inputs'!AJ40,IF(OR('Haq — Monthly P&L and cash'!P5="",'Model inputs'!AJ40=""),"",'Haq — Monthly P&L and cash'!P5='Model inputs'!AJ40))),IF('Model inputs'!AJ41="","",'Model inputs'!AJ41),IF(IF(IF(ISERROR('Haq — Monthly P&L and cash'!P5>'Model inputs'!AJ40),'Haq — Monthly P&L and cash'!P5>'Model inputs'!AJ40,IF(OR('Haq — Monthly P&L and cash'!P5="",'Model inputs'!AJ40=""),"",'Haq — Monthly P&L and cash'!P5>'Model inputs'!AJ40))="",FALSE,IF(ISERROR('Haq — Monthly P&L and cash'!P5>'Model inputs'!AJ40),'Haq — Monthly P&L and cash'!P5>'Model inputs'!AJ40,IF(OR('Haq — Monthly P&L and cash'!P5="",'Model inputs'!AJ40=""),"",'Haq — Monthly P&L and cash'!P5>'Model inputs'!AJ40))),'Haq — Monthly P&L and cash'!O7*'Model inputs'!AJ37,0)) -> 40.455577 | Q8: =IF(IF(IF(ISERROR('Haq — Monthly P&L and cash'!Q5='Model inputs'!AJ40),'Haq — Monthly P&L and cash'!Q5='Model inputs'!AJ40,IF(OR('Haq — Monthly P&L and cash'!Q5="",'Model inputs'!AJ40=""),"",'Haq — Monthly P&L and cash'!Q5='Model inputs'!AJ40))="",FALSE,IF(ISERROR('Haq — Monthly P&L and cash'!Q5='Model inputs'!AJ40),'Haq — Monthly P&L and cash'!Q5='Model inputs'!AJ40,IF(OR('Haq — Monthly P&L and cash'!Q5="",'Model inputs'!AJ40=""),"",'Haq — Monthly P&L and cash'!Q5='Model inputs'!AJ40))),IF('Model inputs'!AJ41="","",'Model inputs'!AJ41),IF(IF(IF(ISERROR('Haq — Monthly P&L and cash'!Q5>'Model inputs'!AJ40),'Haq — Monthly P&L and cash'!Q5>'Model inputs'!AJ40,IF(OR('Haq — Monthly P&L and cash'!Q5="",'Model inputs'!AJ40=""),"",'Haq — Monthly P&L and cash'!Q5>'Model inputs'!AJ40))="",FALSE,IF(ISERROR('Haq — Monthly P&L and cash'!Q5>'Model inputs'!AJ40),'Haq — Monthly P&L and cash'!Q5>'Model inputs'!AJ40,IF(OR('Haq — Monthly P&L and cash'!Q5="",'Model inputs'!AJ40=""),"",'Haq — Monthly P&L and cash'!Q5>'Model inputs'!AJ40))),'Haq — Monthly P&L and cash'!P7*'Model inputs'!AJ37,0)) -> 46.523914 | R8: =IF(IF(IF(ISERROR('Haq — Monthly P&L and cash'!R5='Model inputs'!AJ40),'Haq — Monthly P&L and cash'!R5='Model inputs'!AJ40,IF(OR('Haq — Monthly P&L and cash'!R5="",'Model inputs'!AJ40=""),"",'Haq — Monthly P&L and cash'!R5='Model inputs'!AJ40))="",FALSE,IF(ISERROR('Haq — Monthly P&L and cash'!R5='Model inputs'!AJ40),'Haq — Monthly P&L and cash'!R5='Model inputs'!AJ40,IF(OR('Haq — Monthly P&L and cash'!R5="",'Model inputs'!AJ40=""),"",'Haq — Monthly P&L and cash'!R5='Model inputs'!AJ40))),IF('Model inputs'!AJ41="","",'Model inputs'!AJ41),IF(IF(IF(ISERROR('Haq — Monthly P&L and cash'!R5>'Model inputs'!AJ40),'Haq — Monthly P&L and cash'!R5>'Model inputs'!AJ40,IF(OR('Haq — Monthly P&L and cash'!R5="",'Model inputs'!AJ40=""),"",'Haq — Monthly P&L and cash'!R5>'Model inputs'!AJ40))="",FALSE,IF(ISERROR('Haq — Monthly P&L and cash'!R5>'Model inputs'!AJ40),'Haq — Monthly P&L and cash'!R5>'Model inputs'!AJ40,IF(OR('Haq — Monthly P&L and cash'!R5="",'Model inputs'!AJ40=""),"",'Haq — Monthly P&L and cash'!R5>'Model inputs'!AJ40))),'Haq — Monthly P&L and cash'!Q7*'Model inputs'!AJ37,0)) -> 53.502501 | S8: =IF(IF(IF(ISERROR('Haq — Monthly P&L and cash'!S5='Model inputs'!AJ40),'Haq — Monthly P&L and cash'!S5='Model inputs'!AJ40,IF(OR('Haq — Monthly P&L and cash'!S5="",'Model inputs'!AJ40=""),"",'Haq — Monthly P&L and cash'!S5='Model inputs'!AJ40))="",FALSE,IF(ISERROR('Haq — Monthly P&L and cash'!S5='Model inputs'!AJ40),'Haq — Monthly P&L and cash'!S5='Model inputs'!AJ40,IF(OR('Haq — Monthly P&L and cash'!S5="",'Model inputs'!AJ40=""),"",'Haq — Monthly P&L and cash'!S5='Model inputs'!AJ40))),IF('Model inputs'!AJ41="","",'Model inputs'!AJ41),IF(IF(IF(ISERROR('Haq — Monthly P&L and cash'!S5>'Model inputs'!AJ40),'Haq — Monthly P&L and cash'!S5>'Model inputs'!AJ40,IF(OR('Haq — Monthly P&L and cash'!S5="",'Model inputs'!AJ40=""),"",'Haq — Monthly P&L and cash'!S5>'Model inputs'!AJ40))="",FALSE,IF(ISERROR('Haq — Monthly P&L and cash'!S5>'Model inputs'!AJ40),'Haq — Monthly P&L and cash'!S5>'Model inputs'!AJ40,IF(OR('Haq — Monthly P&L and cash'!S5="",'Model inputs'!AJ40=""),"",'Haq — Monthly P&L and cash'!S5>'Model inputs'!AJ40))),'Haq — Monthly P&L and cash'!R7*'Model inputs'!AJ37,0)) -> 61.527876 | T8: =IF(IF(IF(ISERROR('Haq — Monthly P&L and cash'!T5='Model inputs'!AJ40),'Haq — Monthly P&L and cash'!T5='Model inputs'!AJ40,IF(OR('Haq — Monthly P&L and cash'!T5="",'Model inputs'!AJ40=""),"",'Haq — Monthly P&L and cash'!T5='Model inputs'!AJ40))="",FALSE,IF(ISERROR('Haq — Monthly P&L and cash'!T5='Model inputs'!AJ40),'Haq — Monthly P&L and cash'!T5='Model inputs'!AJ40,IF(OR('Haq — Monthly P&L and cash'!T5="",'Model inputs'!AJ40=""),"",'Haq — Monthly P&L and cash'!T5='Model inputs'!AJ40))),IF('Model inputs'!AJ41="","",'Model inputs'!AJ41),IF(IF(IF(ISERROR('Haq — Monthly P&L and cash'!T5>'Model inputs'!AJ40),'Haq — Monthly P&L and cash'!T5>'Model inputs'!AJ40,IF(OR('Haq — Monthly P&L and cash'!T5="",'Model inputs'!AJ40=""),"",'Haq — Monthly P&L and cash'!T5>'Model inputs'!AJ40))="",FALSE,IF(ISERROR('Haq — Monthly P&L and cash'!T5>'Model inputs'!AJ40),'Haq — Monthly P&L and cash'!T5>'Model inputs'!AJ40,IF(OR('Haq — Monthly P&L and cash'!T5="",'Model inputs'!AJ40=""),"",'Haq — Monthly P&L and cash'!T5>'Model inputs'!AJ40))),'Haq — Monthly P&L and cash'!S7*'Model inputs'!AJ37,0)) -> 70.757058 | U8: =IF(IF(IF(ISERROR('Haq — Monthly P&L and cash'!U5='Model inputs'!AJ40),'Haq — Monthly P&L and cash'!U5='Model inputs'!AJ40,IF(OR('Haq — Monthly P&L and cash'!U5="",'Model inputs'!AJ40=""),"",'Haq — Monthly P&L and cash'!U5='Model inputs'!AJ40))="",FALSE,IF(ISERROR('Haq — Monthly P&L and cash'!U5='Model inputs'!AJ40),'Haq — Monthly P&L and cash'!U5='Model inputs'!AJ40,IF(OR('Haq — Monthly P&L and cash'!U5="",'Model inputs'!AJ40=""),"",'Haq — Monthly P&L and cash'!U5='Model inputs'!AJ40))),IF('Model inputs'!AJ41="","",'Model inputs'!AJ41),IF(IF(IF(ISERROR('Haq — Monthly P&L and cash'!U5>'Model inputs'!AJ40),'Haq — Monthly P&L and cash'!U5>'Model inputs'!AJ40,IF(OR('Haq — Monthly P&L and cash'!U5="",'Model inputs'!AJ40=""),"",'Haq — Monthly P&L and cash'!U5>'Model inputs'!AJ40))="",FALSE,IF(ISERROR('Haq — Monthly P&L and cash'!U5>'Model inputs'!AJ40),'Haq — Monthly P&L and cash'!U5>'Model inputs'!AJ40,IF(OR('Haq — Monthly P&L and cash'!U5="",'Model inputs'!AJ40=""),"",'Haq — Monthly P&L and cash'!U5>'Model inputs'!AJ40))),'Haq — Monthly P&L and cash'!T7*'Model inputs'!AJ37,0)) -> 81.370616 | V8: =IF(IF(IF(ISERROR('Haq — Monthly P&L and cash'!V5='Model inputs'!AJ40),'Haq — Monthly P&L and cash'!V5='Model inputs'!AJ40,IF(OR('Haq — Monthly P&L and cash'!V5="",'Model inputs'!AJ40=""),"",'Haq — Monthly P&L and cash'!V5='Model inputs'!AJ40))="",FALSE,IF(ISERROR('Haq — Monthly P&L and cash'!V5='Model inputs'!AJ40),'Haq — Monthly P&L and cash'!V5='Model inputs'!AJ40,IF(OR('Haq — Monthly P&L and cash'!V5="",'Model inputs'!AJ40=""),"",'Haq — Monthly P&L and cash'!V5='Model inputs'!AJ40))),IF('Model inputs'!AJ41="","",'Model inputs'!AJ41),IF(IF(IF(ISERROR('Haq — Monthly P&L and cash'!V5>'Model inputs'!AJ40),'Haq — Monthly P&L and cash'!V5>'Model inputs'!AJ40,IF(OR('Haq — Monthly P&L and cash'!V5="",'Model inputs'!AJ40=""),"",'Haq — Monthly P&L and cash'!V5>'Model inputs'!AJ40))="",FALSE,IF(ISERROR('Haq — Monthly P&L and cash'!V5>'Model inputs'!AJ40),'Haq — Monthly P&L and cash'!V5>'Model inputs'!AJ40,IF(OR('Haq — Monthly P&L and cash'!V5="",'Model inputs'!AJ40=""),"",'Haq — Monthly P&L and cash'!V5>'Model inputs'!AJ40))),'Haq — Monthly P&L and cash'!U7*'Model inputs'!AJ37,0)) -> 93.576209 | W8: =IF(IF(IF(ISERROR('Haq — Monthly P&L and cash'!W5='Model inputs'!AJ40),'Haq — Monthly P&L and cash'!W5='Model inputs'!AJ40,IF(OR('Haq — Monthly P&L and cash'!W5="",'Model inputs'!AJ40=""),"",'Haq — Monthly P&L and cash'!W5='Model inputs'!AJ40))="",FALSE,IF(ISERROR('Haq — Monthly P&L and cash'!W5='Model inputs'!AJ40),'Haq — Monthly P&L and cash'!W5='Model inputs'!AJ40,IF(OR('Haq — Monthly P&L and cash'!W5="",'Model inputs'!AJ40=""),"",'Haq — Monthly P&L and cash'!W5='Model inputs'!AJ40))),IF('Model inputs'!AJ41="","",'Model inputs'!AJ41),IF(IF(IF(ISERROR('Haq — Monthly P&L and cash'!W5>'Model inputs'!AJ40),'Haq — Monthly P&L and cash'!W5>'Model inputs'!AJ40,IF(OR('Haq — Monthly P&L and cash'!W5="",'Model inputs'!AJ40=""),"",'Haq — Monthly P&L and cash'!W5>'Model inputs'!AJ40))="",FALSE,IF(ISERROR('Haq — Monthly P&L and cash'!W5>'Model inputs'!AJ40),'Haq — Monthly P&L and cash'!W5>'Model inputs'!AJ40,IF(OR('Haq — Monthly P&L and cash'!W5="",'Model inputs'!AJ40=""),"",'Haq — Monthly P&L and cash'!W5>'Model inputs'!AJ40))),'Haq — Monthly P&L and cash'!V7*'Model inputs'!AJ37,0)) -> 107.61264 | X8: =IF(IF(IF(ISERROR('Haq — Monthly P&L and cash'!X5='Model inputs'!AJ40),'Haq — Monthly P&L and cash'!X5='Model inputs'!AJ40,IF(OR('Haq — Monthly P&L and cash'!X5="",'Model inputs'!AJ40=""),"",'Haq — Monthly P&L and cash'!X5='Model inputs'!AJ40))="",FALSE,IF(ISERROR('Haq — Monthly P&L and cash'!X5='Model inputs'!AJ40),'Haq — Monthly P&L and cash'!X5='Model inputs'!AJ40,IF(OR('Haq — Monthly P&L and cash'!X5="",'Model inputs'!AJ40=""),"",'Haq — Monthly P&L and cash'!X5='Model inputs'!AJ40))),IF('Model inputs'!AJ41="","",'Model inputs'!AJ41),IF(IF(IF(ISERROR('Haq — Monthly P&L and cash'!X5>'Model inputs'!AJ40),'Haq — Monthly P&L and cash'!X5>'Model inputs'!AJ40,IF(OR('Haq — Monthly P&L and cash'!X5="",'Model inputs'!AJ40=""),"",'Haq — Monthly P&L and cash'!X5>'Model inputs'!AJ40))="",FALSE,IF(ISERROR('Haq — Monthly P&L and cash'!X5>'Model inputs'!AJ40),'Haq — Monthly P&L and cash'!X5>'Model inputs'!AJ40,IF(OR('Haq — Monthly P&L and cash'!X5="",'Model inputs'!AJ40=""),"",'Haq — Monthly P&L and cash'!X5>'Model inputs'!AJ40))),'Haq — Monthly P&L and cash'!W7*'Model inputs'!AJ37,0)) -> 123.75454 | Y8: =IF(IF(IF(ISERROR('Haq — Monthly P&L and cash'!Y5='Model inputs'!AJ40),'Haq — Monthly P&L and cash'!Y5='Model inputs'!AJ40,IF(OR('Haq — Monthly P&L and cash'!Y5="",'Model inputs'!AJ40=""),"",'Haq — Monthly P&L and cash'!Y5='Model inputs'!AJ40))="",FALSE,IF(ISERROR('Haq — Monthly P&L and cash'!Y5='Model inputs'!AJ40),'Haq — Monthly P&L and cash'!Y5='Model inputs'!AJ40,IF(OR('Haq — Monthly P&L and cash'!Y5="",'Model inputs'!AJ40=""),"",'Haq — Monthly P&L and cash'!Y5='Model inputs'!AJ40))),IF('Model inputs'!AJ41="","",'Model inputs'!AJ41),IF(IF(IF(ISERROR('Haq — Monthly P&L and cash'!Y5>'Model inputs'!AJ40),'Haq — Monthly P&L and cash'!Y5>'Model inputs'!AJ40,IF(OR('Haq — Monthly P&L and cash'!Y5="",'Model inputs'!AJ40=""),"",'Haq — Monthly P&L and cash'!Y5>'Model inputs'!AJ40))="",FALSE,IF(ISERROR('Haq — Monthly P&L and cash'!Y5>'Model inputs'!AJ40),'Haq — Monthly P&L and cash'!Y5>'Model inputs'!AJ40,IF(OR('Haq — Monthly P&L and cash'!Y5="",'Model inputs'!AJ40=""),"",'Haq — Monthly P&L and cash'!Y5>'Model inputs'!AJ40))),'Haq — Monthly P&L and cash'!X7*'Model inputs'!AJ37,0)) -> 142.31772
A9: Haq CSC checks | B9: ='Haq — Monthly P&L and cash'!B7*'Model inputs'!AJ35 -> 0 | C9: ='Haq — Monthly P&L and cash'!C7*'Model inputs'!AJ35 -> 0 | D9: ='Haq — Monthly P&L and cash'!D7*'Model inputs'!AJ35 -> 0 | E9: ='Haq — Monthly P&L and cash'!E7*'Model inputs'!AJ35 -> 4000 | F9: ='Haq — Monthly P&L and cash'!F7*'Model inputs'!AJ35 -> 4600 | G9: ='Haq — Monthly P&L and cash'!G7*'Model inputs'!AJ35 -> 5290 | H9: ='Haq — Monthly P&L and cash'!H7*'Model inputs'!AJ35 -> 6083.5 | I9: ='Haq — Monthly P&L and cash'!I7*'Model inputs'!AJ35 -> 6996.025 | J9: ='Haq — Monthly P&L and cash'!J7*'Model inputs'!AJ35 -> 8045.4287 | K9: ='Haq — Monthly P&L and cash'!K7*'Model inputs'!AJ35 -> 9252.2431 | L9: ='Haq — Monthly P&L and cash'!L7*'Model inputs'!AJ35 -> 10640.08 | M9: ='Haq — Monthly P&L and cash'!M7*'Model inputs'!AJ35 -> 12236.091 | N9: ='Haq — Monthly P&L and cash'!N7*'Model inputs'!AJ35 -> 14071.505 | O9: ='Haq — Monthly P&L and cash'!O7*'Model inputs'!AJ35 -> 16182.231 | P9: ='Haq — Monthly P&L and cash'!P7*'Model inputs'!AJ35 -> 18609.566 | Q9: ='Haq — Monthly P&L and cash'!Q7*'Model inputs'!AJ35 -> 21401 | R9: ='Haq — Monthly P&L and cash'!R7*'Model inputs'!AJ35 -> 24611.15 | S9: ='Haq — Monthly P&L and cash'!S7*'Model inputs'!AJ35 -> 28302.823 | T9: ='Haq — Monthly P&L and cash'!T7*'Model inputs'!AJ35 -> 32548.247 | U9: ='Haq — Monthly P&L and cash'!U7*'Model inputs'!AJ35 -> 37430.483 | V9: ='Haq — Monthly P&L and cash'!V7*'Model inputs'!AJ35 -> 43045.056 | W9: ='Haq — Monthly P&L and cash'!W7*'Model inputs'!AJ35 -> 49501.814 | X9: ='Haq — Monthly P&L and cash'!X7*'Model inputs'!AJ35 -> 56927.087 | Y9: ='Haq — Monthly P&L and cash'!Y7*'Model inputs'!AJ35 -> 65466.15
A10: Haq CSC revenue | B10: ='Haq — Monthly P&L and cash'!B7*('Model inputs'!AJ43+MAX('Model inputs'!AJ35-'Model inputs'!AJ38,0)*'Model inputs'!AJ36) -> 0 | C10: ='Haq — Monthly P&L and cash'!C7*('Model inputs'!AJ43+MAX('Model inputs'!AJ35-'Model inputs'!AJ38,0)*'Model inputs'!AJ36) -> 0 | D10: ='Haq — Monthly P&L and cash'!D7*('Model inputs'!AJ43+MAX('Model inputs'!AJ35-'Model inputs'!AJ38,0)*'Model inputs'!AJ36) -> 0 | E10: ='Haq — Monthly P&L and cash'!E7*('Model inputs'!AJ43+MAX('Model inputs'!AJ35-'Model inputs'!AJ38,0)*'Model inputs'!AJ36) -> 74950 | F10: ='Haq — Monthly P&L and cash'!F7*('Model inputs'!AJ43+MAX('Model inputs'!AJ35-'Model inputs'!AJ38,0)*'Model inputs'!AJ36) -> 86192.5 | G10: ='Haq — Monthly P&L and cash'!G7*('Model inputs'!AJ43+MAX('Model inputs'!AJ35-'Model inputs'!AJ38,0)*'Model inputs'!AJ36) -> 99121.375 | H10: ='Haq — Monthly P&L and cash'!H7*('Model inputs'!AJ43+MAX('Model inputs'!AJ35-'Model inputs'!AJ38,0)*'Model inputs'!AJ36) -> 113989.58 | I10: ='Haq — Monthly P&L and cash'!I7*('Model inputs'!AJ43+MAX('Model inputs'!AJ35-'Model inputs'!AJ38,0)*'Model inputs'!AJ36) -> 131088.02 | J10: ='Haq — Monthly P&L and cash'!J7*('Model inputs'!AJ43+MAX('Model inputs'!AJ35-'Model inputs'!AJ38,0)*'Model inputs'!AJ36) -> 150751.22 | K10: ='Haq — Monthly P&L and cash'!K7*('Model inputs'!AJ43+MAX('Model inputs'!AJ35-'Model inputs'!AJ38,0)*'Model inputs'!AJ36) -> 173363.9 | L10: ='Haq — Monthly P&L and cash'!L7*('Model inputs'!AJ43+MAX('Model inputs'!AJ35-'Model inputs'!AJ38,0)*'Model inputs'!AJ36) -> 199368.49 | M10: ='Haq — Monthly P&L and cash'!M7*('Model inputs'!AJ43+MAX('Model inputs'!AJ35-'Model inputs'!AJ38,0)*'Model inputs'!AJ36) -> 229273.76 | N10: ='Haq — Monthly P&L and cash'!N7*('Model inputs'!AJ43+MAX('Model inputs'!AJ35-'Model inputs'!AJ38,0)*'Model inputs'!AJ36) -> 263664.83 | O10: ='Haq — Monthly P&L and cash'!O7*('Model inputs'!AJ43+MAX('Model inputs'!AJ35-'Model inputs'!AJ38,0)*'Model inputs'!AJ36) -> 303214.55 | P10: ='Haq — Monthly P&L and cash'!P7*('Model inputs'!AJ43+MAX('Model inputs'!AJ35-'Model inputs'!AJ38,0)*'Model inputs'!AJ36) -> 348696.74 | Q10: ='Haq — Monthly P&L and cash'!Q7*('Model inputs'!AJ43+MAX('Model inputs'!AJ35-'Model inputs'!AJ38,0)*'Model inputs'!AJ36) -> 401001.25 | R10: ='Haq — Monthly P&L and cash'!R7*('Model inputs'!AJ43+MAX('Model inputs'!AJ35-'Model inputs'!AJ38,0)*'Model inputs'!AJ36) -> 461151.43 | S10: ='Haq — Monthly P&L and cash'!S7*('Model inputs'!AJ43+MAX('Model inputs'!AJ35-'Model inputs'!AJ38,0)*'Model inputs'!AJ36) -> 530324.15 | T10: ='Haq — Monthly P&L and cash'!T7*('Model inputs'!AJ43+MAX('Model inputs'!AJ35-'Model inputs'!AJ38,0)*'Model inputs'!AJ36) -> 609872.77 | U10: ='Haq — Monthly P&L and cash'!U7*('Model inputs'!AJ43+MAX('Model inputs'!AJ35-'Model inputs'!AJ38,0)*'Model inputs'!AJ36) -> 701353.68 | V10: ='Haq — Monthly P&L and cash'!V7*('Model inputs'!AJ43+MAX('Model inputs'!AJ35-'Model inputs'!AJ38,0)*'Model inputs'!AJ36) -> 806556.74 | W10: ='Haq — Monthly P&L and cash'!W7*('Model inputs'!AJ43+MAX('Model inputs'!AJ35-'Model inputs'!AJ38,0)*'Model inputs'!AJ36) -> 927540.25 | X10: ='Haq — Monthly P&L and cash'!X7*('Model inputs'!AJ43+MAX('Model inputs'!AJ35-'Model inputs'!AJ38,0)*'Model inputs'!AJ36) -> 1066671.3 | Y10: ='Haq — Monthly P&L and cash'!Y7*('Model inputs'!AJ43+MAX('Model inputs'!AJ35-'Model inputs'!AJ38,0)*'Model inputs'!AJ36) -> 1226672
A11: Haq CSR districts | B11: =IF(IF(IF(ISERROR('Haq — Monthly P&L and cash'!B5>=24),'Haq — Monthly P&L and cash'!B5>=24,IF('Haq — Monthly P&L and cash'!B5="","",'Haq — Monthly P&L and cash'!B5>=24))="",FALSE,IF(ISERROR('Haq — Monthly P&L and cash'!B5>=24),'Haq — Monthly P&L and cash'!B5>=24,IF('Haq — Monthly P&L and cash'!B5="","",'Haq — Monthly P&L and cash'!B5>=24))),IF('Model inputs'!AJ51="","",'Model inputs'!AJ51),IF(IF(IF(ISERROR('Haq — Monthly P&L and cash'!B5>=23),'Haq — Monthly P&L and cash'!B5>=23,IF('Haq — Monthly P&L and cash'!B5="","",'Haq — Monthly P&L and cash'!B5>=23))="",FALSE,IF(ISERROR('Haq — Monthly P&L and cash'!B5>=23),'Haq — Monthly P&L and cash'!B5>=23,IF('Haq — Monthly P&L and cash'!B5="","",'Haq — Monthly P&L and cash'!B5>=23))),IF('Model inputs'!AJ50="","",'Model inputs'!AJ50),IF(IF(IF(ISERROR('Haq — Monthly P&L and cash'!B5>=21),'Haq — Monthly P&L and cash'!B5>=21,IF('Haq — Monthly P&L and cash'!B5="","",'Haq — Monthly P&L and cash'!B5>=21))="",FALSE,IF(ISERROR('Haq — Monthly P&L and cash'!B5>=21),'Haq — Monthly P&L and cash'!B5>=21,IF('Haq — Monthly P&L and cash'!B5="","",'Haq — Monthly P&L and cash'!B5>=21))),IF('Model inputs'!AJ49="","",'Model inputs'!AJ49),IF(IF(IF(ISERROR('Haq — Monthly P&L and cash'!B5>=18),'Haq — Monthly P&L and cash'!B5>=18,IF('Haq — Monthly P&L and cash'!B5="","",'Haq — Monthly P&L and cash'!B5>=18))="",FALSE,IF(ISERROR('Haq — Monthly P&L and cash'!B5>=18),'Haq — Monthly P&L and cash'!B5>=18,IF('Haq — Monthly P&L and cash'!B5="","",'Haq — Monthly P&L and cash'!B5>=18))),IF('Model inputs'!AJ48="","",'Model inputs'!AJ48),IF(IF(IF(ISERROR('Haq — Monthly P&L and cash'!B5>=15),'Haq — Monthly P&L and cash'!B5>=15,IF('Haq — Monthly P&L and cash'!B5="","",'Haq — Monthly P&L and cash'!B5>=15))="",FALSE,IF(ISERROR('Haq — Monthly P&L and cash'!B5>=15),'Haq — Monthly P&L and cash'!B5>=15,IF('Haq — Monthly P&L and cash'!B5="","",'Haq — Monthly P&L and cash'!B5>=15))),IF('Model inputs'!AJ47="","",'Model inputs'!AJ47),IF(IF(IF(ISERROR('Haq — Monthly P&L and cash'!B5>=12),'Haq — Monthly P&L and cash'!B5>=12,IF('Haq — Monthly P&L and cash'!B5="","",'Haq — Monthly P&L and cash'!B5>=12))="",FALSE,IF(ISERROR('Haq — Monthly P&L and cash'!B5>=12),'Haq — Monthly P&L and cash'!B5>=12,IF('Haq — Monthly P&L and cash'!B5="","",'Haq — Monthly P&L and cash'!B5>=12))),IF('Model inputs'!AJ46="","",'Model inputs'!AJ46),IF(IF(IF(ISERROR('Haq — Monthly P&L and cash'!B5>=9),'Haq — Monthly P&L and cash'!B5>=9,IF('Haq — Monthly P&L and cash'!B5="","",'Haq — Monthly P&L and cash'!B5>=9))="",FALSE,IF(ISERROR('Haq — Monthly P&L and cash'!B5>=9),'Haq — Monthly P&L and cash'!B5>=9,IF('Haq — Monthly P&L and cash'!B5="","",'Haq — Monthly P&L and cash'!B5>=9))),IF('Model inputs'!AJ53="","",'Model inputs'!AJ53),IF(IF(IF(ISERROR('Haq — Monthly P&L and cash'!B5>=6),'Haq — Monthly P&L and cash'!B5>=6,IF('Haq — Monthly P&L and cash'!B5="","",'Haq — Monthly P&L and cash'!B5>=6))="",FALSE,IF(ISERROR('Haq — Monthly P&L and cash'!B5>=6),'Haq — Monthly P&L and cash'!B5>=6,IF('Haq — Monthly P&L and cash'!B5="","",'Haq — Monthly P&L and cash'!B5>=6))),IF('Model inputs'!AJ52="","",'Model inputs'!AJ52),0)))))))) -> 0 | C11: =IF(IF(IF(ISERROR('Haq — Monthly P&L and cash'!C5>=24),'Haq — Monthly P&L and cash'!C5>=24,IF('Haq — Monthly P&L and cash'!C5="","",'Haq — Monthly P&L and cash'!C5>=24))="",FALSE,IF(ISERROR('Haq — Monthly P&L and cash'!C5>=24),'Haq — Monthly P&L and cash'!C5>=24,IF('Haq — Monthly P&L and cash'!C5="","",'Haq — Monthly P&L and cash'!C5>=24))),IF('Model inputs'!AJ51="","",'Model inputs'!AJ51),IF(IF(IF(ISERROR('Haq — Monthly P&L and cash'!C5>=23),'Haq — Monthly P&L and cash'!C5>=23,IF('Haq — Monthly P&L and cash'!C5="","",'Haq — Monthly P&L and cash'!C5>=23))="",FALSE,IF(ISERROR('Haq — Monthly P&L and cash'!C5>=23),'Haq — Monthly P&L and cash'!C5>=23,IF('Haq — Monthly P&L and cash'!C5="","",'Haq — Monthly P&L and cash'!C5>=23))),IF('Model inputs'!AJ50="","",'Model inputs'!AJ50),IF(IF(IF(ISERROR('Haq — Monthly P&L and cash'!C5>=21),'Haq — Monthly P&L and cash'!C5>=21,IF('Haq — Monthly P&L and cash'!C5="","",'Haq — Monthly P&L and cash'!C5>=21))="",FALSE,IF(ISERROR('Haq — Monthly P&L and cash'!C5>=21),'Haq — Monthly P&L and cash'!C5>=21,IF('Haq — Monthly P&L and cash'!C5="","",'Haq — Monthly P&L and cash'!C5>=21))),IF('Model inputs'!AJ49="","",'Model inputs'!AJ49),IF(IF(IF(ISERROR('Haq — Monthly P&L and cash'!C5>=18),'Haq — Monthly P&L and cash'!C5>=18,IF('Haq — Monthly P&L and cash'!C5="","",'Haq — Monthly P&L and cash'!C5>=18))="",FALSE,IF(ISERROR('Haq — Monthly P&L and cash'!C5>=18),'Haq — Monthly P&L and cash'!C5>=18,IF('Haq — Monthly P&L and cash'!C5="","",'Haq — Monthly P&L and cash'!C5>=18))),IF('Model inputs'!AJ48="","",'Model inputs'!AJ48),IF(IF(IF(ISERROR('Haq — Monthly P&L and cash'!C5>=15),'Haq — Monthly P&L and cash'!C5>=15,IF('Haq — Monthly P&L and cash'!C5="","",'Haq — Monthly P&L and cash'!C5>=15))="",FALSE,IF(ISERROR('Haq — Monthly P&L and cash'!C5>=15),'Haq — Monthly P&L and cash'!C5>=15,IF('Haq — Monthly P&L and cash'!C5="","",'Haq — Monthly P&L and cash'!C5>=15))),IF('Model inputs'!AJ47="","",'Model inputs'!AJ47),IF(IF(IF(ISERROR('Haq — Monthly P&L and cash'!C5>=12),'Haq — Monthly P&L and cash'!C5>=12,IF('Haq — Monthly P&L and cash'!C5="","",'Haq — Monthly P&L and cash'!C5>=12))="",FALSE,IF(ISERROR('Haq — Monthly P&L and cash'!C5>=12),'Haq — Monthly P&L and cash'!C5>=12,IF('Haq — Monthly P&L and cash'!C5="","",'Haq — Monthly P&L and cash'!C5>=12))),IF('Model inputs'!AJ46="","",'Model inputs'!AJ46),IF(IF(IF(ISERROR('Haq — Monthly P&L and cash'!C5>=9),'Haq — Monthly P&L and cash'!C5>=9,IF('Haq — Monthly P&L and cash'!C5="","",'Haq — Monthly P&L and cash'!C5>=9))="",FALSE,IF(ISERROR('Haq — Monthly P&L and cash'!C5>=9),'Haq — Monthly P&L and cash'!C5>=9,IF('Haq — Monthly P&L and cash'!C5="","",'Haq — Monthly P&L and cash'!C5>=9))),IF('Model inputs'!AJ53="","",'Model inputs'!AJ53),IF(IF(IF(ISERROR('Haq — Monthly P&L and cash'!C5>=6),'Haq — Monthly P&L and cash'!C5>=6,IF('Haq — Monthly P&L and cash'!C5="","",'Haq — Monthly P&L and cash'!C5>=6))="",FALSE,IF(ISERROR('Haq — Monthly P&L and cash'!C5>=6),'Haq — Monthly P&L and cash'!C5>=6,IF('Haq — Monthly P&L and cash'!C5="","",'Haq — Monthly P&L and cash'!C5>=6))),IF('Model inputs'!AJ52="","",'Model inputs'!AJ52),0)))))))) -> 0 | D11: =IF(IF(IF(ISERROR('Haq — Monthly P&L and cash'!D5>=24),'Haq — Monthly P&L and cash'!D5>=24,IF('Haq — Monthly P&L and cash'!D5="","",'Haq — Monthly P&L and cash'!D5>=24))="",FALSE,IF(ISERROR('Haq — Monthly P&L and cash'!D5>=24),'Haq — Monthly P&L and cash'!D5>=24,IF('Haq — Monthly P&L and cash'!D5="","",'Haq — Monthly P&L and cash'!D5>=24))),IF('Model inputs'!AJ51="","",'Model inputs'!AJ51),IF(IF(IF(ISERROR('Haq — Monthly P&L and cash'!D5>=23),'Haq — Monthly P&L and cash'!D5>=23,IF('Haq — Monthly P&L and cash'!D5="","",'Haq — Monthly P&L and cash'!D5>=23))="",FALSE,IF(ISERROR('Haq — Monthly P&L and cash'!D5>=23),'Haq — Monthly P&L and cash'!D5>=23,IF('Haq — Monthly P&L and cash'!D5="","",'Haq — Monthly P&L and cash'!D5>=23))),IF('Model inputs'!AJ50="","",'Model inputs'!AJ50),IF(IF(IF(ISERROR('Haq — Monthly P&L and cash'!D5>=21),'Haq — Monthly P&L and cash'!D5>=21,IF('Haq — Monthly P&L and cash'!D5="","",'Haq — Monthly P&L and cash'!D5>=21))="",FALSE,IF(ISERROR('Haq — Monthly P&L and cash'!D5>=21),'Haq — Monthly P&L and cash'!D5>=21,IF('Haq — Monthly P&L and cash'!D5="","",'Haq — Monthly P&L and cash'!D5>=21))),IF('Model inputs'!AJ49="","",'Model inputs'!AJ49),IF(IF(IF(ISERROR('Haq — Monthly P&L and cash'!D5>=18),'Haq — Monthly P&L and cash'!D5>=18,IF('Haq — Monthly P&L and cash'!D5="","",'Haq — Monthly P&L and cash'!D5>=18))="",FALSE,IF(ISERROR('Haq — Monthly P&L and cash'!D5>=18),'Haq — Monthly P&L and cash'!D5>=18,IF('Haq — Monthly P&L and cash'!D5="","",'Haq — Monthly P&L and cash'!D5>=18))),IF('Model inputs'!AJ48="","",'Model inputs'!AJ48),IF(IF(IF(ISERROR('Haq — Monthly P&L and cash'!D5>=15),'Haq — Monthly P&L and cash'!D5>=15,IF('Haq — Monthly P&L and cash'!D5="","",'Haq — Monthly P&L and cash'!D5>=15))="",FALSE,IF(ISERROR('Haq — Monthly P&L and cash'!D5>=15),'Haq — Monthly P&L and cash'!D5>=15,IF('Haq — Monthly P&L and cash'!D5="","",'Haq — Monthly P&L and cash'!D5>=15))),IF('Model inputs'!AJ47="","",'Model inputs'!AJ47),IF(IF(IF(ISERROR('Haq — Monthly P&L and cash'!D5>=12),'Haq — Monthly P&L and cash'!D5>=12,IF('Haq — Monthly P&L and cash'!D5="","",'Haq — Monthly P&L and cash'!D5>=12))="",FALSE,IF(ISERROR('Haq — Monthly P&L and cash'!D5>=12),'Haq — Monthly P&L and cash'!D5>=12,IF('Haq — Monthly P&L and cash'!D5="","",'Haq — Monthly P&L and cash'!D5>=12))),IF('Model inputs'!AJ46="","",'Model inputs'!AJ46),IF(IF(IF(ISERROR('Haq — Monthly P&L and cash'!D5>=9),'Haq — Monthly P&L and cash'!D5>=9,IF('Haq — Monthly P&L and cash'!D5="","",'Haq — Monthly P&L and cash'!D5>=9))="",FALSE,IF(ISERROR('Haq — Monthly P&L and cash'!D5>=9),'Haq — Monthly P&L and cash'!D5>=9,IF('Haq — Monthly P&L and cash'!D5="","",'Haq — Monthly P&L and cash'!D5>=9))),IF('Model inputs'!AJ53="","",'Model inputs'!AJ53),IF(IF(IF(ISERROR('Haq — Monthly P&L and cash'!D5>=6),'Haq — Monthly P&L and cash'!D5>=6,IF('Haq — Monthly P&L and cash'!D5="","",'Haq — Monthly P&L and cash'!D5>=6))="",FALSE,IF(ISERROR('Haq — Monthly P&L and cash'!D5>=6),'Haq — Monthly P&L and cash'!D5>=6,IF('Haq — Monthly P&L and cash'!D5="","",'Haq — Monthly P&L and cash'!D5>=6))),IF('Model inputs'!AJ52="","",'Model inputs'!AJ52),0)))))))) -> 0 | E11: =IF(IF(IF(ISERROR('Haq — Monthly P&L and cash'!E5>=24),'Haq — Monthly P&L and cash'!E5>=24,IF('Haq — Monthly P&L and cash'!E5="","",'Haq — Monthly P&L and cash'!E5>=24))="",FALSE,IF(ISERROR('Haq — Monthly P&L and cash'!E5>=24),'Haq — Monthly P&L and cash'!E5>=24,IF('Haq — Monthly P&L and cash'!E5="","",'Haq — Monthly P&L and cash'!E5>=24))),IF('Model inputs'!AJ51="","",'Model inputs'!AJ51),IF(IF(IF(ISERROR('Haq — Monthly P&L and cash'!E5>=23),'Haq — Monthly P&L and cash'!E5>=23,IF('Haq — Monthly P&L and cash'!E5="","",'Haq — Monthly P&L and cash'!E5>=23))="",FALSE,IF(ISERROR('Haq — Monthly P&L and cash'!E5>=23),'Haq — Monthly P&L and cash'!E5>=23,IF('Haq — Monthly P&L and cash'!E5="","",'Haq — Monthly P&L and cash'!E5>=23))),IF('Model inputs'!AJ50="","",'Model inputs'!AJ50),IF(IF(IF(ISERROR('Haq — Monthly P&L and cash'!E5>=21),'Haq — Monthly P&L and cash'!E5>=21,IF('Haq — Monthly P&L and cash'!E5="","",'Haq — Monthly P&L and cash'!E5>=21))="",FALSE,IF(ISERROR('Haq — Monthly P&L and cash'!E5>=21),'Haq — Monthly P&L and cash'!E5>=21,IF('Haq — Monthly P&L and cash'!E5="","",'Haq — Monthly P&L and cash'!E5>=21))),IF('Model inputs'!AJ49="","",'Model inputs'!AJ49),IF(IF(IF(ISERROR('Haq — Monthly P&L and cash'!E5>=18),'Haq — Monthly P&L and cash'!E5>=18,IF('Haq — Monthly P&L and cash'!E5="","",'Haq — Monthly P&L and cash'!E5>=18))="",FALSE,IF(ISERROR('Haq — Monthly P&L and cash'!E5>=18),'Haq — Monthly P&L and cash'!E5>=18,IF('Haq — Monthly P&L and cash'!E5="","",'Haq — Monthly P&L and cash'!E5>=18))),IF('Model inputs'!AJ48="","",'Model inputs'!AJ48),IF(IF(IF(ISERROR('Haq — Monthly P&L and cash'!E5>=15),'Haq — Monthly P&L and cash'!E5>=15,IF('Haq — Monthly P&L and cash'!E5="","",'Haq — Monthly P&L and cash'!E5>=15))="",FALSE,IF(ISERROR('Haq — Monthly P&L and cash'!E5>=15),'Haq — Monthly P&L and cash'!E5>=15,IF('Haq — Monthly P&L and cash'!E5="","",'Haq — Monthly P&L and cash'!E5>=15))),IF('Model inputs'!AJ47="","",'Model inputs'!AJ47),IF(IF(IF(ISERROR('Haq — Monthly P&L and cash'!E5>=12),'Haq — Monthly P&L and cash'!E5>=12,IF('Haq — Monthly P&L and cash'!E5="","",'Haq — Monthly P&L and cash'!E5>=12))="",FALSE,IF(ISERROR('Haq — Monthly P&L and cash'!E5>=12),'Haq — Monthly P&L and cash'!E5>=12,IF('Haq — Monthly P&L and cash'!E5="","",'Haq — Monthly P&L and cash'!E5>=12))),IF('Model inputs'!AJ46="","",'Model inputs'!AJ46),IF(IF(IF(ISERROR('Haq — Monthly P&L and cash'!E5>=9),'Haq — Monthly P&L and cash'!E5>=9,IF('Haq — Monthly P&L and cash'!E5="","",'Haq — Monthly P&L and cash'!E5>=9))="",FALSE,IF(ISERROR('Haq — Monthly P&L and cash'!E5>=9),'Haq — Monthly P&L and cash'!E5>=9,IF('Haq — Monthly P&L and cash'!E5="","",'Haq — Monthly P&L and cash'!E5>=9))),IF('Model inputs'!AJ53="","",'Model inputs'!AJ53),IF(IF(IF(ISERROR('Haq — Monthly P&L and cash'!E5>=6),'Haq — Monthly P&L and cash'!E5>=6,IF('Haq — Monthly P&L and cash'!E5="","",'Haq — Monthly P&L and cash'!E5>=6))="",FALSE,IF(ISERROR('Haq — Monthly P&L and cash'!E5>=6),'Haq — Monthly P&L and cash'!E5>=6,IF('Haq — Monthly P&L and cash'!E5="","",'Haq — Monthly P&L and cash'!E5>=6))),IF('Model inputs'!AJ52="","",'Model inputs'!AJ52),0)))))))) -> 0 | F11: =IF(IF(IF(ISERROR('Haq — Monthly P&L and cash'!F5>=24),'Haq — Monthly P&L and cash'!F5>=24,IF('Haq — Monthly P&L and cash'!F5="","",'Haq — Monthly P&L and cash'!F5>=24))="",FALSE,IF(ISERROR('Haq — Monthly P&L and cash'!F5>=24),'Haq — Monthly P&L and cash'!F5>=24,IF('Haq — Monthly P&L and cash'!F5="","",'Haq — Monthly P&L and cash'!F5>=24))),IF('Model inputs'!AJ51="","",'Model inputs'!AJ51),IF(IF(IF(ISERROR('Haq — Monthly P&L and cash'!F5>=23),'Haq — Monthly P&L and cash'!F5>=23,IF('Haq — Monthly P&L and cash'!F5="","",'Haq — Monthly P&L and cash'!F5>=23))="",FALSE,IF(ISERROR('Haq — Monthly P&L and cash'!F5>=23),'Haq — Monthly P&L and cash'!F5>=23,IF('Haq — Monthly P&L and cash'!F5="","",'Haq — Monthly P&L and cash'!F5>=23))),IF('Model inputs'!AJ50="","",'Model inputs'!AJ50),IF(IF(IF(ISERROR('Haq — Monthly P&L and cash'!F5>=21),'Haq — Monthly P&L and cash'!F5>=21,IF('Haq — Monthly P&L and cash'!F5="","",'Haq — Monthly P&L and cash'!F5>=21))="",FALSE,IF(ISERROR('Haq — Monthly P&L and cash'!F5>=21),'Haq — Monthly P&L and cash'!F5>=21,IF('Haq — Monthly P&L and cash'!F5="","",'Haq — Monthly P&L and cash'!F5>=21))),IF('Model inputs'!AJ49="","",'Model inputs'!AJ49),IF(IF(IF(ISERROR('Haq — Monthly P&L and cash'!F5>=18),'Haq — Monthly P&L and cash'!F5>=18,IF('Haq — Monthly P&L and cash'!F5="","",'Haq — Monthly P&L and cash'!F5>=18))="",FALSE,IF(ISERROR('Haq — Monthly P&L and cash'!F5>=18),'Haq — Monthly P&L and cash'!F5>=18,IF('Haq — Monthly P&L and cash'!F5="","",'Haq — Monthly P&L and cash'!F5>=18))),IF('Model inputs'!AJ48="","",'Model inputs'!AJ48),IF(IF(IF(ISERROR('Haq — Monthly P&L and cash'!F5>=15),'Haq — Monthly P&L and cash'!F5>=15,IF('Haq — Monthly P&L and cash'!F5="","",'Haq — Monthly P&L and cash'!F5>=15))="",FALSE,IF(ISERROR('Haq — Monthly P&L and cash'!F5>=15),'Haq — Monthly P&L and cash'!F5>=15,IF('Haq — Monthly P&L and cash'!F5="","",'Haq — Monthly P&L and cash'!F5>=15))),IF('Model inputs'!AJ47="","",'Model inputs'!AJ47),IF(IF(IF(ISERROR('Haq — Monthly P&L and cash'!F5>=12),'Haq — Monthly P&L and cash'!F5>=12,IF('Haq — Monthly P&L and cash'!F5="","",'Haq — Monthly P&L and cash'!F5>=12))="",FALSE,IF(ISERROR('Haq — Monthly P&L and cash'!F5>=12),'Haq — Monthly P&L and cash'!F5>=12,IF('Haq — Monthly P&L and cash'!F5="","",'Haq — Monthly P&L and cash'!F5>=12))),IF('Model inputs'!AJ46="","",'Model inputs'!AJ46),IF(IF(IF(ISERROR('Haq — Monthly P&L and cash'!F5>=9),'Haq — Monthly P&L and cash'!F5>=9,IF('Haq — Monthly P&L and cash'!F5="","",'Haq — Monthly P&L and cash'!F5>=9))="",FALSE,IF(ISERROR('Haq — Monthly P&L and cash'!F5>=9),'Haq — Monthly P&L and cash'!F5>=9,IF('Haq — Monthly P&L and cash'!F5="","",'Haq — Monthly P&L and cash'!F5>=9))),IF('Model inputs'!AJ53="","",'Model inputs'!AJ53),IF(IF(IF(ISERROR('Haq — Monthly P&L and cash'!F5>=6),'Haq — Monthly P&L and cash'!F5>=6,IF('Haq — Monthly P&L and cash'!F5="","",'Haq — Monthly P&L and cash'!F5>=6))="",FALSE,IF(ISERROR('Haq — Monthly P&L and cash'!F5>=6),'Haq — Monthly P&L and cash'!F5>=6,IF('Haq — Monthly P&L and cash'!F5="","",'Haq — Monthly P&L and cash'!F5>=6))),IF('Model inputs'!AJ52="","",'Model inputs'!AJ52),0)))))))) -> 0 | G11: =IF(IF(IF(ISERROR('Haq — Monthly P&L and cash'!G5>=24),'Haq — Monthly P&L and cash'!G5>=24,IF('Haq — Monthly P&L and cash'!G5="","",'Haq — Monthly P&L and cash'!G5>=24))="",FALSE,IF(ISERROR('Haq — Monthly P&L and cash'!G5>=24),'Haq — Monthly P&L and cash'!G5>=24,IF('Haq — Monthly P&L and cash'!G5="","",'Haq — Monthly P&L and cash'!G5>=24))),IF('Model inputs'!AJ51="","",'Model inputs'!AJ51),IF(IF(IF(ISERROR('Haq — Monthly P&L and cash'!G5>=23),'Haq — Monthly P&L and cash'!G5>=23,IF('Haq — Monthly P&L and cash'!G5="","",'Haq — Monthly P&L and cash'!G5>=23))="",FALSE,IF(ISERROR('Haq — Monthly P&L and cash'!G5>=23),'Haq — Monthly P&L and cash'!G5>=23,IF('Haq — Monthly P&L and cash'!G5="","",'Haq — Monthly P&L and cash'!G5>=23))),IF('Model inputs'!AJ50="","",'Model inputs'!AJ50),IF(IF(IF(ISERROR('Haq — Monthly P&L and cash'!G5>=21),'Haq — Monthly P&L and cash'!G5>=21,IF('Haq — Monthly P&L and cash'!G5="","",'Haq — Monthly P&L and cash'!G5>=21))="",FALSE,IF(ISERROR('Haq — Monthly P&L and cash'!G5>=21),'Haq — Monthly P&L and cash'!G5>=21,IF('Haq — Monthly P&L and cash'!G5="","",'Haq — Monthly P&L and cash'!G5>=21))),IF('Model inputs'!AJ49="","",'Model inputs'!AJ49),IF(IF(IF(ISERROR('Haq — Monthly P&L and cash'!G5>=18),'Haq — Monthly P&L and cash'!G5>=18,IF('Haq — Monthly P&L and cash'!G5="","",'Haq — Monthly P&L and cash'!G5>=18))="",FALSE,IF(ISERROR('Haq — Monthly P&L and cash'!G5>=18),'Haq — Monthly P&L and cash'!G5>=18,IF('Haq — Monthly P&L and cash'!G5="","",'Haq — Monthly P&L and cash'!G5>=18))),IF('Model inputs'!AJ48="","",'Model inputs'!AJ48),IF(IF(IF(ISERROR('Haq — Monthly P&L and cash'!G5>=15),'Haq — Monthly P&L and cash'!G5>=15,IF('Haq — Monthly P&L and cash'!G5="","",'Haq — Monthly P&L and cash'!G5>=15))="",FALSE,IF(ISERROR('Haq — Monthly P&L and cash'!G5>=15),'Haq — Monthly P&L and cash'!G5>=15,IF('Haq — Monthly P&L and cash'!G5="","",'Haq — Monthly P&L and cash'!G5>=15))),IF('Model inputs'!AJ47="","",'Model inputs'!AJ47),IF(IF(IF(ISERROR('Haq — Monthly P&L and cash'!G5>=12),'Haq — Monthly P&L and cash'!G5>=12,IF('Haq — Monthly P&L and cash'!G5="","",'Haq — Monthly P&L and cash'!G5>=12))="",FALSE,IF(ISERROR('Haq — Monthly P&L and cash'!G5>=12),'Haq — Monthly P&L and cash'!G5>=12,IF('Haq — Monthly P&L and cash'!G5="","",'Haq — Monthly P&L and cash'!G5>=12))),IF('Model inputs'!AJ46="","",'Model inputs'!AJ46),IF(IF(IF(ISERROR('Haq — Monthly P&L and cash'!G5>=9),'Haq — Monthly P&L and cash'!G5>=9,IF('Haq — Monthly P&L and cash'!G5="","",'Haq — Monthly P&L and cash'!G5>=9))="",FALSE,IF(ISERROR('Haq — Monthly P&L and cash'!G5>=9),'Haq — Monthly P&L and cash'!G5>=9,IF('Haq — Monthly P&L and cash'!G5="","",'Haq — Monthly P&L and cash'!G5>=9))),IF('Model inputs'!AJ53="","",'Model inputs'!AJ53),IF(IF(IF(ISERROR('Haq — Monthly P&L and cash'!G5>=6),'Haq — Monthly P&L and cash'!G5>=6,IF('Haq — Monthly P&L and cash'!G5="","",'Haq — Monthly P&L and cash'!G5>=6))="",FALSE,IF(ISERROR('Haq — Monthly P&L and cash'!G5>=6),'Haq — Monthly P&L and cash'!G5>=6,IF('Haq — Monthly P&L and cash'!G5="","",'Haq — Monthly P&L and cash'!G5>=6))),IF('Model inputs'!AJ52="","",'Model inputs'!AJ52),0)))))))) -> 1 | H11: =IF(IF(IF(ISERROR('Haq — Monthly P&L and cash'!H5>=24),'Haq — Monthly P&L and cash'!H5>=24,IF('Haq — Monthly P&L and cash'!H5="","",'Haq — Monthly P&L and cash'!H5>=24))="",FALSE,IF(ISERROR('Haq — Monthly P&L and cash'!H5>=24),'Haq — Monthly P&L and cash'!H5>=24,IF('Haq — Monthly P&L and cash'!H5="","",'Haq — Monthly P&L and cash'!H5>=24))),IF('Model inputs'!AJ51="","",'Model inputs'!AJ51),IF(IF(IF(ISERROR('Haq — Monthly P&L and cash'!H5>=23),'Haq — Monthly P&L and cash'!H5>=23,IF('Haq — Monthly P&L and cash'!H5="","",'Haq — Monthly P&L and cash'!H5>=23))="",FALSE,IF(ISERROR('Haq — Monthly P&L and cash'!H5>=23),'Haq — Monthly P&L and cash'!H5>=23,IF('Haq — Monthly P&L and cash'!H5="","",'Haq — Monthly P&L and cash'!H5>=23))),IF('Model inputs'!AJ50="","",'Model inputs'!AJ50),IF(IF(IF(ISERROR('Haq — Monthly P&L and cash'!H5>=21),'Haq — Monthly P&L and cash'!H5>=21,IF('Haq — Monthly P&L and cash'!H5="","",'Haq — Monthly P&L and cash'!H5>=21))="",FALSE,IF(ISERROR('Haq — Monthly P&L and cash'!H5>=21),'Haq — Monthly P&L and cash'!H5>=21,IF('Haq — Monthly P&L and cash'!H5="","",'Haq — Monthly P&L and cash'!H5>=21))),IF('Model inputs'!AJ49="","",'Model inputs'!AJ49),IF(IF(IF(ISERROR('Haq — Monthly P&L and cash'!H5>=18),'Haq — Monthly P&L and cash'!H5>=18,IF('Haq — Monthly P&L and cash'!H5="","",'Haq — Monthly P&L and cash'!H5>=18))="",FALSE,IF(ISERROR('Haq — Monthly P&L and cash'!H5>=18),'Haq — Monthly P&L and cash'!H5>=18,IF('Haq — Monthly P&L and cash'!H5="","",'Haq — Monthly P&L and cash'!H5>=18))),IF('Model inputs'!AJ48="","",'Model inputs'!AJ48),IF(IF(IF(ISERROR('Haq — Monthly P&L and cash'!H5>=15),'Haq — Monthly P&L and cash'!H5>=15,IF('Haq — Monthly P&L and cash'!H5="","",'Haq — Monthly P&L and cash'!H5>=15))="",FALSE,IF(ISERROR('Haq — Monthly P&L and cash'!H5>=15),'Haq — Monthly P&L and cash'!H5>=15,IF('Haq — Monthly P&L and cash'!H5="","",'Haq — Monthly P&L and cash'!H5>=15))),IF('Model inputs'!AJ47="","",'Model inputs'!AJ47),IF(IF(IF(ISERROR('Haq — Monthly P&L and cash'!H5>=12),'Haq — Monthly P&L and cash'!H5>=12,IF('Haq — Monthly P&L and cash'!H5="","",'Haq — Monthly P&L and cash'!H5>=12))="",FALSE,IF(ISERROR('Haq — Monthly P&L and cash'!H5>=12),'Haq — Monthly P&L and cash'!H5>=12,IF('Haq — Monthly P&L and cash'!H5="","",'Haq — Monthly P&L and cash'!H5>=12))),IF('Model inputs'!AJ46="","",'Model inputs'!AJ46),IF(IF(IF(ISERROR('Haq — Monthly P&L and cash'!H5>=9),'Haq — Monthly P&L and cash'!H5>=9,IF('Haq — Monthly P&L and cash'!H5="","",'Haq — Monthly P&L and cash'!H5>=9))="",FALSE,IF(ISERROR('Haq — Monthly P&L and cash'!H5>=9),'Haq — Monthly P&L and cash'!H5>=9,IF('Haq — Monthly P&L and cash'!H5="","",'Haq — Monthly P&L and cash'!H5>=9))),IF('Model inputs'!AJ53="","",'Model inputs'!AJ53),IF(IF(IF(ISERROR('Haq — Monthly P&L and cash'!H5>=6),'Haq — Monthly P&L and cash'!H5>=6,IF('Haq — Monthly P&L and cash'!H5="","",'Haq — Monthly P&L and cash'!H5>=6))="",FALSE,IF(ISERROR('Haq — Monthly P&L and cash'!H5>=6),'Haq — Monthly P&L and cash'!H5>=6,IF('Haq — Monthly P&L and cash'!H5="","",'Haq — Monthly P&L and cash'!H5>=6))),IF('Model inputs'!AJ52="","",'Model inputs'!AJ52),0)))))))) -> 1 | I11: =IF(IF(IF(ISERROR('Haq — Monthly P&L and cash'!I5>=24),'Haq — Monthly P&L and cash'!I5>=24,IF('Haq — Monthly P&L and cash'!I5="","",'Haq — Monthly P&L and cash'!I5>=24))="",FALSE,IF(ISERROR('Haq — Monthly P&L and cash'!I5>=24),'Haq — Monthly P&L and cash'!I5>=24,IF('Haq — Monthly P&L and cash'!I5="","",'Haq — Monthly P&L and cash'!I5>=24))),IF('Model inputs'!AJ51="","",'Model inputs'!AJ51),IF(IF(IF(ISERROR('Haq — Monthly P&L and cash'!I5>=23),'Haq — Monthly P&L and cash'!I5>=23,IF('Haq — Monthly P&L and cash'!I5="","",'Haq — Monthly P&L and cash'!I5>=23))="",FALSE,IF(ISERROR('Haq — Monthly P&L and cash'!I5>=23),'Haq — Monthly P&L and cash'!I5>=23,IF('Haq — Monthly P&L and cash'!I5="","",'Haq — Monthly P&L and cash'!I5>=23))),IF('Model inputs'!AJ50="","",'Model inputs'!AJ50),IF(IF(IF(ISERROR('Haq — Monthly P&L and cash'!I5>=21),'Haq — Monthly P&L and cash'!I5>=21,IF('Haq — Monthly P&L and cash'!I5="","",'Haq — Monthly P&L and cash'!I5>=21))="",FALSE,IF(ISERROR('Haq — Monthly P&L and cash'!I5>=21),'Haq — Monthly P&L and cash'!I5>=21,IF('Haq — Monthly P&L and cash'!I5="","",'Haq — Monthly P&L and cash'!I5>=21))),IF('Model inputs'!AJ49="","",'Model inputs'!AJ49),IF(IF(IF(ISERROR('Haq — Monthly P&L and cash'!I5>=18),'Haq — Monthly P&L and cash'!I5>=18,IF('Haq — Monthly P&L and cash'!I5="","",'Haq — Monthly P&L and cash'!I5>=18))="",FALSE,IF(ISERROR('Haq — Monthly P&L and cash'!I5>=18),'Haq — Monthly P&L and cash'!I5>=18,IF('Haq — Monthly P&L and cash'!I5="","",'Haq — Monthly P&L and cash'!I5>=18))),IF('Model inputs'!AJ48="","",'Model inputs'!AJ48),IF(IF(IF(ISERROR('Haq — Monthly P&L and cash'!I5>=15),'Haq — Monthly P&L and cash'!I5>=15,IF('Haq — Monthly P&L and cash'!I5="","",'Haq — Monthly P&L and cash'!I5>=15))="",FALSE,IF(ISERROR('Haq — Monthly P&L and cash'!I5>=15),'Haq — Monthly P&L and cash'!I5>=15,IF('Haq — Monthly P&L and cash'!I5="","",'Haq — Monthly P&L and cash'!I5>=15))),IF('Model inputs'!AJ47="","",'Model inputs'!AJ47),IF(IF(IF(ISERROR('Haq — Monthly P&L and cash'!I5>=12),'Haq — Monthly P&L and cash'!I5>=12,IF('Haq — Monthly P&L and cash'!I5="","",'Haq — Monthly P&L and cash'!I5>=12))="",FALSE,IF(ISERROR('Haq — Monthly P&L and cash'!I5>=12),'Haq — Monthly P&L and cash'!I5>=12,IF('Haq — Monthly P&L and cash'!I5="","",'Haq — Monthly P&L and cash'!I5>=12))),IF('Model inputs'!AJ46="","",'Model inputs'!AJ46),IF(IF(IF(ISERROR('Haq — Monthly P&L and cash'!I5>=9),'Haq — Monthly P&L and cash'!I5>=9,IF('Haq — Monthly P&L and cash'!I5="","",'Haq — Monthly P&L and cash'!I5>=9))="",FALSE,IF(ISERROR('Haq — Monthly P&L and cash'!I5>=9),'Haq — Monthly P&L and cash'!I5>=9,IF('Haq — Monthly P&L and cash'!I5="","",'Haq — Monthly P&L and cash'!I5>=9))),IF('Model inputs'!AJ53="","",'Model inputs'!AJ53),IF(IF(IF(ISERROR('Haq — Monthly P&L and cash'!I5>=6),'Haq — Monthly P&L and cash'!I5>=6,IF('Haq — Monthly P&L and cash'!I5="","",'Haq — Monthly P&L and cash'!I5>=6))="",FALSE,IF(ISERROR('Haq — Monthly P&L and cash'!I5>=6),'Haq — Monthly P&L and cash'!I5>=6,IF('Haq — Monthly P&L and cash'!I5="","",'Haq — Monthly P&L and cash'!I5>=6))),IF('Model inputs'!AJ52="","",'Model inputs'!AJ52),0)))))))) -> 1 | J11: =IF(IF(IF(ISERROR('Haq — Monthly P&L and cash'!J5>=24),'Haq — Monthly P&L and cash'!J5>=24,IF('Haq — Monthly P&L and cash'!J5="","",'Haq — Monthly P&L and cash'!J5>=24))="",FALSE,IF(ISERROR('Haq — Monthly P&L and cash'!J5>=24),'Haq — Monthly P&L and cash'!J5>=24,IF('Haq — Monthly P&L and cash'!J5="","",'Haq — Monthly P&L and cash'!J5>=24))),IF('Model inputs'!AJ51="","",'Model inputs'!AJ51),IF(IF(IF(ISERROR('Haq — Monthly P&L and cash'!J5>=23),'Haq — Monthly P&L and cash'!J5>=23,IF('Haq — Monthly P&L and cash'!J5="","",'Haq — Monthly P&L and cash'!J5>=23))="",FALSE,IF(ISERROR('Haq — Monthly P&L and cash'!J5>=23),'Haq — Monthly P&L and cash'!J5>=23,IF('Haq — Monthly P&L and cash'!J5="","",'Haq — Monthly P&L and cash'!J5>=23))),IF('Model inputs'!AJ50="","",'Model inputs'!AJ50),IF(IF(IF(ISERROR('Haq — Monthly P&L and cash'!J5>=21),'Haq — Monthly P&L and cash'!J5>=21,IF('Haq — Monthly P&L and cash'!J5="","",'Haq — Monthly P&L and cash'!J5>=21))="",FALSE,IF(ISERROR('Haq — Monthly P&L and cash'!J5>=21),'Haq — Monthly P&L and cash'!J5>=21,IF('Haq — Monthly P&L and cash'!J5="","",'Haq — Monthly P&L and cash'!J5>=21))),IF('Model inputs'!AJ49="","",'Model inputs'!AJ49),IF(IF(IF(ISERROR('Haq — Monthly P&L and cash'!J5>=18),'Haq — Monthly P&L and cash'!J5>=18,IF('Haq — Monthly P&L and cash'!J5="","",'Haq — Monthly P&L and cash'!J5>=18))="",FALSE,IF(ISERROR('Haq — Monthly P&L and cash'!J5>=18),'Haq — Monthly P&L and cash'!J5>=18,IF('Haq — Monthly P&L and cash'!J5="","",'Haq — Monthly P&L and cash'!J5>=18))),IF('Model inputs'!AJ48="","",'Model inputs'!AJ48),IF(IF(IF(ISERROR('Haq — Monthly P&L and cash'!J5>=15),'Haq — Monthly P&L and cash'!J5>=15,IF('Haq — Monthly P&L and cash'!J5="","",'Haq — Monthly P&L and cash'!J5>=15))="",FALSE,IF(ISERROR('Haq — Monthly P&L and cash'!J5>=15),'Haq — Monthly P&L and cash'!J5>=15,IF('Haq — Monthly P&L and cash'!J5="","",'Haq — Monthly P&L and cash'!J5>=15))),IF('Model inputs'!AJ47="","",'Model inputs'!AJ47),IF(IF(IF(ISERROR('Haq — Monthly P&L and cash'!J5>=12),'Haq — Monthly P&L and cash'!J5>=12,IF('Haq — Monthly P&L and cash'!J5="","",'Haq — Monthly P&L and cash'!J5>=12))="",FALSE,IF(ISERROR('Haq — Monthly P&L and cash'!J5>=12),'Haq — Monthly P&L and cash'!J5>=12,IF('Haq — Monthly P&L and cash'!J5="","",'Haq — Monthly P&L and cash'!J5>=12))),IF('Model inputs'!AJ46="","",'Model inputs'!AJ46),IF(IF(IF(ISERROR('Haq — Monthly P&L and cash'!J5>=9),'Haq — Monthly P&L and cash'!J5>=9,IF('Haq — Monthly P&L and cash'!J5="","",'Haq — Monthly P&L and cash'!J5>=9))="",FALSE,IF(ISERROR('Haq — Monthly P&L and cash'!J5>=9),'Haq — Monthly P&L and cash'!J5>=9,IF('Haq — Monthly P&L and cash'!J5="","",'Haq — Monthly P&L and cash'!J5>=9))),IF('Model inputs'!AJ53="","",'Model inputs'!AJ53),IF(IF(IF(ISERROR('Haq — Monthly P&L and cash'!J5>=6),'Haq — Monthly P&L and cash'!J5>=6,IF('Haq — Monthly P&L and cash'!J5="","",'Haq — Monthly P&L and cash'!J5>=6))="",FALSE,IF(ISERROR('Haq — Monthly P&L and cash'!J5>=6),'Haq — Monthly P&L and cash'!J5>=6,IF('Haq — Monthly P&L and cash'!J5="","",'Haq — Monthly P&L and cash'!J5>=6))),IF('Model inputs'!AJ52="","",'Model inputs'!AJ52),0)))))))) -> 2 | K11: =IF(IF(IF(ISERROR('Haq — Monthly P&L and cash'!K5>=24),'Haq — Monthly P&L and cash'!K5>=24,IF('Haq — Monthly P&L and cash'!K5="","",'Haq — Monthly P&L and cash'!K5>=24))="",FALSE,IF(ISERROR('Haq — Monthly P&L and cash'!K5>=24),'Haq — Monthly P&L and cash'!K5>=24,IF('Haq — Monthly P&L and cash'!K5="","",'Haq — Monthly P&L and cash'!K5>=24))),IF('Model inputs'!AJ51="","",'Model inputs'!AJ51),IF(IF(IF(ISERROR('Haq — Monthly P&L and cash'!K5>=23),'Haq — Monthly P&L and cash'!K5>=23,IF('Haq — Monthly P&L and cash'!K5="","",'Haq — Monthly P&L and cash'!K5>=23))="",FALSE,IF(ISERROR('Haq — Monthly P&L and cash'!K5>=23),'Haq — Monthly P&L and cash'!K5>=23,IF('Haq — Monthly P&L and cash'!K5="","",'Haq — Monthly P&L and cash'!K5>=23))),IF('Model inputs'!AJ50="","",'Model inputs'!AJ50),IF(IF(IF(ISERROR('Haq — Monthly P&L and cash'!K5>=21),'Haq — Monthly P&L and cash'!K5>=21,IF('Haq — Monthly P&L and cash'!K5="","",'Haq — Monthly P&L and cash'!K5>=21))="",FALSE,IF(ISERROR('Haq — Monthly P&L and cash'!K5>=21),'Haq — Monthly P&L and cash'!K5>=21,IF('Haq — Monthly P&L and cash'!K5="","",'Haq — Monthly P&L and cash'!K5>=21))),IF('Model inputs'!AJ49="","",'Model inputs'!AJ49),IF(IF(IF(ISERROR('Haq — Monthly P&L and cash'!K5>=18),'Haq — Monthly P&L and cash'!K5>=18,IF('Haq — Monthly P&L and cash'!K5="","",'Haq — Monthly P&L and cash'!K5>=18))="",FALSE,IF(ISERROR('Haq — Monthly P&L and cash'!K5>=18),'Haq — Monthly P&L and cash'!K5>=18,IF('Haq — Monthly P&L and cash'!K5="","",'Haq — Monthly P&L and cash'!K5>=18))),IF('Model inputs'!AJ48="","",'Model inputs'!AJ48),IF(IF(IF(ISERROR('Haq — Monthly P&L and cash'!K5>=15),'Haq — Monthly P&L and cash'!K5>=15,IF('Haq — Monthly P&L and cash'!K5="","",'Haq — Monthly P&L and cash'!K5>=15))="",FALSE,IF(ISERROR('Haq — Monthly P&L and cash'!K5>=15),'Haq — Monthly P&L and cash'!K5>=15,IF('Haq — Monthly P&L and cash'!K5="","",'Haq — Monthly P&L and cash'!K5>=15))),IF('Model inputs'!AJ47="","",'Model inputs'!AJ47),IF(IF(IF(ISERROR('Haq — Monthly P&L and cash'!K5>=12),'Haq — Monthly P&L and cash'!K5>=12,IF('Haq — Monthly P&L and cash'!K5="","",'Haq — Monthly P&L and cash'!K5>=12))="",FALSE,IF(ISERROR('Haq — Monthly P&L and cash'!K5>=12),'Haq — Monthly P&L and cash'!K5>=12,IF('Haq — Monthly P&L and cash'!K5="","",'Haq — Monthly P&L and cash'!K5>=12))),IF('Model inputs'!AJ46="","",'Model inputs'!AJ46),IF(IF(IF(ISERROR('Haq — Monthly P&L and cash'!K5>=9),'Haq — Monthly P&L and cash'!K5>=9,IF('Haq — Monthly P&L and cash'!K5="","",'Haq — Monthly P&L and cash'!K5>=9))="",FALSE,IF(ISERROR('Haq — Monthly P&L and cash'!K5>=9),'Haq — Monthly P&L and cash'!K5>=9,IF('Haq — Monthly P&L and cash'!K5="","",'Haq — Monthly P&L and cash'!K5>=9))),IF('Model inputs'!AJ53="","",'Model inputs'!AJ53),IF(IF(IF(ISERROR('Haq — Monthly P&L and cash'!K5>=6),'Haq — Monthly P&L and cash'!K5>=6,IF('Haq — Monthly P&L and cash'!K5="","",'Haq — Monthly P&L and cash'!K5>=6))="",FALSE,IF(ISERROR('Haq — Monthly P&L and cash'!K5>=6),'Haq — Monthly P&L and cash'!K5>=6,IF('Haq — Monthly P&L and cash'!K5="","",'Haq — Monthly P&L and cash'!K5>=6))),IF('Model inputs'!AJ52="","",'Model inputs'!AJ52),0)))))))) -> 2 | L11: =IF(IF(IF(ISERROR('Haq — Monthly P&L and cash'!L5>=24),'Haq — Monthly P&L and cash'!L5>=24,IF('Haq — Monthly P&L and cash'!L5="","",'Haq — Monthly P&L and cash'!L5>=24))="",FALSE,IF(ISERROR('Haq — Monthly P&L and cash'!L5>=24),'Haq — Monthly P&L and cash'!L5>=24,IF('Haq — Monthly P&L and cash'!L5="","",'Haq — Monthly P&L and cash'!L5>=24))),IF('Model inputs'!AJ51="","",'Model inputs'!AJ51),IF(IF(IF(ISERROR('Haq — Monthly P&L and cash'!L5>=23),'Haq — Monthly P&L and cash'!L5>=23,IF('Haq — Monthly P&L and cash'!L5="","",'Haq — Monthly P&L and cash'!L5>=23))="",FALSE,IF(ISERROR('Haq — Monthly P&L and cash'!L5>=23),'Haq — Monthly P&L and cash'!L5>=23,IF('Haq — Monthly P&L and cash'!L5="","",'Haq — Monthly P&L and cash'!L5>=23))),IF('Model inputs'!AJ50="","",'Model inputs'!AJ50),IF(IF(IF(ISERROR('Haq — Monthly P&L and cash'!L5>=21),'Haq — Monthly P&L and cash'!L5>=21,IF('Haq — Monthly P&L and cash'!L5="","",'Haq — Monthly P&L and cash'!L5>=21))="",FALSE,IF(ISERROR('Haq — Monthly P&L and cash'!L5>=21),'Haq — Monthly P&L and cash'!L5>=21,IF('Haq — Monthly P&L and cash'!L5="","",'Haq — Monthly P&L and cash'!L5>=21))),IF('Model inputs'!AJ49="","",'Model inputs'!AJ49),IF(IF(IF(ISERROR('Haq — Monthly P&L and cash'!L5>=18),'Haq — Monthly P&L and cash'!L5>=18,IF('Haq — Monthly P&L and cash'!L5="","",'Haq — Monthly P&L and cash'!L5>=18))="",FALSE,IF(ISERROR('Haq — Monthly P&L and cash'!L5>=18),'Haq — Monthly P&L and cash'!L5>=18,IF('Haq — Monthly P&L and cash'!L5="","",'Haq — Monthly P&L and cash'!L5>=18))),IF('Model inputs'!AJ48="","",'Model inputs'!AJ48),IF(IF(IF(ISERROR('Haq — Monthly P&L and cash'!L5>=15),'Haq — Monthly P&L and cash'!L5>=15,IF('Haq — Monthly P&L and cash'!L5="","",'Haq — Monthly P&L and cash'!L5>=15))="",FALSE,IF(ISERROR('Haq — Monthly P&L and cash'!L5>=15),'Haq — Monthly P&L and cash'!L5>=15,IF('Haq — Monthly P&L and cash'!L5="","",'Haq — Monthly P&L and cash'!L5>=15))),IF('Model inputs'!AJ47="","",'Model inputs'!AJ47),IF(IF(IF(ISERROR('Haq — Monthly P&L and cash'!L5>=12),'Haq — Monthly P&L and cash'!L5>=12,IF('Haq — Monthly P&L and cash'!L5="","",'Haq — Monthly P&L and cash'!L5>=12))="",FALSE,IF(ISERROR('Haq — Monthly P&L and cash'!L5>=12),'Haq — Monthly P&L and cash'!L5>=12,IF('Haq — Monthly P&L and cash'!L5="","",'Haq — Monthly P&L and cash'!L5>=12))),IF('Model inputs'!AJ46="","",'Model inputs'!AJ46),IF(IF(IF(ISERROR('Haq — Monthly P&L and cash'!L5>=9),'Haq — Monthly P&L and cash'!L5>=9,IF('Haq — Monthly P&L and cash'!L5="","",'Haq — Monthly P&L and cash'!L5>=9))="",FALSE,IF(ISERROR('Haq — Monthly P&L and cash'!L5>=9),'Haq — Monthly P&L and cash'!L5>=9,IF('Haq — Monthly P&L and cash'!L5="","",'Haq — Monthly P&L and cash'!L5>=9))),IF('Model inputs'!AJ53="","",'Model inputs'!AJ53),IF(IF(IF(ISERROR('Haq — Monthly P&L and cash'!L5>=6),'Haq — Monthly P&L and cash'!L5>=6,IF('Haq — Monthly P&L and cash'!L5="","",'Haq — Monthly P&L and cash'!L5>=6))="",FALSE,IF(ISERROR('Haq — Monthly P&L and cash'!L5>=6),'Haq — Monthly P&L and cash'!L5>=6,IF('Haq — Monthly P&L and cash'!L5="","",'Haq — Monthly P&L and cash'!L5>=6))),IF('Model inputs'!AJ52="","",'Model inputs'!AJ52),0)))))))) -> 2 | M11: =IF(IF(IF(ISERROR('Haq — Monthly P&L and cash'!M5>=24),'Haq — Monthly P&L and cash'!M5>=24,IF('Haq — Monthly P&L and cash'!M5="","",'Haq — Monthly P&L and cash'!M5>=24))="",FALSE,IF(ISERROR('Haq — Monthly P&L and cash'!M5>=24),'Haq — Monthly P&L and cash'!M5>=24,IF('Haq — Monthly P&L and cash'!M5="","",'Haq — Monthly P&L and cash'!M5>=24))),IF('Model inputs'!AJ51="","",'Model inputs'!AJ51),IF(IF(IF(ISERROR('Haq — Monthly P&L and cash'!M5>=23),'Haq — Monthly P&L and cash'!M5>=23,IF('Haq — Monthly P&L and cash'!M5="","",'Haq — Monthly P&L and cash'!M5>=23))="",FALSE,IF(ISERROR('Haq — Monthly P&L and cash'!M5>=23),'Haq — Monthly P&L and cash'!M5>=23,IF('Haq — Monthly P&L and cash'!M5="","",'Haq — Monthly P&L and cash'!M5>=23))),IF('Model inputs'!AJ50="","",'Model inputs'!AJ50),IF(IF(IF(ISERROR('Haq — Monthly P&L and cash'!M5>=21),'Haq — Monthly P&L and cash'!M5>=21,IF('Haq — Monthly P&L and cash'!M5="","",'Haq — Monthly P&L and cash'!M5>=21))="",FALSE,IF(ISERROR('Haq — Monthly P&L and cash'!M5>=21),'Haq — Monthly P&L and cash'!M5>=21,IF('Haq — Monthly P&L and cash'!M5="","",'Haq — Monthly P&L and cash'!M5>=21))),IF('Model inputs'!AJ49="","",'Model inputs'!AJ49),IF(IF(IF(ISERROR('Haq — Monthly P&L and cash'!M5>=18),'Haq — Monthly P&L and cash'!M5>=18,IF('Haq — Monthly P&L and cash'!M5="","",'Haq — Monthly P&L and cash'!M5>=18))="",FALSE,IF(ISERROR('Haq — Monthly P&L and cash'!M5>=18),'Haq — Monthly P&L and cash'!M5>=18,IF('Haq — Monthly P&L and cash'!M5="","",'Haq — Monthly P&L and cash'!M5>=18))),IF('Model inputs'!AJ48="","",'Model inputs'!AJ48),IF(IF(IF(ISERROR('Haq — Monthly P&L and cash'!M5>=15),'Haq — Monthly P&L and cash'!M5>=15,IF('Haq — Monthly P&L and cash'!M5="","",'Haq — Monthly P&L and cash'!M5>=15))="",FALSE,IF(ISERROR('Haq — Monthly P&L and cash'!M5>=15),'Haq — Monthly P&L and cash'!M5>=15,IF('Haq — Monthly P&L and cash'!M5="","",'Haq — Monthly P&L and cash'!M5>=15))),IF('Model inputs'!AJ47="","",'Model inputs'!AJ47),IF(IF(IF(ISERROR('Haq — Monthly P&L and cash'!M5>=12),'Haq — Monthly P&L and cash'!M5>=12,IF('Haq — Monthly P&L and cash'!M5="","",'Haq — Monthly P&L and cash'!M5>=12))="",FALSE,IF(ISERROR('Haq — Monthly P&L and cash'!M5>=12),'Haq — Monthly P&L and cash'!M5>=12,IF('Haq — Monthly P&L and cash'!M5="","",'Haq — Monthly P&L and cash'!M5>=12))),IF('Model inputs'!AJ46="","",'Model inputs'!AJ46),IF(IF(IF(ISERROR('Haq — Monthly P&L and cash'!M5>=9),'Haq — Monthly P&L and cash'!M5>=9,IF('Haq — Monthly P&L and cash'!M5="","",'Haq — Monthly P&L and cash'!M5>=9))="",FALSE,IF(ISERROR('Haq — Monthly P&L and cash'!M5>=9),'Haq — Monthly P&L and cash'!M5>=9,IF('Haq — Monthly P&L and cash'!M5="","",'Haq — Monthly P&L and cash'!M5>=9))),IF('Model inputs'!AJ53="","",'Model inputs'!AJ53),IF(IF(IF(ISERROR('Haq — Monthly P&L and cash'!M5>=6),'Haq — Monthly P&L and cash'!M5>=6,IF('Haq — Monthly P&L and cash'!M5="","",'Haq — Monthly P&L and cash'!M5>=6))="",FALSE,IF(ISERROR('Haq — Monthly P&L and cash'!M5>=6),'Haq — Monthly P&L and cash'!M5>=6,IF('Haq — Monthly P&L and cash'!M5="","",'Haq — Monthly P&L and cash'!M5>=6))),IF('Model inputs'!AJ52="","",'Model inputs'!AJ52),0)))))))) -> 3 | N11: =IF(IF(IF(ISERROR('Haq — Monthly P&L and cash'!N5>=24),'Haq — Monthly P&L and cash'!N5>=24,IF('Haq — Monthly P&L and cash'!N5="","",'Haq — Monthly P&L and cash'!N5>=24))="",FALSE,IF(ISERROR('Haq — Monthly P&L and cash'!N5>=24),'Haq — Monthly P&L and cash'!N5>=24,IF('Haq — Monthly P&L and cash'!N5="","",'Haq — Monthly P&L and cash'!N5>=24))),IF('Model inputs'!AJ51="","",'Model inputs'!AJ51),IF(IF(IF(ISERROR('Haq — Monthly P&L and cash'!N5>=23),'Haq — Monthly P&L and cash'!N5>=23,IF('Haq — Monthly P&L and cash'!N5="","",'Haq — Monthly P&L and cash'!N5>=23))="",FALSE,IF(ISERROR('Haq — Monthly P&L and cash'!N5>=23),'Haq — Monthly P&L and cash'!N5>=23,IF('Haq — Monthly P&L and cash'!N5="","",'Haq — Monthly P&L and cash'!N5>=23))),IF('Model inputs'!AJ50="","",'Model inputs'!AJ50),IF(IF(IF(ISERROR('Haq — Monthly P&L and cash'!N5>=21),'Haq — Monthly P&L and cash'!N5>=21,IF('Haq — Monthly P&L and cash'!N5="","",'Haq — Monthly P&L and cash'!N5>=21))="",FALSE,IF(ISERROR('Haq — Monthly P&L and cash'!N5>=21),'Haq — Monthly P&L and cash'!N5>=21,IF('Haq — Monthly P&L and cash'!N5="","",'Haq — Monthly P&L and cash'!N5>=21))),IF('Model inputs'!AJ49="","",'Model inputs'!AJ49),IF(IF(IF(ISERROR('Haq — Monthly P&L and cash'!N5>=18),'Haq — Monthly P&L and cash'!N5>=18,IF('Haq — Monthly P&L and cash'!N5="","",'Haq — Monthly P&L and cash'!N5>=18))="",FALSE,IF(ISERROR('Haq — Monthly P&L and cash'!N5>=18),'Haq — Monthly P&L and cash'!N5>=18,IF('Haq — Monthly P&L and cash'!N5="","",'Haq — Monthly P&L and cash'!N5>=18))),IF('Model inputs'!AJ48="","",'Model inputs'!AJ48),IF(IF(IF(ISERROR('Haq — Monthly P&L and cash'!N5>=15),'Haq — Monthly P&L and cash'!N5>=15,IF('Haq — Monthly P&L and cash'!N5="","",'Haq — Monthly P&L and cash'!N5>=15))="",FALSE,IF(ISERROR('Haq — Monthly P&L and cash'!N5>=15),'Haq — Monthly P&L and cash'!N5>=15,IF('Haq — Monthly P&L and cash'!N5="","",'Haq — Monthly P&L and cash'!N5>=15))),IF('Model inputs'!AJ47="","",'Model inputs'!AJ47),IF(IF(IF(ISERROR('Haq — Monthly P&L and cash'!N5>=12),'Haq — Monthly P&L and cash'!N5>=12,IF('Haq — Monthly P&L and cash'!N5="","",'Haq — Monthly P&L and cash'!N5>=12))="",FALSE,IF(ISERROR('Haq — Monthly P&L and cash'!N5>=12),'Haq — Monthly P&L and cash'!N5>=12,IF('Haq — Monthly P&L and cash'!N5="","",'Haq — Monthly P&L and cash'!N5>=12))),IF('Model inputs'!AJ46="","",'Model inputs'!AJ46),IF(IF(IF(ISERROR('Haq — Monthly P&L and cash'!N5>=9),'Haq — Monthly P&L and cash'!N5>=9,IF('Haq — Monthly P&L and cash'!N5="","",'Haq — Monthly P&L and cash'!N5>=9))="",FALSE,IF(ISERROR('Haq — Monthly P&L and cash'!N5>=9),'Haq — Monthly P&L and cash'!N5>=9,IF('Haq — Monthly P&L and cash'!N5="","",'Haq — Monthly P&L and cash'!N5>=9))),IF('Model inputs'!AJ53="","",'Model inputs'!AJ53),IF(IF(IF(ISERROR('Haq — Monthly P&L and cash'!N5>=6),'Haq — Monthly P&L and cash'!N5>=6,IF('Haq — Monthly P&L and cash'!N5="","",'Haq — Monthly P&L and cash'!N5>=6))="",FALSE,IF(ISERROR('Haq — Monthly P&L and cash'!N5>=6),'Haq — Monthly P&L and cash'!N5>=6,IF('Haq — Monthly P&L and cash'!N5="","",'Haq — Monthly P&L and cash'!N5>=6))),IF('Model inputs'!AJ52="","",'Model inputs'!AJ52),0)))))))) -> 3 | O11: =IF(IF(IF(ISERROR('Haq — Monthly P&L and cash'!O5>=24),'Haq — Monthly P&L and cash'!O5>=24,IF('Haq — Monthly P&L and cash'!O5="","",'Haq — Monthly P&L and cash'!O5>=24))="",FALSE,IF(ISERROR('Haq — Monthly P&L and cash'!O5>=24),'Haq — Monthly P&L and cash'!O5>=24,IF('Haq — Monthly P&L and cash'!O5="","",'Haq — Monthly P&L and cash'!O5>=24))),IF('Model inputs'!AJ51="","",'Model inputs'!AJ51),IF(IF(IF(ISERROR('Haq — Monthly P&L and cash'!O5>=23),'Haq — Monthly P&L and cash'!O5>=23,IF('Haq — Monthly P&L and cash'!O5="","",'Haq — Monthly P&L and cash'!O5>=23))="",FALSE,IF(ISERROR('Haq — Monthly P&L and cash'!O5>=23),'Haq — Monthly P&L and cash'!O5>=23,IF('Haq — Monthly P&L and cash'!O5="","",'Haq — Monthly P&L and cash'!O5>=23))),IF('Model inputs'!AJ50="","",'Model inputs'!AJ50),IF(IF(IF(ISERROR('Haq — Monthly P&L and cash'!O5>=21),'Haq — Monthly P&L and cash'!O5>=21,IF('Haq — Monthly P&L and cash'!O5="","",'Haq — Monthly P&L and cash'!O5>=21))="",FALSE,IF(ISERROR('Haq — Monthly P&L and cash'!O5>=21),'Haq — Monthly P&L and cash'!O5>=21,IF('Haq — Monthly P&L and cash'!O5="","",'Haq — Monthly P&L and cash'!O5>=21))),IF('Model inputs'!AJ49="","",'Model inputs'!AJ49),IF(IF(IF(ISERROR('Haq — Monthly P&L and cash'!O5>=18),'Haq — Monthly P&L and cash'!O5>=18,IF('Haq — Monthly P&L and cash'!O5="","",'Haq — Monthly P&L and cash'!O5>=18))="",FALSE,IF(ISERROR('Haq — Monthly P&L and cash'!O5>=18),'Haq — Monthly P&L and cash'!O5>=18,IF('Haq — Monthly P&L and cash'!O5="","",'Haq — Monthly P&L and cash'!O5>=18))),IF('Model inputs'!AJ48="","",'Model inputs'!AJ48),IF(IF(IF(ISERROR('Haq — Monthly P&L and cash'!O5>=15),'Haq — Monthly P&L and cash'!O5>=15,IF('Haq — Monthly P&L and cash'!O5="","",'Haq — Monthly P&L and cash'!O5>=15))="",FALSE,IF(ISERROR('Haq — Monthly P&L and cash'!O5>=15),'Haq — Monthly P&L and cash'!O5>=15,IF('Haq — Monthly P&L and cash'!O5="","",'Haq — Monthly P&L and cash'!O5>=15))),IF('Model inputs'!AJ47="","",'Model inputs'!AJ47),IF(IF(IF(ISERROR('Haq — Monthly P&L and cash'!O5>=12),'Haq — Monthly P&L and cash'!O5>=12,IF('Haq — Monthly P&L and cash'!O5="","",'Haq — Monthly P&L and cash'!O5>=12))="",FALSE,IF(ISERROR('Haq — Monthly P&L and cash'!O5>=12),'Haq — Monthly P&L and cash'!O5>=12,IF('Haq — Monthly P&L and cash'!O5="","",'Haq — Monthly P&L and cash'!O5>=12))),IF('Model inputs'!AJ46="","",'Model inputs'!AJ46),IF(IF(IF(ISERROR('Haq — Monthly P&L and cash'!O5>=9),'Haq — Monthly P&L and cash'!O5>=9,IF('Haq — Monthly P&L and cash'!O5="","",'Haq — Monthly P&L and cash'!O5>=9))="",FALSE,IF(ISERROR('Haq — Monthly P&L and cash'!O5>=9),'Haq — Monthly P&L and cash'!O5>=9,IF('Haq — Monthly P&L and cash'!O5="","",'Haq — Monthly P&L and cash'!O5>=9))),IF('Model inputs'!AJ53="","",'Model inputs'!AJ53),IF(IF(IF(ISERROR('Haq — Monthly P&L and cash'!O5>=6),'Haq — Monthly P&L and cash'!O5>=6,IF('Haq — Monthly P&L and cash'!O5="","",'Haq — Monthly P&L and cash'!O5>=6))="",FALSE,IF(ISERROR('Haq — Monthly P&L and cash'!O5>=6),'Haq — Monthly P&L and cash'!O5>=6,IF('Haq — Monthly P&L and cash'!O5="","",'Haq — Monthly P&L and cash'!O5>=6))),IF('Model inputs'!AJ52="","",'Model inputs'!AJ52),0)))))))) -> 3 | P11: =IF(IF(IF(ISERROR('Haq — Monthly P&L and cash'!P5>=24),'Haq — Monthly P&L and cash'!P5>=24,IF('Haq — Monthly P&L and cash'!P5="","",'Haq — Monthly P&L and cash'!P5>=24))="",FALSE,IF(ISERROR('Haq — Monthly P&L and cash'!P5>=24),'Haq — Monthly P&L and cash'!P5>=24,IF('Haq — Monthly P&L and cash'!P5="","",'Haq — Monthly P&L and cash'!P5>=24))),IF('Model inputs'!AJ51="","",'Model inputs'!AJ51),IF(IF(IF(ISERROR('Haq — Monthly P&L and cash'!P5>=23),'Haq — Monthly P&L and cash'!P5>=23,IF('Haq — Monthly P&L and cash'!P5="","",'Haq — Monthly P&L and cash'!P5>=23))="",FALSE,IF(ISERROR('Haq — Monthly P&L and cash'!P5>=23),'Haq — Monthly P&L and cash'!P5>=23,IF('Haq — Monthly P&L and cash'!P5="","",'Haq — Monthly P&L and cash'!P5>=23))),IF('Model inputs'!AJ50="","",'Model inputs'!AJ50),IF(IF(IF(ISERROR('Haq — Monthly P&L and cash'!P5>=21),'Haq — Monthly P&L and cash'!P5>=21,IF('Haq — Monthly P&L and cash'!P5="","",'Haq — Monthly P&L and cash'!P5>=21))="",FALSE,IF(ISERROR('Haq — Monthly P&L and cash'!P5>=21),'Haq — Monthly P&L and cash'!P5>=21,IF('Haq — Monthly P&L and cash'!P5="","",'Haq — Monthly P&L and cash'!P5>=21))),IF('Model inputs'!AJ49="","",'Model inputs'!AJ49),IF(IF(IF(ISERROR('Haq — Monthly P&L and cash'!P5>=18),'Haq — Monthly P&L and cash'!P5>=18,IF('Haq — Monthly P&L and cash'!P5="","",'Haq — Monthly P&L and cash'!P5>=18))="",FALSE,IF(ISERROR('Haq — Monthly P&L and cash'!P5>=18),'Haq — Monthly P&L and cash'!P5>=18,IF('Haq — Monthly P&L and cash'!P5="","",'Haq — Monthly P&L and cash'!P5>=18))),IF('Model inputs'!AJ48="","",'Model inputs'!AJ48),IF(IF(IF(ISERROR('Haq — Monthly P&L and cash'!P5>=15),'Haq — Monthly P&L and cash'!P5>=15,IF('Haq — Monthly P&L and cash'!P5="","",'Haq — Monthly P&L and cash'!P5>=15))="",FALSE,IF(ISERROR('Haq — Monthly P&L and cash'!P5>=15),'Haq — Monthly P&L and cash'!P5>=15,IF('Haq — Monthly P&L and cash'!P5="","",'Haq — Monthly P&L and cash'!P5>=15))),IF('Model inputs'!AJ47="","",'Model inputs'!AJ47),IF(IF(IF(ISERROR('Haq — Monthly P&L and cash'!P5>=12),'Haq — Monthly P&L and cash'!P5>=12,IF('Haq — Monthly P&L and cash'!P5="","",'Haq — Monthly P&L and cash'!P5>=12))="",FALSE,IF(ISERROR('Haq — Monthly P&L and cash'!P5>=12),'Haq — Monthly P&L and cash'!P5>=12,IF('Haq — Monthly P&L and cash'!P5="","",'Haq — Monthly P&L and cash'!P5>=12))),IF('Model inputs'!AJ46="","",'Model inputs'!AJ46),IF(IF(IF(ISERROR('Haq — Monthly P&L and cash'!P5>=9),'Haq — Monthly P&L and cash'!P5>=9,IF('Haq — Monthly P&L and cash'!P5="","",'Haq — Monthly P&L and cash'!P5>=9))="",FALSE,IF(ISERROR('Haq — Monthly P&L and cash'!P5>=9),'Haq — Monthly P&L and cash'!P5>=9,IF('Haq — Monthly P&L and cash'!P5="","",'Haq — Monthly P&L and cash'!P5>=9))),IF('Model inputs'!AJ53="","",'Model inputs'!AJ53),IF(IF(IF(ISERROR('Haq — Monthly P&L and cash'!P5>=6),'Haq — Monthly P&L and cash'!P5>=6,IF('Haq — Monthly P&L and cash'!P5="","",'Haq — Monthly P&L and cash'!P5>=6))="",FALSE,IF(ISERROR('Haq — Monthly P&L and cash'!P5>=6),'Haq — Monthly P&L and cash'!P5>=6,IF('Haq — Monthly P&L and cash'!P5="","",'Haq — Monthly P&L and cash'!P5>=6))),IF('Model inputs'!AJ52="","",'Model inputs'!AJ52),0)))))))) -> 4 | Q11: =IF(IF(IF(ISERROR('Haq — Monthly P&L and cash'!Q5>=24),'Haq — Monthly P&L and cash'!Q5>=24,IF('Haq — Monthly P&L and cash'!Q5="","",'Haq — Monthly P&L and cash'!Q5>=24))="",FALSE,IF(ISERROR('Haq — Monthly P&L and cash'!Q5>=24),'Haq — Monthly P&L and cash'!Q5>=24,IF('Haq — Monthly P&L and cash'!Q5="","",'Haq — Monthly P&L and cash'!Q5>=24))),IF('Model inputs'!AJ51="","",'Model inputs'!AJ51),IF(IF(IF(ISERROR('Haq — Monthly P&L and cash'!Q5>=23),'Haq — Monthly P&L and cash'!Q5>=23,IF('Haq — Monthly P&L and cash'!Q5="","",'Haq — Monthly P&L and cash'!Q5>=23))="",FALSE,IF(ISERROR('Haq — Monthly P&L and cash'!Q5>=23),'Haq — Monthly P&L and cash'!Q5>=23,IF('Haq — Monthly P&L and cash'!Q5="","",'Haq — Monthly P&L and cash'!Q5>=23))),IF('Model inputs'!AJ50="","",'Model inputs'!AJ50),IF(IF(IF(ISERROR('Haq — Monthly P&L and cash'!Q5>=21),'Haq — Monthly P&L and cash'!Q5>=21,IF('Haq — Monthly P&L and cash'!Q5="","",'Haq — Monthly P&L and cash'!Q5>=21))="",FALSE,IF(ISERROR('Haq — Monthly P&L and cash'!Q5>=21),'Haq — Monthly P&L and cash'!Q5>=21,IF('Haq — Monthly P&L and cash'!Q5="","",'Haq — Monthly P&L and cash'!Q5>=21))),IF('Model inputs'!AJ49="","",'Model inputs'!AJ49),IF(IF(IF(ISERROR('Haq — Monthly P&L and cash'!Q5>=18),'Haq — Monthly P&L and cash'!Q5>=18,IF('Haq — Monthly P&L and cash'!Q5="","",'Haq — Monthly P&L and cash'!Q5>=18))="",FALSE,IF(ISERROR('Haq — Monthly P&L and cash'!Q5>=18),'Haq — Monthly P&L and cash'!Q5>=18,IF('Haq — Monthly P&L and cash'!Q5="","",'Haq — Monthly P&L and cash'!Q5>=18))),IF('Model inputs'!AJ48="","",'Model inputs'!AJ48),IF(IF(IF(ISERROR('Haq — Monthly P&L and cash'!Q5>=15),'Haq — Monthly P&L and cash'!Q5>=15,IF('Haq — Monthly P&L and cash'!Q5="","",'Haq — Monthly P&L and cash'!Q5>=15))="",FALSE,IF(ISERROR('Haq — Monthly P&L and cash'!Q5>=15),'Haq — Monthly P&L and cash'!Q5>=15,IF('Haq — Monthly P&L and cash'!Q5="","",'Haq — Monthly P&L and cash'!Q5>=15))),IF('Model inputs'!AJ47="","",'Model inputs'!AJ47),IF(IF(IF(ISERROR('Haq — Monthly P&L and cash'!Q5>=12),'Haq — Monthly P&L and cash'!Q5>=12,IF('Haq — Monthly P&L and cash'!Q5="","",'Haq — Monthly P&L and cash'!Q5>=12))="",FALSE,IF(ISERROR('Haq — Monthly P&L and cash'!Q5>=12),'Haq — Monthly P&L and cash'!Q5>=12,IF('Haq — Monthly P&L and cash'!Q5="","",'Haq — Monthly P&L and cash'!Q5>=12))),IF('Model inputs'!AJ46="","",'Model inputs'!AJ46),IF(IF(IF(ISERROR('Haq — Monthly P&L and cash'!Q5>=9),'Haq — Monthly P&L and cash'!Q5>=9,IF('Haq — Monthly P&L and cash'!Q5="","",'Haq — Monthly P&L and cash'!Q5>=9))="",FALSE,IF(ISERROR('Haq — Monthly P&L and cash'!Q5>=9),'Haq — Monthly P&L and cash'!Q5>=9,IF('Haq — Monthly P&L and cash'!Q5="","",'Haq — Monthly P&L and cash'!Q5>=9))),IF('Model inputs'!AJ53="","",'Model inputs'!AJ53),IF(IF(IF(ISERROR('Haq — Monthly P&L and cash'!Q5>=6),'Haq — Monthly P&L and cash'!Q5>=6,IF('Haq — Monthly P&L and cash'!Q5="","",'Haq — Monthly P&L and cash'!Q5>=6))="",FALSE,IF(ISERROR('Haq — Monthly P&L and cash'!Q5>=6),'Haq — Monthly P&L and cash'!Q5>=6,IF('Haq — Monthly P&L and cash'!Q5="","",'Haq — Monthly P&L and cash'!Q5>=6))),IF('Model inputs'!AJ52="","",'Model inputs'!AJ52),0)))))))) -> 4 | R11: =IF(IF(IF(ISERROR('Haq — Monthly P&L and cash'!R5>=24),'Haq — Monthly P&L and cash'!R5>=24,IF('Haq — Monthly P&L and cash'!R5="","",'Haq — Monthly P&L and cash'!R5>=24))="",FALSE,IF(ISERROR('Haq — Monthly P&L and cash'!R5>=24),'Haq — Monthly P&L and cash'!R5>=24,IF('Haq — Monthly P&L and cash'!R5="","",'Haq — Monthly P&L and cash'!R5>=24))),IF('Model inputs'!AJ51="","",'Model inputs'!AJ51),IF(IF(IF(ISERROR('Haq — Monthly P&L and cash'!R5>=23),'Haq — Monthly P&L and cash'!R5>=23,IF('Haq — Monthly P&L and cash'!R5="","",'Haq — Monthly P&L and cash'!R5>=23))="",FALSE,IF(ISERROR('Haq — Monthly P&L and cash'!R5>=23),'Haq — Monthly P&L and cash'!R5>=23,IF('Haq — Monthly P&L and cash'!R5="","",'Haq — Monthly P&L and cash'!R5>=23))),IF('Model inputs'!AJ50="","",'Model inputs'!AJ50),IF(IF(IF(ISERROR('Haq — Monthly P&L and cash'!R5>=21),'Haq — Monthly P&L and cash'!R5>=21,IF('Haq — Monthly P&L and cash'!R5="","",'Haq — Monthly P&L and cash'!R5>=21))="",FALSE,IF(ISERROR('Haq — Monthly P&L and cash'!R5>=21),'Haq — Monthly P&L and cash'!R5>=21,IF('Haq — Monthly P&L and cash'!R5="","",'Haq — Monthly P&L and cash'!R5>=21))),IF('Model inputs'!AJ49="","",'Model inputs'!AJ49),IF(IF(IF(ISERROR('Haq — Monthly P&L and cash'!R5>=18),'Haq — Monthly P&L and cash'!R5>=18,IF('Haq — Monthly P&L and cash'!R5="","",'Haq — Monthly P&L and cash'!R5>=18))="",FALSE,IF(ISERROR('Haq — Monthly P&L and cash'!R5>=18),'Haq — Monthly P&L and cash'!R5>=18,IF('Haq — Monthly P&L and cash'!R5="","",'Haq — Monthly P&L and cash'!R5>=18))),IF('Model inputs'!AJ48="","",'Model inputs'!AJ48),IF(IF(IF(ISERROR('Haq — Monthly P&L and cash'!R5>=15),'Haq — Monthly P&L and cash'!R5>=15,IF('Haq — Monthly P&L and cash'!R5="","",'Haq — Monthly P&L and cash'!R5>=15))="",FALSE,IF(ISERROR('Haq — Monthly P&L and cash'!R5>=15),'Haq — Monthly P&L and cash'!R5>=15,IF('Haq — Monthly P&L and cash'!R5="","",'Haq — Monthly P&L and cash'!R5>=15))),IF('Model inputs'!AJ47="","",'Model inputs'!AJ47),IF(IF(IF(ISERROR('Haq — Monthly P&L and cash'!R5>=12),'Haq — Monthly P&L and cash'!R5>=12,IF('Haq — Monthly P&L and cash'!R5="","",'Haq — Monthly P&L and cash'!R5>=12))="",FALSE,IF(ISERROR('Haq — Monthly P&L and cash'!R5>=12),'Haq — Monthly P&L and cash'!R5>=12,IF('Haq — Monthly P&L and cash'!R5="","",'Haq — Monthly P&L and cash'!R5>=12))),IF('Model inputs'!AJ46="","",'Model inputs'!AJ46),IF(IF(IF(ISERROR('Haq — Monthly P&L and cash'!R5>=9),'Haq — Monthly P&L and cash'!R5>=9,IF('Haq — Monthly P&L and cash'!R5="","",'Haq — Monthly P&L and cash'!R5>=9))="",FALSE,IF(ISERROR('Haq — Monthly P&L and cash'!R5>=9),'Haq — Monthly P&L and cash'!R5>=9,IF('Haq — Monthly P&L and cash'!R5="","",'Haq — Monthly P&L and cash'!R5>=9))),IF('Model inputs'!AJ53="","",'Model inputs'!AJ53),IF(IF(IF(ISERROR('Haq — Monthly P&L and cash'!R5>=6),'Haq — Monthly P&L and cash'!R5>=6,IF('Haq — Monthly P&L and cash'!R5="","",'Haq — Monthly P&L and cash'!R5>=6))="",FALSE,IF(ISERROR('Haq — Monthly P&L and cash'!R5>=6),'Haq — Monthly P&L and cash'!R5>=6,IF('Haq — Monthly P&L and cash'!R5="","",'Haq — Monthly P&L and cash'!R5>=6))),IF('Model inputs'!AJ52="","",'Model inputs'!AJ52),0)))))))) -> 4 | S11: =IF(IF(IF(ISERROR('Haq — Monthly P&L and cash'!S5>=24),'Haq — Monthly P&L and cash'!S5>=24,IF('Haq — Monthly P&L and cash'!S5="","",'Haq — Monthly P&L and cash'!S5>=24))="",FALSE,IF(ISERROR('Haq — Monthly P&L and cash'!S5>=24),'Haq — Monthly P&L and cash'!S5>=24,IF('Haq — Monthly P&L and cash'!S5="","",'Haq — Monthly P&L and cash'!S5>=24))),IF('Model inputs'!AJ51="","",'Model inputs'!AJ51),IF(IF(IF(ISERROR('Haq — Monthly P&L and cash'!S5>=23),'Haq — Monthly P&L and cash'!S5>=23,IF('Haq — Monthly P&L and cash'!S5="","",'Haq — Monthly P&L and cash'!S5>=23))="",FALSE,IF(ISERROR('Haq — Monthly P&L and cash'!S5>=23),'Haq — Monthly P&L and cash'!S5>=23,IF('Haq — Monthly P&L and cash'!S5="","",'Haq — Monthly P&L and cash'!S5>=23))),IF('Model inputs'!AJ50="","",'Model inputs'!AJ50),IF(IF(IF(ISERROR('Haq — Monthly P&L and cash'!S5>=21),'Haq — Monthly P&L and cash'!S5>=21,IF('Haq — Monthly P&L and cash'!S5="","",'Haq — Monthly P&L and cash'!S5>=21))="",FALSE,IF(ISERROR('Haq — Monthly P&L and cash'!S5>=21),'Haq — Monthly P&L and cash'!S5>=21,IF('Haq — Monthly P&L and cash'!S5="","",'Haq — Monthly P&L and cash'!S5>=21))),IF('Model inputs'!AJ49="","",'Model inputs'!AJ49),IF(IF(IF(ISERROR('Haq — Monthly P&L and cash'!S5>=18),'Haq — Monthly P&L and cash'!S5>=18,IF('Haq — Monthly P&L and cash'!S5="","",'Haq — Monthly P&L and cash'!S5>=18))="",FALSE,IF(ISERROR('Haq — Monthly P&L and cash'!S5>=18),'Haq — Monthly P&L and cash'!S5>=18,IF('Haq — Monthly P&L and cash'!S5="","",'Haq — Monthly P&L and cash'!S5>=18))),IF('Model inputs'!AJ48="","",'Model inputs'!AJ48),IF(IF(IF(ISERROR('Haq — Monthly P&L and cash'!S5>=15),'Haq — Monthly P&L and cash'!S5>=15,IF('Haq — Monthly P&L and cash'!S5="","",'Haq — Monthly P&L and cash'!S5>=15))="",FALSE,IF(ISERROR('Haq — Monthly P&L and cash'!S5>=15),'Haq — Monthly P&L and cash'!S5>=15,IF('Haq — Monthly P&L and cash'!S5="","",'Haq — Monthly P&L and cash'!S5>=15))),IF('Model inputs'!AJ47="","",'Model inputs'!AJ47),IF(IF(IF(ISERROR('Haq — Monthly P&L and cash'!S5>=12),'Haq — Monthly P&L and cash'!S5>=12,IF('Haq — Monthly P&L and cash'!S5="","",'Haq — Monthly P&L and cash'!S5>=12))="",FALSE,IF(ISERROR('Haq — Monthly P&L and cash'!S5>=12),'Haq — Monthly P&L and cash'!S5>=12,IF('Haq — Monthly P&L and cash'!S5="","",'Haq — Monthly P&L and cash'!S5>=12))),IF('Model inputs'!AJ46="","",'Model inputs'!AJ46),IF(IF(IF(ISERROR('Haq — Monthly P&L and cash'!S5>=9),'Haq — Monthly P&L and cash'!S5>=9,IF('Haq — Monthly P&L and cash'!S5="","",'Haq — Monthly P&L and cash'!S5>=9))="",FALSE,IF(ISERROR('Haq — Monthly P&L and cash'!S5>=9),'Haq — Monthly P&L and cash'!S5>=9,IF('Haq — Monthly P&L and cash'!S5="","",'Haq — Monthly P&L and cash'!S5>=9))),IF('Model inputs'!AJ53="","",'Model inputs'!AJ53),IF(IF(IF(ISERROR('Haq — Monthly P&L and cash'!S5>=6),'Haq — Monthly P&L and cash'!S5>=6,IF('Haq — Monthly P&L and cash'!S5="","",'Haq — Monthly P&L and cash'!S5>=6))="",FALSE,IF(ISERROR('Haq — Monthly P&L and cash'!S5>=6),'Haq — Monthly P&L and cash'!S5>=6,IF('Haq — Monthly P&L and cash'!S5="","",'Haq — Monthly P&L and cash'!S5>=6))),IF('Model inputs'!AJ52="","",'Model inputs'!AJ52),0)))))))) -> 5 | T11: =IF(IF(IF(ISERROR('Haq — Monthly P&L and cash'!T5>=24),'Haq — Monthly P&L and cash'!T5>=24,IF('Haq — Monthly P&L and cash'!T5="","",'Haq — Monthly P&L and cash'!T5>=24))="",FALSE,IF(ISERROR('Haq — Monthly P&L and cash'!T5>=24),'Haq — Monthly P&L and cash'!T5>=24,IF('Haq — Monthly P&L and cash'!T5="","",'Haq — Monthly P&L and cash'!T5>=24))),IF('Model inputs'!AJ51="","",'Model inputs'!AJ51),IF(IF(IF(ISERROR('Haq — Monthly P&L and cash'!T5>=23),'Haq — Monthly P&L and cash'!T5>=23,IF('Haq — Monthly P&L and cash'!T5="","",'Haq — Monthly P&L and cash'!T5>=23))="",FALSE,IF(ISERROR('Haq — Monthly P&L and cash'!T5>=23),'Haq — Monthly P&L and cash'!T5>=23,IF('Haq — Monthly P&L and cash'!T5="","",'Haq — Monthly P&L and cash'!T5>=23))),IF('Model inputs'!AJ50="","",'Model inputs'!AJ50),IF(IF(IF(ISERROR('Haq — Monthly P&L and cash'!T5>=21),'Haq — Monthly P&L and cash'!T5>=21,IF('Haq — Monthly P&L and cash'!T5="","",'Haq — Monthly P&L and cash'!T5>=21))="",FALSE,IF(ISERROR('Haq — Monthly P&L and cash'!T5>=21),'Haq — Monthly P&L and cash'!T5>=21,IF('Haq — Monthly P&L and cash'!T5="","",'Haq — Monthly P&L and cash'!T5>=21))),IF('Model inputs'!AJ49="","",'Model inputs'!AJ49),IF(IF(IF(ISERROR('Haq — Monthly P&L and cash'!T5>=18),'Haq — Monthly P&L and cash'!T5>=18,IF('Haq — Monthly P&L and cash'!T5="","",'Haq — Monthly P&L and cash'!T5>=18))="",FALSE,IF(ISERROR('Haq — Monthly P&L and cash'!T5>=18),'Haq — Monthly P&L and cash'!T5>=18,IF('Haq — Monthly P&L and cash'!T5="","",'Haq — Monthly P&L and cash'!T5>=18))),IF('Model inputs'!AJ48="","",'Model inputs'!AJ48),IF(IF(IF(ISERROR('Haq — Monthly P&L and cash'!T5>=15),'Haq — Monthly P&L and cash'!T5>=15,IF('Haq — Monthly P&L and cash'!T5="","",'Haq — Monthly P&L and cash'!T5>=15))="",FALSE,IF(ISERROR('Haq — Monthly P&L and cash'!T5>=15),'Haq — Monthly P&L and cash'!T5>=15,IF('Haq — Monthly P&L and cash'!T5="","",'Haq — Monthly P&L and cash'!T5>=15))),IF('Model inputs'!AJ47="","",'Model inputs'!AJ47),IF(IF(IF(ISERROR('Haq — Monthly P&L and cash'!T5>=12),'Haq — Monthly P&L and cash'!T5>=12,IF('Haq — Monthly P&L and cash'!T5="","",'Haq — Monthly P&L and cash'!T5>=12))="",FALSE,IF(ISERROR('Haq — Monthly P&L and cash'!T5>=12),'Haq — Monthly P&L and cash'!T5>=12,IF('Haq — Monthly P&L and cash'!T5="","",'Haq — Monthly P&L and cash'!T5>=12))),IF('Model inputs'!AJ46="","",'Model inputs'!AJ46),IF(IF(IF(ISERROR('Haq — Monthly P&L and cash'!T5>=9),'Haq — Monthly P&L and cash'!T5>=9,IF('Haq — Monthly P&L and cash'!T5="","",'Haq — Monthly P&L and cash'!T5>=9))="",FALSE,IF(ISERROR('Haq — Monthly P&L and cash'!T5>=9),'Haq — Monthly P&L and cash'!T5>=9,IF('Haq — Monthly P&L and cash'!T5="","",'Haq — Monthly P&L and cash'!T5>=9))),IF('Model inputs'!AJ53="","",'Model inputs'!AJ53),IF(IF(IF(ISERROR('Haq — Monthly P&L and cash'!T5>=6),'Haq — Monthly P&L and cash'!T5>=6,IF('Haq — Monthly P&L and cash'!T5="","",'Haq — Monthly P&L and cash'!T5>=6))="",FALSE,IF(ISERROR('Haq — Monthly P&L and cash'!T5>=6),'Haq — Monthly P&L and cash'!T5>=6,IF('Haq — Monthly P&L and cash'!T5="","",'Haq — Monthly P&L and cash'!T5>=6))),IF('Model inputs'!AJ52="","",'Model inputs'!AJ52),0)))))))) -> 5 | U11: =IF(IF(IF(ISERROR('Haq — Monthly P&L and cash'!U5>=24),'Haq — Monthly P&L and cash'!U5>=24,IF('Haq — Monthly P&L and cash'!U5="","",'Haq — Monthly P&L and cash'!U5>=24))="",FALSE,IF(ISERROR('Haq — Monthly P&L and cash'!U5>=24),'Haq — Monthly P&L and cash'!U5>=24,IF('Haq — Monthly P&L and cash'!U5="","",'Haq — Monthly P&L and cash'!U5>=24))),IF('Model inputs'!AJ51="","",'Model inputs'!AJ51),IF(IF(IF(ISERROR('Haq — Monthly P&L and cash'!U5>=23),'Haq — Monthly P&L and cash'!U5>=23,IF('Haq — Monthly P&L and cash'!U5="","",'Haq — Monthly P&L and cash'!U5>=23))="",FALSE,IF(ISERROR('Haq — Monthly P&L and cash'!U5>=23),'Haq — Monthly P&L and cash'!U5>=23,IF('Haq — Monthly P&L and cash'!U5="","",'Haq — Monthly P&L and cash'!U5>=23))),IF('Model inputs'!AJ50="","",'Model inputs'!AJ50),IF(IF(IF(ISERROR('Haq — Monthly P&L and cash'!U5>=21),'Haq — Monthly P&L and cash'!U5>=21,IF('Haq — Monthly P&L and cash'!U5="","",'Haq — Monthly P&L and cash'!U5>=21))="",FALSE,IF(ISERROR('Haq — Monthly P&L and cash'!U5>=21),'Haq — Monthly P&L and cash'!U5>=21,IF('Haq — Monthly P&L and cash'!U5="","",'Haq — Monthly P&L and cash'!U5>=21))),IF('Model inputs'!AJ49="","",'Model inputs'!AJ49),IF(IF(IF(ISERROR('Haq — Monthly P&L and cash'!U5>=18),'Haq — Monthly P&L and cash'!U5>=18,IF('Haq — Monthly P&L and cash'!U5="","",'Haq — Monthly P&L and cash'!U5>=18))="",FALSE,IF(ISERROR('Haq — Monthly P&L and cash'!U5>=18),'Haq — Monthly P&L and cash'!U5>=18,IF('Haq — Monthly P&L and cash'!U5="","",'Haq — Monthly P&L and cash'!U5>=18))),IF('Model inputs'!AJ48="","",'Model inputs'!AJ48),IF(IF(IF(ISERROR('Haq — Monthly P&L and cash'!U5>=15),'Haq — Monthly P&L and cash'!U5>=15,IF('Haq — Monthly P&L and cash'!U5="","",'Haq — Monthly P&L and cash'!U5>=15))="",FALSE,IF(ISERROR('Haq — Monthly P&L and cash'!U5>=15),'Haq — Monthly P&L and cash'!U5>=15,IF('Haq — Monthly P&L and cash'!U5="","",'Haq — Monthly P&L and cash'!U5>=15))),IF('Model inputs'!AJ47="","",'Model inputs'!AJ47),IF(IF(IF(ISERROR('Haq — Monthly P&L and cash'!U5>=12),'Haq — Monthly P&L and cash'!U5>=12,IF('Haq — Monthly P&L and cash'!U5="","",'Haq — Monthly P&L and cash'!U5>=12))="",FALSE,IF(ISERROR('Haq — Monthly P&L and cash'!U5>=12),'Haq — Monthly P&L and cash'!U5>=12,IF('Haq — Monthly P&L and cash'!U5="","",'Haq — Monthly P&L and cash'!U5>=12))),IF('Model inputs'!AJ46="","",'Model inputs'!AJ46),IF(IF(IF(ISERROR('Haq — Monthly P&L and cash'!U5>=9),'Haq — Monthly P&L and cash'!U5>=9,IF('Haq — Monthly P&L and cash'!U5="","",'Haq — Monthly P&L and cash'!U5>=9))="",FALSE,IF(ISERROR('Haq — Monthly P&L and cash'!U5>=9),'Haq — Monthly P&L and cash'!U5>=9,IF('Haq — Monthly P&L and cash'!U5="","",'Haq — Monthly P&L and cash'!U5>=9))),IF('Model inputs'!AJ53="","",'Model inputs'!AJ53),IF(IF(IF(ISERROR('Haq — Monthly P&L and cash'!U5>=6),'Haq — Monthly P&L and cash'!U5>=6,IF('Haq — Monthly P&L and cash'!U5="","",'Haq — Monthly P&L and cash'!U5>=6))="",FALSE,IF(ISERROR('Haq — Monthly P&L and cash'!U5>=6),'Haq — Monthly P&L and cash'!U5>=6,IF('Haq — Monthly P&L and cash'!U5="","",'Haq — Monthly P&L and cash'!U5>=6))),IF('Model inputs'!AJ52="","",'Model inputs'!AJ52),0)))))))) -> 5 | V11: =IF(IF(IF(ISERROR('Haq — Monthly P&L and cash'!V5>=24),'Haq — Monthly P&L and cash'!V5>=24,IF('Haq — Monthly P&L and cash'!V5="","",'Haq — Monthly P&L and cash'!V5>=24))="",FALSE,IF(ISERROR('Haq — Monthly P&L and cash'!V5>=24),'Haq — Monthly P&L and cash'!V5>=24,IF('Haq — Monthly P&L and cash'!V5="","",'Haq — Monthly P&L and cash'!V5>=24))),IF('Model inputs'!AJ51="","",'Model inputs'!AJ51),IF(IF(IF(ISERROR('Haq — Monthly P&L and cash'!V5>=23),'Haq — Monthly P&L and cash'!V5>=23,IF('Haq — Monthly P&L and cash'!V5="","",'Haq — Monthly P&L and cash'!V5>=23))="",FALSE,IF(ISERROR('Haq — Monthly P&L and cash'!V5>=23),'Haq — Monthly P&L and cash'!V5>=23,IF('Haq — Monthly P&L and cash'!V5="","",'Haq — Monthly P&L and cash'!V5>=23))),IF('Model inputs'!AJ50="","",'Model inputs'!AJ50),IF(IF(IF(ISERROR('Haq — Monthly P&L and cash'!V5>=21),'Haq — Monthly P&L and cash'!V5>=21,IF('Haq — Monthly P&L and cash'!V5="","",'Haq — Monthly P&L and cash'!V5>=21))="",FALSE,IF(ISERROR('Haq — Monthly P&L and cash'!V5>=21),'Haq — Monthly P&L and cash'!V5>=21,IF('Haq — Monthly P&L and cash'!V5="","",'Haq — Monthly P&L and cash'!V5>=21))),IF('Model inputs'!AJ49="","",'Model inputs'!AJ49),IF(IF(IF(ISERROR('Haq — Monthly P&L and cash'!V5>=18),'Haq — Monthly P&L and cash'!V5>=18,IF('Haq — Monthly P&L and cash'!V5="","",'Haq — Monthly P&L and cash'!V5>=18))="",FALSE,IF(ISERROR('Haq — Monthly P&L and cash'!V5>=18),'Haq — Monthly P&L and cash'!V5>=18,IF('Haq — Monthly P&L and cash'!V5="","",'Haq — Monthly P&L and cash'!V5>=18))),IF('Model inputs'!AJ48="","",'Model inputs'!AJ48),IF(IF(IF(ISERROR('Haq — Monthly P&L and cash'!V5>=15),'Haq — Monthly P&L and cash'!V5>=15,IF('Haq — Monthly P&L and cash'!V5="","",'Haq — Monthly P&L and cash'!V5>=15))="",FALSE,IF(ISERROR('Haq — Monthly P&L and cash'!V5>=15),'Haq — Monthly P&L and cash'!V5>=15,IF('Haq — Monthly P&L and cash'!V5="","",'Haq — Monthly P&L and cash'!V5>=15))),IF('Model inputs'!AJ47="","",'Model inputs'!AJ47),IF(IF(IF(ISERROR('Haq — Monthly P&L and cash'!V5>=12),'Haq — Monthly P&L and cash'!V5>=12,IF('Haq — Monthly P&L and cash'!V5="","",'Haq — Monthly P&L and cash'!V5>=12))="",FALSE,IF(ISERROR('Haq — Monthly P&L and cash'!V5>=12),'Haq — Monthly P&L and cash'!V5>=12,IF('Haq — Monthly P&L and cash'!V5="","",'Haq — Monthly P&L and cash'!V5>=12))),IF('Model inputs'!AJ46="","",'Model inputs'!AJ46),IF(IF(IF(ISERROR('Haq — Monthly P&L and cash'!V5>=9),'Haq — Monthly P&L and cash'!V5>=9,IF('Haq — Monthly P&L and cash'!V5="","",'Haq — Monthly P&L and cash'!V5>=9))="",FALSE,IF(ISERROR('Haq — Monthly P&L and cash'!V5>=9),'Haq — Monthly P&L and cash'!V5>=9,IF('Haq — Monthly P&L and cash'!V5="","",'Haq — Monthly P&L and cash'!V5>=9))),IF('Model inputs'!AJ53="","",'Model inputs'!AJ53),IF(IF(IF(ISERROR('Haq — Monthly P&L and cash'!V5>=6),'Haq — Monthly P&L and cash'!V5>=6,IF('Haq — Monthly P&L and cash'!V5="","",'Haq — Monthly P&L and cash'!V5>=6))="",FALSE,IF(ISERROR('Haq — Monthly P&L and cash'!V5>=6),'Haq — Monthly P&L and cash'!V5>=6,IF('Haq — Monthly P&L and cash'!V5="","",'Haq — Monthly P&L and cash'!V5>=6))),IF('Model inputs'!AJ52="","",'Model inputs'!AJ52),0)))))))) -> 6 | W11: =IF(IF(IF(ISERROR('Haq — Monthly P&L and cash'!W5>=24),'Haq — Monthly P&L and cash'!W5>=24,IF('Haq — Monthly P&L and cash'!W5="","",'Haq — Monthly P&L and cash'!W5>=24))="",FALSE,IF(ISERROR('Haq — Monthly P&L and cash'!W5>=24),'Haq — Monthly P&L and cash'!W5>=24,IF('Haq — Monthly P&L and cash'!W5="","",'Haq — Monthly P&L and cash'!W5>=24))),IF('Model inputs'!AJ51="","",'Model inputs'!AJ51),IF(IF(IF(ISERROR('Haq — Monthly P&L and cash'!W5>=23),'Haq — Monthly P&L and cash'!W5>=23,IF('Haq — Monthly P&L and cash'!W5="","",'Haq — Monthly P&L and cash'!W5>=23))="",FALSE,IF(ISERROR('Haq — Monthly P&L and cash'!W5>=23),'Haq — Monthly P&L and cash'!W5>=23,IF('Haq — Monthly P&L and cash'!W5="","",'Haq — Monthly P&L and cash'!W5>=23))),IF('Model inputs'!AJ50="","",'Model inputs'!AJ50),IF(IF(IF(ISERROR('Haq — Monthly P&L and cash'!W5>=21),'Haq — Monthly P&L and cash'!W5>=21,IF('Haq — Monthly P&L and cash'!W5="","",'Haq — Monthly P&L and cash'!W5>=21))="",FALSE,IF(ISERROR('Haq — Monthly P&L and cash'!W5>=21),'Haq — Monthly P&L and cash'!W5>=21,IF('Haq — Monthly P&L and cash'!W5="","",'Haq — Monthly P&L and cash'!W5>=21))),IF('Model inputs'!AJ49="","",'Model inputs'!AJ49),IF(IF(IF(ISERROR('Haq — Monthly P&L and cash'!W5>=18),'Haq — Monthly P&L and cash'!W5>=18,IF('Haq — Monthly P&L and cash'!W5="","",'Haq — Monthly P&L and cash'!W5>=18))="",FALSE,IF(ISERROR('Haq — Monthly P&L and cash'!W5>=18),'Haq — Monthly P&L and cash'!W5>=18,IF('Haq — Monthly P&L and cash'!W5="","",'Haq — Monthly P&L and cash'!W5>=18))),IF('Model inputs'!AJ48="","",'Model inputs'!AJ48),IF(IF(IF(ISERROR('Haq — Monthly P&L and cash'!W5>=15),'Haq — Monthly P&L and cash'!W5>=15,IF('Haq — Monthly P&L and cash'!W5="","",'Haq — Monthly P&L and cash'!W5>=15))="",FALSE,IF(ISERROR('Haq — Monthly P&L and cash'!W5>=15),'Haq — Monthly P&L and cash'!W5>=15,IF('Haq — Monthly P&L and cash'!W5="","",'Haq — Monthly P&L and cash'!W5>=15))),IF('Model inputs'!AJ47="","",'Model inputs'!AJ47),IF(IF(IF(ISERROR('Haq — Monthly P&L and cash'!W5>=12),'Haq — Monthly P&L and cash'!W5>=12,IF('Haq — Monthly P&L and cash'!W5="","",'Haq — Monthly P&L and cash'!W5>=12))="",FALSE,IF(ISERROR('Haq — Monthly P&L and cash'!W5>=12),'Haq — Monthly P&L and cash'!W5>=12,IF('Haq — Monthly P&L and cash'!W5="","",'Haq — Monthly P&L and cash'!W5>=12))),IF('Model inputs'!AJ46="","",'Model inputs'!AJ46),IF(IF(IF(ISERROR('Haq — Monthly P&L and cash'!W5>=9),'Haq — Monthly P&L and cash'!W5>=9,IF('Haq — Monthly P&L and cash'!W5="","",'Haq — Monthly P&L and cash'!W5>=9))="",FALSE,IF(ISERROR('Haq — Monthly P&L and cash'!W5>=9),'Haq — Monthly P&L and cash'!W5>=9,IF('Haq — Monthly P&L and cash'!W5="","",'Haq — Monthly P&L and cash'!W5>=9))),IF('Model inputs'!AJ53="","",'Model inputs'!AJ53),IF(IF(IF(ISERROR('Haq — Monthly P&L and cash'!W5>=6),'Haq — Monthly P&L and cash'!W5>=6,IF('Haq — Monthly P&L and cash'!W5="","",'Haq — Monthly P&L and cash'!W5>=6))="",FALSE,IF(ISERROR('Haq — Monthly P&L and cash'!W5>=6),'Haq — Monthly P&L and cash'!W5>=6,IF('Haq — Monthly P&L and cash'!W5="","",'Haq — Monthly P&L and cash'!W5>=6))),IF('Model inputs'!AJ52="","",'Model inputs'!AJ52),0)))))))) -> 6 | X11: =IF(IF(IF(ISERROR('Haq — Monthly P&L and cash'!X5>=24),'Haq — Monthly P&L and cash'!X5>=24,IF('Haq — Monthly P&L and cash'!X5="","",'Haq — Monthly P&L and cash'!X5>=24))="",FALSE,IF(ISERROR('Haq — Monthly P&L and cash'!X5>=24),'Haq — Monthly P&L and cash'!X5>=24,IF('Haq — Monthly P&L and cash'!X5="","",'Haq — Monthly P&L and cash'!X5>=24))),IF('Model inputs'!AJ51="","",'Model inputs'!AJ51),IF(IF(IF(ISERROR('Haq — Monthly P&L and cash'!X5>=23),'Haq — Monthly P&L and cash'!X5>=23,IF('Haq — Monthly P&L and cash'!X5="","",'Haq — Monthly P&L and cash'!X5>=23))="",FALSE,IF(ISERROR('Haq — Monthly P&L and cash'!X5>=23),'Haq — Monthly P&L and cash'!X5>=23,IF('Haq — Monthly P&L and cash'!X5="","",'Haq — Monthly P&L and cash'!X5>=23))),IF('Model inputs'!AJ50="","",'Model inputs'!AJ50),IF(IF(IF(ISERROR('Haq — Monthly P&L and cash'!X5>=21),'Haq — Monthly P&L and cash'!X5>=21,IF('Haq — Monthly P&L and cash'!X5="","",'Haq — Monthly P&L and cash'!X5>=21))="",FALSE,IF(ISERROR('Haq — Monthly P&L and cash'!X5>=21),'Haq — Monthly P&L and cash'!X5>=21,IF('Haq — Monthly P&L and cash'!X5="","",'Haq — Monthly P&L and cash'!X5>=21))),IF('Model inputs'!AJ49="","",'Model inputs'!AJ49),IF(IF(IF(ISERROR('Haq — Monthly P&L and cash'!X5>=18),'Haq — Monthly P&L and cash'!X5>=18,IF('Haq — Monthly P&L and cash'!X5="","",'Haq — Monthly P&L and cash'!X5>=18))="",FALSE,IF(ISERROR('Haq — Monthly P&L and cash'!X5>=18),'Haq — Monthly P&L and cash'!X5>=18,IF('Haq — Monthly P&L and cash'!X5="","",'Haq — Monthly P&L and cash'!X5>=18))),IF('Model inputs'!AJ48="","",'Model inputs'!AJ48),IF(IF(IF(ISERROR('Haq — Monthly P&L and cash'!X5>=15),'Haq — Monthly P&L and cash'!X5>=15,IF('Haq — Monthly P&L and cash'!X5="","",'Haq — Monthly P&L and cash'!X5>=15))="",FALSE,IF(ISERROR('Haq — Monthly P&L and cash'!X5>=15),'Haq — Monthly P&L and cash'!X5>=15,IF('Haq — Monthly P&L and cash'!X5="","",'Haq — Monthly P&L and cash'!X5>=15))),IF('Model inputs'!AJ47="","",'Model inputs'!AJ47),IF(IF(IF(ISERROR('Haq — Monthly P&L and cash'!X5>=12),'Haq — Monthly P&L and cash'!X5>=12,IF('Haq — Monthly P&L and cash'!X5="","",'Haq — Monthly P&L and cash'!X5>=12))="",FALSE,IF(ISERROR('Haq — Monthly P&L and cash'!X5>=12),'Haq — Monthly P&L and cash'!X5>=12,IF('Haq — Monthly P&L and cash'!X5="","",'Haq — Monthly P&L and cash'!X5>=12))),IF('Model inputs'!AJ46="","",'Model inputs'!AJ46),IF(IF(IF(ISERROR('Haq — Monthly P&L and cash'!X5>=9),'Haq — Monthly P&L and cash'!X5>=9,IF('Haq — Monthly P&L and cash'!X5="","",'Haq — Monthly P&L and cash'!X5>=9))="",FALSE,IF(ISERROR('Haq — Monthly P&L and cash'!X5>=9),'Haq — Monthly P&L and cash'!X5>=9,IF('Haq — Monthly P&L and cash'!X5="","",'Haq — Monthly P&L and cash'!X5>=9))),IF('Model inputs'!AJ53="","",'Model inputs'!AJ53),IF(IF(IF(ISERROR('Haq — Monthly P&L and cash'!X5>=6),'Haq — Monthly P&L and cash'!X5>=6,IF('Haq — Monthly P&L and cash'!X5="","",'Haq — Monthly P&L and cash'!X5>=6))="",FALSE,IF(ISERROR('Haq — Monthly P&L and cash'!X5>=6),'Haq — Monthly P&L and cash'!X5>=6,IF('Haq — Monthly P&L and cash'!X5="","",'Haq — Monthly P&L and cash'!X5>=6))),IF('Model inputs'!AJ52="","",'Model inputs'!AJ52),0)))))))) -> 7 | Y11: =IF(IF(IF(ISERROR('Haq — Monthly P&L and cash'!Y5>=24),'Haq — Monthly P&L and cash'!Y5>=24,IF('Haq — Monthly P&L and cash'!Y5="","",'Haq — Monthly P&L and cash'!Y5>=24))="",FALSE,IF(ISERROR('Haq — Monthly P&L and cash'!Y5>=24),'Haq — Monthly P&L and cash'!Y5>=24,IF('Haq — Monthly P&L and cash'!Y5="","",'Haq — Monthly P&L and cash'!Y5>=24))),IF('Model inputs'!AJ51="","",'Model inputs'!AJ51),IF(IF(IF(ISERROR('Haq — Monthly P&L and cash'!Y5>=23),'Haq — Monthly P&L and cash'!Y5>=23,IF('Haq — Monthly P&L and cash'!Y5="","",'Haq — Monthly P&L and cash'!Y5>=23))="",FALSE,IF(ISERROR('Haq — Monthly P&L and cash'!Y5>=23),'Haq — Monthly P&L and cash'!Y5>=23,IF('Haq — Monthly P&L and cash'!Y5="","",'Haq — Monthly P&L and cash'!Y5>=23))),IF('Model inputs'!AJ50="","",'Model inputs'!AJ50),IF(IF(IF(ISERROR('Haq — Monthly P&L and cash'!Y5>=21),'Haq — Monthly P&L and cash'!Y5>=21,IF('Haq — Monthly P&L and cash'!Y5="","",'Haq — Monthly P&L and cash'!Y5>=21))="",FALSE,IF(ISERROR('Haq — Monthly P&L and cash'!Y5>=21),'Haq — Monthly P&L and cash'!Y5>=21,IF('Haq — Monthly P&L and cash'!Y5="","",'Haq — Monthly P&L and cash'!Y5>=21))),IF('Model inputs'!AJ49="","",'Model inputs'!AJ49),IF(IF(IF(ISERROR('Haq — Monthly P&L and cash'!Y5>=18),'Haq — Monthly P&L and cash'!Y5>=18,IF('Haq — Monthly P&L and cash'!Y5="","",'Haq — Monthly P&L and cash'!Y5>=18))="",FALSE,IF(ISERROR('Haq — Monthly P&L and cash'!Y5>=18),'Haq — Monthly P&L and cash'!Y5>=18,IF('Haq — Monthly P&L and cash'!Y5="","",'Haq — Monthly P&L and cash'!Y5>=18))),IF('Model inputs'!AJ48="","",'Model inputs'!AJ48),IF(IF(IF(ISERROR('Haq — Monthly P&L and cash'!Y5>=15),'Haq — Monthly P&L and cash'!Y5>=15,IF('Haq — Monthly P&L and cash'!Y5="","",'Haq — Monthly P&L and cash'!Y5>=15))="",FALSE,IF(ISERROR('Haq — Monthly P&L and cash'!Y5>=15),'Haq — Monthly P&L and cash'!Y5>=15,IF('Haq — Monthly P&L and cash'!Y5="","",'Haq — Monthly P&L and cash'!Y5>=15))),IF('Model inputs'!AJ47="","",'Model inputs'!AJ47),IF(IF(IF(ISERROR('Haq — Monthly P&L and cash'!Y5>=12),'Haq — Monthly P&L and cash'!Y5>=12,IF('Haq — Monthly P&L and cash'!Y5="","",'Haq — Monthly P&L and cash'!Y5>=12))="",FALSE,IF(ISERROR('Haq — Monthly P&L and cash'!Y5>=12),'Haq — Monthly P&L and cash'!Y5>=12,IF('Haq — Monthly P&L and cash'!Y5="","",'Haq — Monthly P&L and cash'!Y5>=12))),IF('Model inputs'!AJ46="","",'Model inputs'!AJ46),IF(IF(IF(ISERROR('Haq — Monthly P&L and cash'!Y5>=9),'Haq — Monthly P&L and cash'!Y5>=9,IF('Haq — Monthly P&L and cash'!Y5="","",'Haq — Monthly P&L and cash'!Y5>=9))="",FALSE,IF(ISERROR('Haq — Monthly P&L and cash'!Y5>=9),'Haq — Monthly P&L and cash'!Y5>=9,IF('Haq — Monthly P&L and cash'!Y5="","",'Haq — Monthly P&L and cash'!Y5>=9))),IF('Model inputs'!AJ53="","",'Model inputs'!AJ53),IF(IF(IF(ISERROR('Haq — Monthly P&L and cash'!Y5>=6),'Haq — Monthly P&L and cash'!Y5>=6,IF('Haq — Monthly P&L and cash'!Y5="","",'Haq — Monthly P&L and cash'!Y5>=6))="",FALSE,IF(ISERROR('Haq — Monthly P&L and cash'!Y5>=6),'Haq — Monthly P&L and cash'!Y5>=6,IF('Haq — Monthly P&L and cash'!Y5="","",'Haq — Monthly P&L and cash'!Y5>=6))),IF('Model inputs'!AJ52="","",'Model inputs'!AJ52),0)))))))) -> 8
A12: Haq CSR launches | B12: =MAX('Haq — Monthly P&L and cash'!B11-'Model inputs'!C17,0) -> 0 | C12: =MAX('Haq — Monthly P&L and cash'!C11-'Haq — Monthly P&L and cash'!B11,0) -> 0 | D12: =MAX('Haq — Monthly P&L and cash'!D11-'Haq — Monthly P&L and cash'!C11,0) -> 0 | E12: =MAX('Haq — Monthly P&L and cash'!E11-'Haq — Monthly P&L and cash'!D11,0) -> 0 | F12: =MAX('Haq — Monthly P&L and cash'!F11-'Haq — Monthly P&L and cash'!E11,0) -> 0 | G12: =MAX('Haq — Monthly P&L and cash'!G11-'Haq — Monthly P&L and cash'!F11,0) -> 1 | H12: =MAX('Haq — Monthly P&L and cash'!H11-'Haq — Monthly P&L and cash'!G11,0) -> 0 | I12: =MAX('Haq — Monthly P&L and cash'!I11-'Haq — Monthly P&L and cash'!H11,0) -> 0 | J12: =MAX('Haq — Monthly P&L and cash'!J11-'Haq — Monthly P&L and cash'!I11,0) -> 1 | ... Y12: =MAX('Haq — Monthly P&L and cash'!Y11-'Haq — Monthly P&L and cash'!X11,0) -> 1
A13: Haq CSR checks | B13: ='Haq — Monthly P&L and cash'!B11*'Model inputs'!AJ45/12 -> 0 | C13: ='Haq — Monthly P&L and cash'!C11*'Model inputs'!AJ45/12 -> 0 | D13: ='Haq — Monthly P&L and cash'!D11*'Model inputs'!AJ45/12 -> 0 | E13: ='Haq — Monthly P&L and cash'!E11*'Model inputs'!AJ45/12 -> 0 | F13: ='Haq — Monthly P&L and cash'!F11*'Model inputs'!AJ45/12 -> 0 | G13: ='Haq — Monthly P&L and cash'!G11*'Model inputs'!AJ45/12 -> 2083.3333 | H13: ='Haq — Monthly P&L and cash'!H11*'Model inputs'!AJ45/12 -> 2083.3333 | I13: ='Haq — Monthly P&L and cash'!I11*'Model inputs'!AJ45/12 -> 2083.3333 | J13: ='Haq — Monthly P&L and cash'!J11*'Model inputs'!AJ45/12 -> 4166.6667 | K13: ='Haq — Monthly P&L and cash'!K11*'Model inputs'!AJ45/12 -> 4166.6667 | L13: ='Haq — Monthly P&L and cash'!L11*'Model inputs'!AJ45/12 -> 4166.6667 | M13: ='Haq — Monthly P&L and cash'!M11*'Model inputs'!AJ45/12 -> 6250 | N13: ='Haq — Monthly P&L and cash'!N11*'Model inputs'!AJ45/12 -> 6250 | O13: ='Haq — Monthly P&L and cash'!O11*'Model inputs'!AJ45/12 -> 6250 | P13: ='Haq — Monthly P&L and cash'!P11*'Model inputs'!AJ45/12 -> 8333.3333 | Q13: ='Haq — Monthly P&L and cash'!Q11*'Model inputs'!AJ45/12 -> 8333.3333 | R13: ='Haq — Monthly P&L and cash'!R11*'Model inputs'!AJ45/12 -> 8333.3333 | S13: ='Haq — Monthly P&L and cash'!S11*'Model inputs'!AJ45/12 -> 10416.667 | T13: ='Haq — Monthly P&L and cash'!T11*'Model inputs'!AJ45/12 -> 10416.667 | U13: ='Haq — Monthly P&L and cash'!U11*'Model inputs'!AJ45/12 -> 10416.667 | V13: ='Haq — Monthly P&L and cash'!V11*'Model inputs'!AJ45/12 -> 12500 | W13: ='Haq — Monthly P&L and cash'!W11*'Model inputs'!AJ45/12 -> 12500 | X13: ='Haq — Monthly P&L and cash'!X11*'Model inputs'!AJ45/12 -> 14583.333 | Y13: ='Haq — Monthly P&L and cash'!Y11*'Model inputs'!AJ45/12 -> 16666.667
A14: Haq CSR revenue | B14: ='Haq — Monthly P&L and cash'!B11*'Model inputs'!AJ44/12 -> 0 | C14: ='Haq — Monthly P&L and cash'!C11*'Model inputs'!AJ44/12 -> 0 | D14: ='Haq — Monthly P&L and cash'!D11*'Model inputs'!AJ44/12 -> 0 | E14: ='Haq — Monthly P&L and cash'!E11*'Model inputs'!AJ44/12 -> 0 | F14: ='Haq — Monthly P&L and cash'!F11*'Model inputs'!AJ44/12 -> 0 | G14: ='Haq — Monthly P&L and cash'!G11*'Model inputs'!AJ44/12 -> 41666.667 | H14: ='Haq — Monthly P&L and cash'!H11*'Model inputs'!AJ44/12 -> 41666.667 | I14: ='Haq — Monthly P&L and cash'!I11*'Model inputs'!AJ44/12 -> 41666.667 | J14: ='Haq — Monthly P&L and cash'!J11*'Model inputs'!AJ44/12 -> 83333.333 | K14: ='Haq — Monthly P&L and cash'!K11*'Model inputs'!AJ44/12 -> 83333.333 | L14: ='Haq — Monthly P&L and cash'!L11*'Model inputs'!AJ44/12 -> 83333.333 | M14: ='Haq — Monthly P&L and cash'!M11*'Model inputs'!AJ44/12 -> 125000 | N14: ='Haq — Monthly P&L and cash'!N11*'Model inputs'!AJ44/12 -> 125000 | O14: ='Haq — Monthly P&L and cash'!O11*'Model inputs'!AJ44/12 -> 125000 | P14: ='Haq — Monthly P&L and cash'!P11*'Model inputs'!AJ44/12 -> 166666.67 | Q14: ='Haq — Monthly P&L and cash'!Q11*'Model inputs'!AJ44/12 -> 166666.67 | R14: ='Haq — Monthly P&L and cash'!R11*'Model inputs'!AJ44/12 -> 166666.67 | S14: ='Haq — Monthly P&L and cash'!S11*'Model inputs'!AJ44/12 -> 208333.33 | T14: ='Haq — Monthly P&L and cash'!T11*'Model inputs'!AJ44/12 -> 208333.33 | U14: ='Haq — Monthly P&L and cash'!U11*'Model inputs'!AJ44/12 -> 208333.33 | V14: ='Haq — Monthly P&L and cash'!V11*'Model inputs'!AJ44/12 -> 250000 | W14: ='Haq — Monthly P&L and cash'!W11*'Model inputs'!AJ44/12 -> 250000 | X14: ='Haq — Monthly P&L and cash'!X11*'Model inputs'!AJ44/12 -> 291666.67 | Y14: ='Haq — Monthly P&L and cash'!Y11*'Model inputs'!AJ44/12 -> 333333.33
A15: Haq CSR receipts | B15: ='Haq — Monthly P&L and cash'!B12*'Model inputs'!AJ44+0*'Model inputs'!AJ33 -> 0 | C15: ='Haq — Monthly P&L and cash'!C12*'Model inputs'!AJ44+0*'Model inputs'!AJ33 -> 0 | D15: ='Haq — Monthly P&L and cash'!D12*'Model inputs'!AJ44+'Model inputs'!AB19*'Model inputs'!AJ33 -> 0 | E15: ='Haq — Monthly P&L and cash'!E12*'Model inputs'!AJ44+'Model inputs'!AC19*'Model inputs'!AJ33 -> 0 | F15: ='Haq — Monthly P&L and cash'!F12*'Model inputs'!AJ44+'Model inputs'!AD19*'Model inputs'!AJ33 -> 0 | G15: ='Haq — Monthly P&L and cash'!G12*'Model inputs'!AJ44+'Model inputs'!AE19*'Model inputs'!AJ33 -> 500000 | H15: ='Haq — Monthly P&L and cash'!H12*'Model inputs'!AJ44+'Model inputs'!AF19*'Model inputs'!AJ33 -> 0 | I15: ='Haq — Monthly P&L and cash'!I12*'Model inputs'!AJ44+'Model inputs'!AG19*'Model inputs'!AJ33 -> 0 | J15: ='Haq — Monthly P&L and cash'!J12*'Model inputs'!AJ44+'Model inputs'!AH19*'Model inputs'!AJ33 -> 500000 | K15: ='Haq — Monthly P&L and cash'!K12*'Model inputs'!AJ44+'Model inputs'!AI19*'Model inputs'!AJ33 -> 0 | L15: ='Haq — Monthly P&L and cash'!L12*'Model inputs'!AJ44+'Model inputs'!B19*'Model inputs'!AJ33 -> 0 | M15: ='Haq — Monthly P&L and cash'!M12*'Model inputs'!AJ44+'Model inputs'!C19*'Model inputs'!AJ33 -> 500000 | N15: ='Haq — Monthly P&L and cash'!N12*'Model inputs'!AJ44+'Haq — Monthly P&L and cash'!B15*'Model inputs'!AJ33 -> 0 | O15: ='Haq — Monthly P&L and cash'!O12*'Model inputs'!AJ44+'Haq — Monthly P&L and cash'!C15*'Model inputs'!AJ33 -> 0 | P15: ='Haq — Monthly P&L and cash'!P12*'Model inputs'!AJ44+'Haq — Monthly P&L and cash'!D15*'Model inputs'!AJ33 -> 500000 | Q15: ='Haq — Monthly P&L and cash'!Q12*'Model inputs'!AJ44+'Haq — Monthly P&L and cash'!E15*'Model inputs'!AJ33 -> 0 | R15: ='Haq — Monthly P&L and cash'!R12*'Model inputs'!AJ44+'Haq — Monthly P&L and cash'!F15*'Model inputs'!AJ33 -> 0 | S15: ='Haq — Monthly P&L and cash'!S12*'Model inputs'!AJ44+'Haq — Monthly P&L and cash'!G15*'Model inputs'!AJ33 -> 1000000 | T15: ='Haq — Monthly P&L and cash'!T12*'Model inputs'!AJ44+'Haq — Monthly P&L and cash'!H15*'Model inputs'!AJ33 -> 0 | U15: ='Haq — Monthly P&L and cash'!U12*'Model inputs'!AJ44+'Haq — Monthly P&L and cash'!I15*'Model inputs'!AJ33 -> 0 | V15: ='Haq — Monthly P&L and cash'!V12*'Model inputs'!AJ44+'Haq — Monthly P&L and cash'!J15*'Model inputs'!AJ33 -> 1000000 | W15: ='Haq — Monthly P&L and cash'!W12*'Model inputs'!AJ44+'Haq — Monthly P&L and cash'!K15*'Model inputs'!AJ33 -> 0 | X15: ='Haq — Monthly P&L and cash'!X12*'Model inputs'!AJ44+'Haq — Monthly P&L and cash'!L15*'Model inputs'!AJ33 -> 500000 | Y15: ='Haq — Monthly P&L and cash'!Y12*'Model inputs'!AJ44+'Haq — Monthly P&L and cash'!M15*'Model inputs'!AJ33 -> 1000000
